Workbook
Name AP71AJ72: 'Greenfield — Em Cobrança'!$AP$71

Sheet 🔧 Painel
A1: V&F | Sistema Seguro Garantia — Painel de Controle
A2: =TODAY() -> 46112
A4: INDICADORES
A5: BASE TOTAL | D5: PIPELINE ATIVO | G5: FOLLOW-UPS ATRASADOS
A6: =Dashboard!B5 -> 6693 | B6: empresas | D6: =Dashboard!C5 -> 1 | E6: oportunidades | G6: =COUNTIF('Greenfield — Em Cobrança'!AB4:AB6696,"*Atrasado*") -> 1 | H6: urgentes
A7: =Dashboard!B6 -> 47710321310 | B7: valor total | D7: =Dashboard!C6 -> 75813202 | E7: em pipeline | G7: ligar HOJE | H7: → ver Worklist
A9: PROPOSTAS ENVIADAS | D9: EMISSÕES (WON) | G9: CONSULTAS PENDENTES
A10: =Dashboard!E5 -> 0 | B10: propostas | D10: =Dashboard!F5 -> 0 | E10: =Dashboard!F6 -> 0 | G10: =COUNTIF('Greenfield — Em Cobrança'!S4:S6696,"")-COUNTIF('Greenfield — Em Cobrança'!W4:W6696,"") -> -6 | H10: s/ consulta
A11: =Dashboard!E6 -> 0 | B11: valor propostas | D11: convertidos ✅ | E11: =IF(Dashboard!B5=0,"-",TEXT(Dashboard!F5/Dashboard!B5,"0.0%")) -> 0,0% | G11: no pipeline, consultar Cia
A13: TOP 10 OPORTUNIDADES POR PRÊMIO ESTIMADO
A14: Empresa | B14: Valor Aberto (R$) | D14: Prêmio Estim. (R$) | E14: Estágio
A15: {=IFERROR(_xlws.SORT(_xlws.FILTER(HSTACK('Greenfield — Em Cobrança'!B4:B6696,'Greenfield — Em Cobrança'!H4:H6696,'Greenfield — Em Cobrança'!AC4:AC6696,'Greenfield — Em Cobrança'!AD4:AD6696,'Greenfield — Em Cobrança'!W4:W6696),'Greenfield — Em Cobrança'!AD4:AD6696>0),4,-1),"Nenhum prêmio estimado ainda — preencha a Taxa Estim. (%) na Greenfield")} -> Nenhum prêmio estimado ainda — preencha a Taxa Estim. (%) na Greenfield

Sheet Dashboard
A1: V&F | Dashboard — Pipeline Seguro Garantia
A2: Atualizado automaticamente | Base: 6.693 empresas Greenfield
A4: KPI | B4: Total Prospects | C4: Pipeline Ativo | D4: Consultas em Andamento | E4: Propostas Enviadas | F4: Emissões (Won) | G4: Perdidos | H4: Taxa Conversão
A5: Quantidade | B5: =COUNTA('Greenfield — Em Cobrança'!B4:B6696) -> 6693 | C5: =COUNTIFS('Greenfield — Em Cobrança'!W4:W6696,"<>",'Greenfield — Em Cobrança'!W4:W6696,"<>🗑️ Descarte",'Greenfield — Em Cobrança'!W4:W6696,"<>❌ Perdido") -> 1 | D5: =COUNTIF('Greenfield — Em Cobrança'!W4:W6696,"📞 Consulta Cia") -> 0 | E5: =COUNTIF('Greenfield — Em Cobrança'!W4:W6696,"📋 Proposta Enviada") -> 0 | F5: =COUNTIF('Greenfield — Em Cobrança'!W4:W6696,"✅ Emissão") -> 0 | G5: =COUNTIF('Greenfield — Em Cobrança'!W4:W6696,"❌ Perdido") -> 0 | H5: =IF(B5=0,"-",F5/B5) -> 0
A6: Valor (R$) | B6: =SUM('Greenfield — Em Cobrança'!H4:H6696) -> 47710321310 | C6: {=SUMPRODUCT(('Greenfield — Em Cobrança'!W4:W6696<>"")*('Greenfield — Em Cobrança'!W4:W6696<>"🗑️ Descarte")*('Greenfield — Em Cobrança'!W4:W6696<>"❌ Perdido")*'Greenfield — Em Cobrança'!H4:H6696)} -> 75813202 | D6: =SUMIF('Greenfield — Em Cobrança'!W4:W6696,"📞 Consulta Cia",'Greenfield — Em Cobrança'!H4:H6696) -> 0 | E6: =SUMIF('Greenfield — Em Cobrança'!W4:W6696,"📋 Proposta Enviada",'Greenfield — Em Cobrança'!H4:H6696) -> 0 | F6: =SUMIF('Greenfield — Em Cobrança'!W4:W6696,"✅ Emissão",'Greenfield — Em Cobrança'!H4:H6696) -> 0 | G6: =SUMIF('Greenfield — Em Cobrança'!W4:W6696,"❌ Perdido",'Greenfield — Em Cobrança'!H4:H6696) -> 0 | H6: =IF(B6=0,"-",F6/B6) -> 0
A8: 📈 FUNIL POR ESTÁGIO | E8: 📅 FOLLOW-UP STATUS
A9: Estágio | B9: Qtd Empresas | C9: Valor Pipeline (R$) | E9: Status | F9: Qtd | G9: % do Total
A10: (Sem estágio) | B10: =COUNTIF('Greenfield — Em Cobrança'!W4:W6696,"") -> 6692 | C10: =SUMIF('Greenfield — Em Cobrança'!W4:W6696,"",'Greenfield — Em Cobrança'!H4:H6696) -> 47634508108 | E10: 🟢 Em dia | F10: =COUNTIF('Greenfield — Em Cobrança'!AB4:AB6696,"*Em dia*") -> 0 | G10: =IF(SUM(G10:G13)=0,"-",F10/SUM(F10:F13)) -> #REF!
A11: 🆕 Novo | B11: =COUNTIF('Greenfield — Em Cobrança'!W4:W6696,"🆕 Novo") -> 1 | C11: =SUMIF('Greenfield — Em Cobrança'!W4:W6696,"🆕 Novo",'Greenfield — Em Cobrança'!H4:H6696) -> 75813202 | E11: 🟡 Atenção | F11: =COUNTIF('Greenfield — Em Cobrança'!AB4:AB6696,"*Atenção*") -> 0 | G11: =IF(SUM(G10:G13)=0,"-",F11/SUM(F10:F13)) -> #REF!
A12: 📞 Consulta Cia | B12: =COUNTIF('Greenfield — Em Cobrança'!W4:W6696,"📞 Consulta Cia") -> 0 | C12: =SUMIF('Greenfield — Em Cobrança'!W4:W6696,"📞 Consulta Cia",'Greenfield — Em Cobrança'!H4:H6696) -> 0 | E12: 🔴 Atrasado | F12: =COUNTIF('Greenfield — Em Cobrança'!AB4:AB6696,"*Atrasado*") -> 1 | G12: =IF(SUM(G10:G13)=0,"-",F12/SUM(F10:F13)) -> #REF!
A13: 📋 Proposta Enviada | B13: =COUNTIF('Greenfield — Em Cobrança'!W4:W6696,"📋 Proposta Enviada") -> 0 | C13: =SUMIF('Greenfield — Em Cobrança'!W4:W6696,"📋 Proposta Enviada",'Greenfield — Em Cobrança'!H4:H6696) -> 0 | E13: Sem contato | F13: =COUNTIF('Greenfield — Em Cobrança'!AB4:AB6696,"") -> 6692 | G13: =IF(SUM(G10:G13)=0,"-",F13/SUM(F10:F13)) -> #REF!
A14: 🤝 Negociação | B14: =COUNTIF('Greenfield — Em Cobrança'!W4:W6696,"🤝 Negociação") -> 0 | C14: =SUMIF('Greenfield — Em Cobrança'!W4:W6696,"🤝 Negociação",'Greenfield — Em Cobrança'!H4:H6696) -> 0
A15: ✅ Emissão | B15: =COUNTIF('Greenfield — Em Cobrança'!W4:W6696,"✅ Emissão") -> 0 | C15: =SUMIF('Greenfield — Em Cobrança'!W4:W6696,"✅ Emissão",'Greenfield — Em Cobrança'!H4:H6696) -> 0
A16: ❌ Perdido | B16: =COUNTIF('Greenfield — Em Cobrança'!W4:W6696,"❌ Perdido") -> 0 | C16: =SUMIF('Greenfield — Em Cobrança'!W4:W6696,"❌ Perdido",'Greenfield — Em Cobrança'!H4:H6696) -> 0
A17: 🗑️ Descarte | B17: =COUNTIF('Greenfield — Em Cobrança'!W4:W6696,"🗑️ Descarte") -> 0 | C17: =SUMIF('Greenfield — Em Cobrança'!W4:W6696,"🗑️ Descarte",'Greenfield — Em Cobrança'!H4:H6696) -> 0
A19: 🏦 RESULTADO SEGURADORA | E19: 💰 PRÊMIO & RECEITA ESTIMADA
A20: Situação Cia | B20: Qtd | C20: Valor (R$) | E20: Métrica | F20: Valor | G20: Obs.
A21: Cadastrou (✅) | B21: =COUNTIF('Greenfield — Em Cobrança'!S4:S6696,"Cadastrou") -> 1 | C21: =SUMIF('Greenfield — Em Cobrança'!S4:S6696,"Cadastrou",'Greenfield — Em Cobrança'!H4:H6696) -> 75813202 | E21: Prêmio Total Estimado (R$) | F21: =SUMIF('Greenfield — Em Cobrança'!AC4:AC6696,">0",'Greenfield — Em Cobrança'!AD4:AD6696) -> 265346.21 | G21: Soma de todos com taxa preenchida
A22: Fora da Política | B22: =COUNTIF('Greenfield — Em Cobrança'!S4:S6696,"Fora da Política") -> 0 | C22: =SUMIF('Greenfield — Em Cobrança'!S4:S6696,"Fora da Política",'Greenfield — Em Cobrança'!H4:H6696) -> 0 | E22: Prêmio Médio por Apólice (R$) | F22: =IF(COUNTIF('Greenfield — Em Cobrança'!AC4:AC6696,">0")=0,"-",F21/COUNTIF('Greenfield — Em Cobrança'!AC4:AC6696,">0")) -> 265346.21 | G22: Média
A23: SERASA | B23: =COUNTIF('Greenfield — Em Cobrança'!S4:S6696,"SERASA") -> 0 | C23: =SUMIF('Greenfield — Em Cobrança'!S4:S6696,"SERASA",'Greenfield — Em Cobrança'!H4:H6696) -> 0 | E23: Qtd com Taxa Preenchida | F23: =COUNTIF('Greenfield — Em Cobrança'!AC4:AC6696,">0") -> 1 | G23: Empresas cotadas
A24: Outro Corretor | B24: =COUNTIF('Greenfield — Em Cobrança'!S4:S6696,"Outro Corretor") -> 0 | C24: =SUMIF('Greenfield — Em Cobrança'!S4:S6696,"Outro Corretor",'Greenfield — Em Cobrança'!H4:H6696) -> 0 | E24: Valor IS Coberto (R$) | F24: =SUMIF('Greenfield — Em Cobrança'!S4:S6696,"Cadastrou",'Greenfield — Em Cobrança'!H4:H6696) -> 75813202 | G24: Valor com seguro aprovado
A25: Inapta/Baixada | B25: =COUNTIF('Greenfield — Em Cobrança'!S4:S6696,"Inapta/Baixada") -> 6 | C25: =SUMIF('Greenfield — Em Cobrança'!S4:S6696,"Inapta/Baixada",'Greenfield — Em Cobrança'!H4:H6696) -> 3.0646608e+08 | E25: Receita V&F Potencial (5a) | F25: =SUM('Greenfield — Em Cobrança'!AI4:AI6696) -> 5.3628624e+08 | G25: Base total × Taxa × 5a × 30%
A26: Pendente consulta | B26: =COUNTIF('Greenfield — Em Cobrança'!S4:S6696,"") -> 6686 | C26: =SUMIF('Greenfield — Em Cobrança'!S4:S6696,"",'Greenfield — Em Cobrança'!H4:H6696) -> 47328042026 | E26: Prêmio Total Apólices (5a) | F26: =SUM('Greenfield — Em Cobrança'!AH4:AH6696) -> 1787620785 | G26: Mercado total endereçável
A28: 🎯 PIPELINE POR PRIORIDADE
A29: Prioridade | B29: Qtd Total | C29: Em Pipeline | D29: Valor Pipeline (R$)
A30: 🔴 ALTA | B30: =COUNTIF('Greenfield — Em Cobrança'!F4:F6696,"*ALTA*") -> 1993 | C30: =COUNTIFS('Greenfield — Em Cobrança'!F4:F6696,"*ALTA*",'Greenfield — Em Cobrança'!W4:W6696,"<>",'Greenfield — Em Cobrança'!W4:W6696,"<>🗑️ Descarte",'Greenfield — Em Cobrança'!W4:W6696,"<>❌ Perdido") -> 1 | D30: {=SUMPRODUCT(ISNUMBER(SEARCH("ALTA",'Greenfield — Em Cobrança'!F4:F6696))*('Greenfield — Em Cobrança'!W4:W6696<>"")*('Greenfield — Em Cobrança'!W4:W6696<>"🗑️ Descarte")*('Greenfield — Em Cobrança'!W4:W6696<>"❌ Perdido")*'Greenfield — Em Cobrança'!H4:H6696)} -> 75813202
A31: 🟡 MÉDIA | B31: =COUNTIF('Greenfield — Em Cobrança'!F4:F6696,"*MÉDIA*") -> 2069 | C31: =COUNTIFS('Greenfield — Em Cobrança'!F4:F6696,"*MÉDIA*",'Greenfield — Em Cobrança'!W4:W6696,"<>",'Greenfield — Em Cobrança'!W4:W6696,"<>🗑️ Descarte",'Greenfield — Em Cobrança'!W4:W6696,"<>❌ Perdido") -> 0 | D31: {=SUMPRODUCT(ISNUMBER(SEARCH("MÉDIA",'Greenfield — Em Cobrança'!F4:F6696))*('Greenfield — Em Cobrança'!W4:W6696<>"")*('Greenfield — Em Cobrança'!W4:W6696<>"🗑️ Descarte")*('Greenfield — Em Cobrança'!W4:W6696<>"❌ Perdido")*'Greenfield — Em Cobrança'!H4:H6696)} -> 0
A32: ⚪ NORMAL | B32: =COUNTIF('Greenfield — Em Cobrança'!F4:F6696,"*NORMAL*") -> 2631 | C32: =COUNTIFS('Greenfield — Em Cobrança'!F4:F6696,"*NORMAL*",'Greenfield — Em Cobrança'!W4:W6696,"<>",'Greenfield — Em Cobrança'!W4:W6696,"<>🗑️ Descarte",'Greenfield — Em Cobrança'!W4:W6696,"<>❌ Perdido") -> 0 | D32: {=SUMPRODUCT(ISNUMBER(SEARCH("NORMAL",'Greenfield — Em Cobrança'!F4:F6696))*('Greenfield — Em Cobrança'!W4:W6696<>"")*('Greenfield — Em Cobrança'!W4:W6696<>"🗑️ Descarte")*('Greenfield — Em Cobrança'!W4:W6696<>"❌ Perdido")*'Greenfield — Em Cobrança'!H4:H6696)} -> 0
A33: TOTAL | B33: =SUM(B30:B32) -> 6693 | C33: =SUM(C30:C32) -> 1 | D33: =SUM(D30:D32) -> 75813202

Sheet Greenfield — Em Cobrança
A1: V&F | Seguro Garantia — Greenfield: Inscrições Ajuizadas sem Garantia (R$1M–R$50M | 2021–2025) | BA1: Situação | BB1: Col1_Default | BC1: Col2_Default | BD1: Col3_Default
A2: Base: 6,693 empresas | 1993 ALTA | 2069 MÉDIA | 2631 NORMAL • Apenas PRINCIPAL • Sem falidos/RJ • CNPJ Raiz | S2: ✏️ = campo editável | 🔒 = protegido (fórmula ou dado-fonte) | BA2: Cadastrou | BB2: — | BC2: — | BD2: ✅ Aprovado
A3: # | B3: Empresa | C3: UF | D3: CNPJ Raiz | E3: Score | F3: Prioridade | G3: Faixa Valor | H3: Valor Aberto (R$) | I3: Qtd. Inscrições | J3: Anos na PGFN | K3: Ano Últ. Inscrição | L3: Receita Principal | M3: Ano Entrada PGFN | N3: Situações Presentes | O3: Base12 | P3: DV1 | Q3: DV2 | R3: CNPJ Completo | S3: ✏️ Situação Cia | T3: ✏️ Limite / Status | U3: ✏️ Taxa / Motivo | V3: Resultado / Ação | W3: ✏️ Estágio Pipeline | X3: ✏️ Responsável V&F | Y3: ✏️ Dt. Último Contato | Z3: ✏️ Próx. Follow-up | AA3: Dias s/ Contato | AB3: Status Follow-up | AC3: ✏️ Taxa Real (%) | AD3: Prêmio Estim. (R$) | AE3: ✏️ Observações | AF3: Taxa Aplicada | AG3: Prêmio Anual (R$) | AH3: AI3 | AI3: Receita V&F 30% (R$) | AJ3: ✏️ Capital Social (R$) | AK3: ✏️ Porte | AL3: ✏️ Simples Nacional | AM3: ✏️ Telefone | AN3: ✏️ E-mail | AO3: ✏️ Contato (Nome) | AP3: ✏️ Contato (Cargo) | AQ3: ✏️ Contato (Celular) | BA3: Fora da Política | BC3: Regra da Cia | BD3: Refazer 2ª Cia
A4: 1 | B4: MANTOVANI INTERNATIONAL TRADING S.A. | C4: SP | D4: 40008207 | E4: 70.37 | F4: 🔴 ALTA | G4: R$ 50M+ | H4: 75813202 | I4: 2 | J4: 0.7 | K4: 2025 | L4: Receita da dívida ativa - CSLL | Receita da dívida ativa - IRPJ | M4: 2025 | N4: COBRANCA | O4: =TEXT(D4,"00000000")&"0001" -> 400082070001 | P4: =IF(MOD(MID(O4,1,1)*5+MID(O4,2,1)*4+MID(O4,3,1)*3+MID(O4,4,1)*2+MID(O4,5,1)*9+MID(O4,6,1)*8+MID(O4,7,1)*7+MID(O4,8,1)*6+MID(O4,9,1)*5+MID(O4,10,1)*4+MID(O4,11,1)*3+MID(O4,12,1)*2,11)<2,0,11-MOD(MID(O4,1,1)*5+MID(O4,2,1)*4+MID(O4,3,1)*3+MID(O4,4,1)*2+MID(O4,5,1)*9+MID(O4,6,1)*8+MID(O4,7,1)*7+MID(O4,8,1)*6+MID(O4,9,1)*5+MID(O4,10,1)*4+MID(O4,11,1)*3+MID(O4,12,1)*2,11)) -> 2 | Q4: =IF(MOD(MID(O4,1,1)*6+MID(O4,2,1)*5+MID(O4,3,1)*4+MID(O4,4,1)*3+MID(O4,5,1)*2+MID(O4,6,1)*9+MID(O4,7,1)*8+MID(O4,8,1)*7+MID(O4,9,1)*6+MID(O4,10,1)*5+MID(O4,11,1)*4+MID(O4,12,1)*3+P4*2,11)<2,0,11-MOD(MID(O4,1,1)*6+MID(O4,2,1)*5+MID(O4,3,1)*4+MID(O4,4,1)*3+MID(O4,5,1)*2+MID(O4,6,1)*9+MID(O4,7,1)*8+MID(O4,8,1)*7+MID(O4,9,1)*6+MID(O4,10,1)*5+MID(O4,11,1)*4+MID(O4,12,1)*3+P4*2,11)) -> 7 | R4: =MID(O4,1,2)&"."&MID(O4,3,3)&"."&MID(O4,6,3)&"/"&MID(O4,9,4)&"-"&TEXT(P4,"0")&TEXT(Q4,"0") -> 40.008.207/0001-27 | S4: Cadastrou | T4: 100000000 | U4: 0.35 | V4: =IF(S4="","",XLOOKUP(S4,$BA$2:$BA$6,$BD$2:$BD$6,"")) -> ✅ Aprovado | W4: 🆕 Novo | X4: Rodrigo Vazquez | Y4: 46106 | Z4: 46107 | AA4: =IF(Y4="","",IF(INT(TODAY()-Y4)<0,"⚠️ Data futura",INT(TODAY()-Y4))) -> 6 | AB4: =IF(AA4="","",IF(Z4="",IF(AA4>14,"🔴 Atrasado",IF(AA4>7,"🟡 Atenção","🟢 Em dia")),IF(TODAY()>Z4,"🔴 Atrasado",IF(Z4-TODAY()<=3,"🟡 Atenção","🟢 Em dia")))) -> 🔴 Atrasado | AC4: 0.0035 | AD4: =IF(OR(AC4="",H4=""),"",H4*AC4) -> 265346.21 | AE4: Falta CCG | AF4: =IF(AC4>0,AC4,'⚙️ Config'!$B$10) -> 0.0035 | AG4: =H4*AF4 -> 265346.21 | AH4: =AG4*'⚙️ Config'!$B$11 -> 1326731 | AI4: =AH4*'⚙️ Config'!$B$12 -> 398019.31 | AJ4: 150000000 | AK4: Grande | AL4: Não | AM4: 11 4758-2949 | AN4: karinamantovani@gmail.com | BA4: SERASA | BC4: SERASA | BD4: Análise Manual
A5: 2 | B5: MEAT & LEATHER INDUSTRIA E COMERCIO DE ALIMENTOS LTDA | C5: MS | D5: 30735239 | E5: 58.37 | F5: 🔴 ALTA | G5: R$ 50M+ | H5: 63544701 | I5: 2 | J5: 1 | K5: 2025 | L5: Receita da dívida ativa - CSLL | Receita da dívida ativa - IRPJ | M5: 2025 | N5: COBRANCA | O5: =TEXT(D5,"00000000")&"0001" -> 307352390001 | P5: =IF(MOD(MID(O5,1,1)*5+MID(O5,2,1)*4+MID(O5,3,1)*3+MID(O5,4,1)*2+MID(O5,5,1)*9+MID(O5,6,1)*8+MID(O5,7,1)*7+MID(O5,8,1)*6+MID(O5,9,1)*5+MID(O5,10,1)*4+MID(O5,11,1)*3+MID(O5,12,1)*2,11)<2,0,11-MOD(MID(O5,1,1)*5+MID(O5,2,1)*4+MID(O5,3,1)*3+MID(O5,4,1)*2+MID(O5,5,1)*9+MID(O5,6,1)*8+MID(O5,7,1)*7+MID(O5,8,1)*6+MID(O5,9,1)*5+MID(O5,10,1)*4+MID(O5,11,1)*3+MID(O5,12,1)*2,11)) -> 7 | Q5: =IF(MOD(MID(O5,1,1)*6+MID(O5,2,1)*5+MID(O5,3,1)*4+MID(O5,4,1)*3+MID(O5,5,1)*2+MID(O5,6,1)*9+MID(O5,7,1)*8+MID(O5,8,1)*7+MID(O5,9,1)*6+MID(O5,10,1)*5+MID(O5,11,1)*4+MID(O5,12,1)*3+P5*2,11)<2,0,11-MOD(MID(O5,1,1)*6+MID(O5,2,1)*5+MID(O5,3,1)*4+MID(O5,4,1)*3+MID(O5,5,1)*2+MID(O5,6,1)*9+MID(O5,7,1)*8+MID(O5,8,1)*7+MID(O5,9,1)*6+MID(O5,10,1)*5+MID(O5,11,1)*4+MID(O5,12,1)*3+P5*2,11)) -> 0 | R5: =MID(O5,1,2)&"."&MID(O5,3,3)&"."&MID(O5,6,3)&"/"&MID(O5,9,4)&"-"&TEXT(P5,"0")&TEXT(Q5,"0") -> 30.735.239/0001-70 | S5: Inapta/Baixada | T5: =IF(S5="","",IF(S5="Cadastrou","",XLOOKUP(S5,$BA$2:$BA$6,$BB$2:$BB$6,""))) | U5: =IF(S5="","",IF(S5="Cadastrou","",XLOOKUP(S5,$BA$2:$BA$6,$BC$2:$BC$6,""))) | V5: =IF(S5="","",XLOOKUP(S5,$BA$2:$BA$6,$BD$2:$BD$6,"")) | AA5: =IF(Y5="","",IF(INT(TODAY()-Y5)<0,"⚠️ Data futura",INT(TODAY()-Y5))) | AB5: =IF(AA5="","",IF(Z5="",IF(AA5>14,"🔴 Atrasado",IF(AA5>7,"🟡 Atenção","🟢 Em dia")),IF(TODAY()>Z5,"🔴 Atrasado",IF(Z5-TODAY()<=3,"🟡 Atenção","🟢 Em dia")))) | AD5: =IF(OR(AC5="",H5=""),"",H5*AC5) | AF5: =IF(AC5>0,AC5,'⚙️ Config'!$B$10) -> 0.0075 | AG5: =H5*AF5 -> 476585.26 | AH5: =AG5*'⚙️ Config'!$B$11 -> 2382926.3 | AI5: =AH5*'⚙️ Config'!$B$12 -> 714877.89 | BA5: Outro Corretor | BC5: Análise | BD5: Ana
A6: 3 | B6: HMAR CONSULTORIA EM INFORMATICA LTDA | C6: SP | D6: 09182880 | E6: 67.34 | F6: 🔴 ALTA | G6: R$ 50M+ | H6: 58517893 | I6: 2 | J6: 0.8 | K6: 2025 | L6: Receita da dívida ativa - IOF | Receita da dívida ativa - IRRF | M6: 2025 | N6: AJUIZADA_SEM_GAR | O6: =TEXT(D6,"00000000")&"0001" -> 091828800001 | P6: =IF(MOD(MID(O6,1,1)*5+MID(O6,2,1)*4+MID(O6,3,1)*3+MID(O6,4,1)*2+MID(O6,5,1)*9+MID(O6,6,1)*8+MID(O6,7,1)*7+MID(O6,8,1)*6+MID(O6,9,1)*5+MID(O6,10,1)*4+MID(O6,11,1)*3+MID(O6,12,1)*2,11)<2,0,11-MOD(MID(O6,1,1)*5+MID(O6,2,1)*4+MID(O6,3,1)*3+MID(O6,4,1)*2+MID(O6,5,1)*9+MID(O6,6,1)*8+MID(O6,7,1)*7+MID(O6,8,1)*6+MID(O6,9,1)*5+MID(O6,10,1)*4+MID(O6,11,1)*3+MID(O6,12,1)*2,11)) -> 3 | Q6: =IF(MOD(MID(O6,1,1)*6+MID(O6,2,1)*5+MID(O6,3,1)*4+MID(O6,4,1)*3+MID(O6,5,1)*2+MID(O6,6,1)*9+MID(O6,7,1)*8+MID(O6,8,1)*7+MID(O6,9,1)*6+MID(O6,10,1)*5+MID(O6,11,1)*4+MID(O6,12,1)*3+P6*2,11)<2,0,11-MOD(MID(O6,1,1)*6+MID(O6,2,1)*5+MID(O6,3,1)*4+MID(O6,4,1)*3+MID(O6,5,1)*2+MID(O6,6,1)*9+MID(O6,7,1)*8+MID(O6,8,1)*7+MID(O6,9,1)*6+MID(O6,10,1)*5+MID(O6,11,1)*4+MID(O6,12,1)*3+P6*2,11)) -> 9 | R6: =MID(O6,1,2)&"."&MID(O6,3,3)&"."&MID(O6,6,3)&"/"&MID(O6,9,4)&"-"&TEXT(P6,"0")&TEXT(Q6,"0") -> 09.182.880/0001-39 | S6: Inapta/Baixada | T6: =IF(S6="","",IF(S6="Cadastrou","",XLOOKUP(S6,$BA$2:$BA$6,$BB$2:$BB$6,""))) | U6: =IF(S6="","",IF(S6="Cadastrou","",XLOOKUP(S6,$BA$2:$BA$6,$BC$2:$BC$6,""))) | V6: =IF(S6="","",XLOOKUP(S6,$BA$2:$BA$6,$BD$2:$BD$6,"")) | AA6: =IF(Y6="","",IF(INT(TODAY()-Y6)<0,"⚠️ Data futura",INT(TODAY()-Y6))) | AB6: =IF(AA6="","",IF(Z6="",IF(AA6>14,"🔴 Atrasado",IF(AA6>7,"🟡 Atenção","🟢 Em dia")),IF(TODAY()>Z6,"🔴 Atrasado",IF(Z6-TODAY()<=3,"🟡 Atenção","🟢 Em dia")))) | AD6: =IF(OR(AC6="",H6=""),"",H6*AC6) | AF6: =IF(AC6>0,AC6,'⚙️ Config'!$B$10) -> 0.0075 | AG6: =H6*AF6 -> 438884.2 | AH6: =AG6*'⚙️ Config'!$B$11 -> 2194421 | AI6: =AH6*'⚙️ Config'!$B$12 -> 658326.3 | BC6: Descarte | BD6: Descarte
A7: 4 | B7: MUNICIPIO DE CACHOEIRA PAULISTA | C7: SP | D7: 45192275 | E7: 59.53 | F7: 🔴 ALTA | G7: R$ 50M+ | H7: 53460614 | I7: 2 | J7: 1 | K7: 2025 | L7: R D Ativa -Multa Isolada Compensação Previdenciária Indevida | R D Ativa - Glosa de Compensação Previdenciária | M7: 2025 | N7: AJUIZADA_SEM_GAR | O7: =TEXT(D7,"00000000")&"0001" -> 451922750001 | P7: =IF(MOD(MID(O7,1,1)*5+MID(O7,2,1)*4+MID(O7,3,1)*3+MID(O7,4,1)*2+MID(O7,5,1)*9+MID(O7,6,1)*8+MID(O7,7,1)*7+MID(O7,8,1)*6+MID(O7,9,1)*5+MID(O7,10,1)*4+MID(O7,11,1)*3+MID(O7,12,1)*2,11)<2,0,11-MOD(MID(O7,1,1)*5+MID(O7,2,1)*4+MID(O7,3,1)*3+MID(O7,4,1)*2+MID(O7,5,1)*9+MID(O7,6,1)*8+MID(O7,7,1)*7+MID(O7,8,1)*6+MID(O7,9,1)*5+MID(O7,10,1)*4+MID(O7,11,1)*3+MID(O7,12,1)*2,11)) -> 0 | Q7: =IF(MOD(MID(O7,1,1)*6+MID(O7,2,1)*5+MID(O7,3,1)*4+MID(O7,4,1)*3+MID(O7,5,1)*2+MID(O7,6,1)*9+MID(O7,7,1)*8+MID(O7,8,1)*7+MID(O7,9,1)*6+MID(O7,10,1)*5+MID(O7,11,1)*4+MID(O7,12,1)*3+P7*2,11)<2,0,11-MOD(MID(O7,1,1)*6+MID(O7,2,1)*5+MID(O7,3,1)*4+MID(O7,4,1)*3+MID(O7,5,1)*2+MID(O7,6,1)*9+MID(O7,7,1)*8+MID(O7,8,1)*7+MID(O7,9,1)*6+MID(O7,10,1)*5+MID(O7,11,1)*4+MID(O7,12,1)*3+P7*2,11)) -> 2 | R7: =MID(O7,1,2)&"."&MID(O7,3,3)&"."&MID(O7,6,3)&"/"&MID(O7,9,4)&"-"&TEXT(P7,"0")&TEXT(Q7,"0") -> 45.192.275/0001-02 | S7: Inapta/Baixada | T7: =IF(S7="","",IF(S7="Cadastrou","",XLOOKUP(S7,$BA$2:$BA$6,$BB$2:$BB$6,""))) | U7: =IF(S7="","",IF(S7="Cadastrou","",XLOOKUP(S7,$BA$2:$BA$6,$BC$2:$BC$6,""))) | V7: =IF(S7="","",XLOOKUP(S7,$BA$2:$BA$6,$BD$2:$BD$6,"")) | AA7: =IF(Y7="","",IF(INT(TODAY()-Y7)<0,"⚠️ Data futura",INT(TODAY()-Y7))) | AB7: =IF(AA7="","",IF(Z7="",IF(AA7>14,"🔴 Atrasado",IF(AA7>7,"🟡 Atenção","🟢 Em dia")),IF(TODAY()>Z7,"🔴 Atrasado",IF(Z7-TODAY()<=3,"🟡 Atenção","🟢 Em dia")))) | AD7: =IF(OR(AC7="",H7=""),"",H7*AC7) | AF7: =IF(AC7>0,AC7,'⚙️ Config'!$B$10) -> 0.0075 | AG7: =H7*AF7 -> 400954.61 | AH7: =AG7*'⚙️ Config'!$B$11 -> 2004773 | AI7: =AH7*'⚙️ Config'!$B$12 -> 601431.91
A8: 5 | B8: COPAR CONDUTORES ELETRICOS LTDA | C8: SP | D8: 17344440 | E8: 41.86 | F8: 🔴 ALTA | G8: R$ 50M+ | H8: 52937645 | I8: 2 | J8: 1.8 | K8: 2024 | L8: Receita da dívida ativa - PIS | Receita da dívida ativa - CSLL | M8: 2024 | N8: COBRANCA | O8: =TEXT(D8,"00000000")&"0001" -> 173444400001 | P8: =IF(MOD(MID(O8,1,1)*5+MID(O8,2,1)*4+MID(O8,3,1)*3+MID(O8,4,1)*2+MID(O8,5,1)*9+MID(O8,6,1)*8+MID(O8,7,1)*7+MID(O8,8,1)*6+MID(O8,9,1)*5+MID(O8,10,1)*4+MID(O8,11,1)*3+MID(O8,12,1)*2,11)<2,0,11-MOD(MID(O8,1,1)*5+MID(O8,2,1)*4+MID(O8,3,1)*3+MID(O8,4,1)*2+MID(O8,5,1)*9+MID(O8,6,1)*8+MID(O8,7,1)*7+MID(O8,8,1)*6+MID(O8,9,1)*5+MID(O8,10,1)*4+MID(O8,11,1)*3+MID(O8,12,1)*2,11)) -> 6 | Q8: =IF(MOD(MID(O8,1,1)*6+MID(O8,2,1)*5+MID(O8,3,1)*4+MID(O8,4,1)*3+MID(O8,5,1)*2+MID(O8,6,1)*9+MID(O8,7,1)*8+MID(O8,8,1)*7+MID(O8,9,1)*6+MID(O8,10,1)*5+MID(O8,11,1)*4+MID(O8,12,1)*3+P8*2,11)<2,0,11-MOD(MID(O8,1,1)*6+MID(O8,2,1)*5+MID(O8,3,1)*4+MID(O8,4,1)*3+MID(O8,5,1)*2+MID(O8,6,1)*9+MID(O8,7,1)*8+MID(O8,8,1)*7+MID(O8,9,1)*6+MID(O8,10,1)*5+MID(O8,11,1)*4+MID(O8,12,1)*3+P8*2,11)) -> 9 | R8: =MID(O8,1,2)&"."&MID(O8,3,3)&"."&MID(O8,6,3)&"/"&MID(O8,9,4)&"-"&TEXT(P8,"0")&TEXT(Q8,"0") -> 17.344.440/0001-69 | S8: Inapta/Baixada | T8: =IF(S8="","",IF(S8="Cadastrou","",XLOOKUP(S8,$BA$2:$BA$6,$BB$2:$BB$6,""))) | U8: =IF(S8="","",IF(S8="Cadastrou","",XLOOKUP(S8,$BA$2:$BA$6,$BC$2:$BC$6,""))) | V8: =IF(S8="","",XLOOKUP(S8,$BA$2:$BA$6,$BD$2:$BD$6,"")) | AA8: =IF(Y8="","",IF(INT(TODAY()-Y8)<0,"⚠️ Data futura",INT(TODAY()-Y8))) | AB8: =IF(AA8="","",IF(Z8="",IF(AA8>14,"🔴 Atrasado",IF(AA8>7,"🟡 Atenção","🟢 Em dia")),IF(TODAY()>Z8,"🔴 Atrasado",IF(Z8-TODAY()<=3,"🟡 Atenção","🟢 Em dia")))) | AD8: =IF(OR(AC8="",H8=""),"",H8*AC8) | AF8: =IF(AC8>0,AC8,'⚙️ Config'!$B$10) -> 0.0075 | AG8: =H8*AF8 -> 397032.34 | AH8: =AG8*'⚙️ Config'!$B$11 -> 1985161.7 | AI8: =AH8*'⚙️ Config'!$B$12 -> 595548.51
A9: 6 | B9: ACO E ACO VERGALHOES LTDA | C9: MS | D9: 08345565 | E9: 65.23 | F9: 🔴 ALTA | G9: R$ 50M+ | H9: 51488054 | I9: 2 | J9: 0.8 | K9: 2025 | L9: Receita da dívida ativa - CSLL | Receita da dívida ativa - IRPJ | M9: 2025 | N9: AJUIZADA_SEM_GAR | O9: =TEXT(D9,"00000000")&"0001" -> 083455650001 | P9: =IF(MOD(MID(O9,1,1)*5+MID(O9,2,1)*4+MID(O9,3,1)*3+MID(O9,4,1)*2+MID(O9,5,1)*9+MID(O9,6,1)*8+MID(O9,7,1)*7+MID(O9,8,1)*6+MID(O9,9,1)*5+MID(O9,10,1)*4+MID(O9,11,1)*3+MID(O9,12,1)*2,11)<2,0,11-MOD(MID(O9,1,1)*5+MID(O9,2,1)*4+MID(O9,3,1)*3+MID(O9,4,1)*2+MID(O9,5,1)*9+MID(O9,6,1)*8+MID(O9,7,1)*7+MID(O9,8,1)*6+MID(O9,9,1)*5+MID(O9,10,1)*4+MID(O9,11,1)*3+MID(O9,12,1)*2,11)) -> 1 | Q9: =IF(MOD(MID(O9,1,1)*6+MID(O9,2,1)*5+MID(O9,3,1)*4+MID(O9,4,1)*3+MID(O9,5,1)*2+MID(O9,6,1)*9+MID(O9,7,1)*8+MID(O9,8,1)*7+MID(O9,9,1)*6+MID(O9,10,1)*5+MID(O9,11,1)*4+MID(O9,12,1)*3+P9*2,11)<2,0,11-MOD(MID(O9,1,1)*6+MID(O9,2,1)*5+MID(O9,3,1)*4+MID(O9,4,1)*3+MID(O9,5,1)*2+MID(O9,6,1)*9+MID(O9,7,1)*8+MID(O9,8,1)*7+MID(O9,9,1)*6+MID(O9,10,1)*5+MID(O9,11,1)*4+MID(O9,12,1)*3+P9*2,11)) -> 2 | R9: =MID(O9,1,2)&"."&MID(O9,3,3)&"."&MID(O9,6,3)&"/"&MID(O9,9,4)&"-"&TEXT(P9,"0")&TEXT(Q9,"0") -> 08.345.565/0001-12 | T9: =IF(S9="","",IF(S9="Cadastrou","",XLOOKUP(S9,$BA$2:$BA$6,$BB$2:$BB$6,""))) | U9: =IF(S9="","",IF(S9="Cadastrou","",XLOOKUP(S9,$BA$2:$BA$6,$BC$2:$BC$6,""))) | V9: =IF(S9="","",XLOOKUP(S9,$BA$2:$BA$6,$BD$2:$BD$6,"")) | AA9: =IF(Y9="","",IF(INT(TODAY()-Y9)<0,"⚠️ Data futura",INT(TODAY()-Y9))) | AB9: =IF(AA9="","",IF(Z9="",IF(AA9>14,"🔴 Atrasado",IF(AA9>7,"🟡 Atenção","🟢 Em dia")),IF(TODAY()>Z9,"🔴 Atrasado",IF(Z9-TODAY()<=3,"🟡 Atenção","🟢 Em dia")))) | AD9: =IF(OR(AC9="",H9=""),"",H9*AC9) | AF9: =IF(AC9>0,AC9,'⚙️ Config'!$B$10) -> 0.0075 | AG9: =H9*AF9 -> 386160.41 | AH9: =AG9*'⚙️ Config'!$B$11 -> 1930802 | AI9: =AH9*'⚙️ Config'!$B$12 -> 579240.61
A10: 7 | B10: FRIG WEST TRANSPORTES LTDA | C10: SP | D10: 10426902 | E10: 50.08 | F10: 🔴 ALTA | G10: R$ 30-50M | H10: 44306739 | I10: 2 | J10: 1.3 | K10: 2024 | L10: R D Ativa - Contribuição Previdenciária Sobre Receita Bruta | R D Ativa - Contribuição Risco Ambiental/Aposent Especial | M10: 2024 | N10: COBRANCA | O10: =TEXT(D10,"00000000")&"0001" -> 104269020001 | P10: =IF(MOD(MID(O10,1,1)*5+MID(O10,2,1)*4+MID(O10,3,1)*3+MID(O10,4,1)*2+MID(O10,5,1)*9+MID(O10,6,1)*8+MID(O10,7,1)*7+MID(O10,8,1)*6+MID(O10,9,1)*5+MID(O10,10,1)*4+MID(O10,11,1)*3+MID(O10,12,1)*2,11)<2,0,11-MOD(MID(O10,1,1)*5+MID(O10,2,1)*4+MID(O10,3,1)*3+MID(O10,4,1)*2+MID(O10,5,1)*9+MID(O10,6,1)*8+MID(O10,7,1)*7+MID(O10,8,1)*6+MID(O10,9,1)*5+MID(O10,10,1)*4+MID(O10,11,1)*3+MID(O10,12,1)*2,11)) -> 4 | Q10: =IF(MOD(MID(O10,1,1)*6+MID(O10,2,1)*5+MID(O10,3,1)*4+MID(O10,4,1)*3+MID(O10,5,1)*2+MID(O10,6,1)*9+MID(O10,7,1)*8+MID(O10,8,1)*7+MID(O10,9,1)*6+MID(O10,10,1)*5+MID(O10,11,1)*4+MID(O10,12,1)*3+P10*2,11)<2,0,11-MOD(MID(O10,1,1)*6+MID(O10,2,1)*5+MID(O10,3,1)*4+MID(O10,4,1)*3+MID(O10,5,1)*2+MID(O10,6,1)*9+MID(O10,7,1)*8+MID(O10,8,1)*7+MID(O10,9,1)*6+MID(O10,10,1)*5+MID(O10,11,1)*4+MID(O10,12,1)*3+P10*2,11)) -> 8 | R10: =MID(O10,1,2)&"."&MID(O10,3,3)&"."&MID(O10,6,3)&"/"&MID(O10,9,4)&"-"&TEXT(P10,"0")&TEXT(Q10,"0") -> 10.426.902/0001-48 | T10: =IF(S10="","",IF(S10="Cadastrou","",XLOOKUP(S10,$BA$2:$BA$6,$BB$2:$BB$6,""))) | U10: =IF(S10="","",IF(S10="Cadastrou","",XLOOKUP(S10,$BA$2:$BA$6,$BC$2:$BC$6,""))) | V10: =IF(S10="","",XLOOKUP(S10,$BA$2:$BA$6,$BD$2:$BD$6,"")) | AA10: =IF(Y10="","",IF(INT(TODAY()-Y10)<0,"⚠️ Data futura",INT(TODAY()-Y10))) | AB10: =IF(AA10="","",IF(Z10="",IF(AA10>14,"🔴 Atrasado",IF(AA10>7,"🟡 Atenção","🟢 Em dia")),IF(TODAY()>Z10,"🔴 Atrasado",IF(Z10-TODAY()<=3,"🟡 Atenção","🟢 Em dia")))) | AD10: =IF(OR(AC10="",H10=""),"",H10*AC10) | AF10: =IF(AC10>0,AC10,'⚙️ Config'!$B$10) -> 0.0075 | AG10: =H10*AF10 -> 332300.55 | AH10: =AG10*'⚙️ Config'!$B$11 -> 1661502.7 | AI10: =AH10*'⚙️ Config'!$B$12 -> 498450.82 | AO10: Inapta/Baixada
A11: 8 | B11: YOUNG LINE CONFECCOES LTDA | C11: SP | D11: 96420344 | E11: 56.12 | F11: 🔴 ALTA | G11: R$ 30-50M | H11: 41784265 | I11: 1 | J11: 1.5 | K11: 2024 | L11: Receita da dívida ativa - IRRF | M11: 2024 | N11: COBRANCA | O11: =TEXT(D11,"00000000")&"0001" -> 964203440001 | P11: =IF(MOD(MID(O11,1,1)*5+MID(O11,2,1)*4+MID(O11,3,1)*3+MID(O11,4,1)*2+MID(O11,5,1)*9+MID(O11,6,1)*8+MID(O11,7,1)*7+MID(O11,8,1)*6+MID(O11,9,1)*5+MID(O11,10,1)*4+MID(O11,11,1)*3+MID(O11,12,1)*2,11)<2,0,11-MOD(MID(O11,1,1)*5+MID(O11,2,1)*4+MID(O11,3,1)*3+MID(O11,4,1)*2+MID(O11,5,1)*9+MID(O11,6,1)*8+MID(O11,7,1)*7+MID(O11,8,1)*6+MID(O11,9,1)*5+MID(O11,10,1)*4+MID(O11,11,1)*3+MID(O11,12,1)*2,11)) -> 2 | Q11: =IF(MOD(MID(O11,1,1)*6+MID(O11,2,1)*5+MID(O11,3,1)*4+MID(O11,4,1)*3+MID(O11,5,1)*2+MID(O11,6,1)*9+MID(O11,7,1)*8+MID(O11,8,1)*7+MID(O11,9,1)*6+MID(O11,10,1)*5+MID(O11,11,1)*4+MID(O11,12,1)*3+P11*2,11)<2,0,11-MOD(MID(O11,1,1)*6+MID(O11,2,1)*5+MID(O11,3,1)*4+MID(O11,4,1)*3+MID(O11,5,1)*2+MID(O11,6,1)*9+MID(O11,7,1)*8+MID(O11,8,1)*7+MID(O11,9,1)*6+MID(O11,10,1)*5+MID(O11,11,1)*4+MID(O11,12,1)*3+P11*2,11)) -> 9 | R11: =MID(O11,1,2)&"."&MID(O11,3,3)&"."&MID(O11,6,3)&"/"&MID(O11,9,4)&"-"&TEXT(P11,"0")&TEXT(Q11,"0") -> 96.420.344/0001-29 | S11: Inapta/Baixada | T11: =IF(S11="","",IF(S11="Cadastrou","",XLOOKUP(S11,$BA$2:$BA$6,$BB$2:$BB$6,""))) | U11: =IF(S11="","",IF(S11="Cadastrou","",XLOOKUP(S11,$BA$2:$BA$6,$BC$2:$BC$6,""))) | V11: =IF(S11="","",XLOOKUP(S11,$BA$2:$BA$6,$BD$2:$BD$6,"")) | AA11: =IF(Y11="","",IF(INT(TODAY()-Y11)<0,"⚠️ Data futura",INT(TODAY()-Y11))) | AB11: =IF(AA11="","",IF(Z11="",IF(AA11>14,"🔴 Atrasado",IF(AA11>7,"🟡 Atenção","🟢 Em dia")),IF(TODAY()>Z11,"🔴 Atrasado",IF(Z11-TODAY()<=3,"🟡 Atenção","🟢 Em dia")))) | AD11: =IF(OR(AC11="",H11=""),"",H11*AC11) | AF11: =IF(AC11>0,AC11,'⚙️ Config'!$B$10) -> 0.0075 | AG11: =H11*AF11 -> 313381.99 | AH11: =AG11*'⚙️ Config'!$B$11 -> 1566910 | AI11: =AH11*'⚙️ Config'!$B$12 -> 470072.99
A12: 9 | B12: MADEX INDUSTRIA DE PLASTICOS LTDA | C12: SP | D12: 45067428 | E12: 69.45 | F12: 🔴 ALTA | G12: R$ 30-50M | H12: 41763002 | I12: 2 | J12: 0.7 | K12: 2025 | L12: Receita da dívida ativa - CSLL | Receita da dívida ativa - IRPJ | M12: 2025 | N12: COBRANCA | O12: =TEXT(D12,"00000000")&"0001" -> 450674280001 | P12: =IF(MOD(MID(O12,1,1)*5+MID(O12,2,1)*4+MID(O12,3,1)*3+MID(O12,4,1)*2+MID(O12,5,1)*9+MID(O12,6,1)*8+MID(O12,7,1)*7+MID(O12,8,1)*6+MID(O12,9,1)*5+MID(O12,10,1)*4+MID(O12,11,1)*3+MID(O12,12,1)*2,11)<2,0,11-MOD(MID(O12,1,1)*5+MID(O12,2,1)*4+MID(O12,3,1)*3+MID(O12,4,1)*2+MID(O12,5,1)*9+MID(O12,6,1)*8+MID(O12,7,1)*7+MID(O12,8,1)*6+MID(O12,9,1)*5+MID(O12,10,1)*4+MID(O12,11,1)*3+MID(O12,12,1)*2,11)) -> 9 | Q12: =IF(MOD(MID(O12,1,1)*6+MID(O12,2,1)*5+MID(O12,3,1)*4+MID(O12,4,1)*3+MID(O12,5,1)*2+MID(O12,6,1)*9+MID(O12,7,1)*8+MID(O12,8,1)*7+MID(O12,9,1)*6+MID(O12,10,1)*5+MID(O12,11,1)*4+MID(O12,12,1)*3+P12*2,11)<2,0,11-MOD(MID(O12,1,1)*6+MID(O12,2,1)*5+MID(O12,3,1)*4+MID(O12,4,1)*3+MID(O12,5,1)*2+MID(O12,6,1)*9+MID(O12,7,1)*8+MID(O12,8,1)*7+MID(O12,9,1)*6+MID(O12,10,1)*5+MID(O12,11,1)*4+MID(O12,12,1)*3+P12*2,11)) -> 0 | R12: =MID(O12,1,2)&"."&MID(O12,3,3)&"."&MID(O12,6,3)&"/"&MID(O12,9,4)&"-"&TEXT(P12,"0")&TEXT(Q12,"0") -> 45.067.428/0001-90 | T12: =IF(S12="","",IF(S12="Cadastrou","",XLOOKUP(S12,$BA$2:$BA$6,$BB$2:$BB$6,""))) | U12: =IF(S12="","",IF(S12="Cadastrou","",XLOOKUP(S12,$BA$2:$BA$6,$BC$2:$BC$6,""))) | V12: =IF(S12="","",XLOOKUP(S12,$BA$2:$BA$6,$BD$2:$BD$6,"")) | AA12: =IF(Y12="","",IF(INT(TODAY()-Y12)<0,"⚠️ Data futura",INT(TODAY()-Y12))) | AB12: =IF(AA12="","",IF(Z12="",IF(AA12>14,"🔴 Atrasado",IF(AA12>7,"🟡 Atenção","🟢 Em dia")),IF(TODAY()>Z12,"🔴 Atrasado",IF(Z12-TODAY()<=3,"🟡 Atenção","🟢 Em dia")))) | AD12: =IF(OR(AC12="",H12=""),"",H12*AC12) | AF12: =IF(AC12>0,AC12,'⚙️ Config'!$B$10) -> 0.0075 | AG12: =H12*AF12 -> 313222.52 | AH12: =AG12*'⚙️ Config'!$B$11 -> 1566112.6 | AI12: =AH12*'⚙️ Config'!$B$12 -> 469833.78
A13: 10 | B13: FX VIAGENS E TURISMO LTDA | C13: SP | D13: 10923833 | E13: 45.03 | F13: 🔴 ALTA | G13: R$ 30-50M | H13: 36220964 | I13: 2 | J13: 1.8 | K13: 2024 | L13: Receita da dívida ativa - PIS | R D Ativa - Simples Nacional | M13: 2024 | N13: AJUIZADA_SEM_GAR | O13: =TEXT(D13,"00000000")&"0001" -> 109238330001 | P13: =IF(MOD(MID(O13,1,1)*5+MID(O13,2,1)*4+MID(O13,3,1)*3+MID(O13,4,1)*2+MID(O13,5,1)*9+MID(O13,6,1)*8+MID(O13,7,1)*7+MID(O13,8,1)*6+MID(O13,9,1)*5+MID(O13,10,1)*4+MID(O13,11,1)*3+MID(O13,12,1)*2,11)<2,0,11-MOD(MID(O13,1,1)*5+MID(O13,2,1)*4+MID(O13,3,1)*3+MID(O13,4,1)*2+MID(O13,5,1)*9+MID(O13,6,1)*8+MID(O13,7,1)*7+MID(O13,8,1)*6+MID(O13,9,1)*5+MID(O13,10,1)*4+MID(O13,11,1)*3+MID(O13,12,1)*2,11)) -> 8 | Q13: =IF(MOD(MID(O13,1,1)*6+MID(O13,2,1)*5+MID(O13,3,1)*4+MID(O13,4,1)*3+MID(O13,5,1)*2+MID(O13,6,1)*9+MID(O13,7,1)*8+MID(O13,8,1)*7+MID(O13,9,1)*6+MID(O13,10,1)*5+MID(O13,11,1)*4+MID(O13,12,1)*3+P13*2,11)<2,0,11-MOD(MID(O13,1,1)*6+MID(O13,2,1)*5+MID(O13,3,1)*4+MID(O13,4,1)*3+MID(O13,5,1)*2+MID(O13,6,1)*9+MID(O13,7,1)*8+MID(O13,8,1)*7+MID(O13,9,1)*6+MID(O13,10,1)*5+MID(O13,11,1)*4+MID(O13,12,1)*3+P13*2,11)) -> 8 | R13: =MID(O13,1,2)&"."&MID(O13,3,3)&"."&MID(O13,6,3)&"/"&MID(O13,9,4)&"-"&TEXT(P13,"0")&TEXT(Q13,"0") -> 10.923.833/0001-88 | S13: Inapta/Baixada | T13: =IF(S13="","",IF(S13="Cadastrou","",XLOOKUP(S13,$BA$2:$BA$6,$BB$2:$BB$6,""))) | U13: =IF(S13="","",IF(S13="Cadastrou","",XLOOKUP(S13,$BA$2:$BA$6,$BC$2:$BC$6,""))) | V13: =IF(S13="","",XLOOKUP(S13,$BA$2:$BA$6,$BD$2:$BD$6,"")) | AA13: =IF(Y13="","",IF(INT(TODAY()-Y13)<0,"⚠️ Data futura",INT(TODAY()-Y13))) | AB13: =IF(AA13="","",IF(Z13="",IF(AA13>14,"🔴 Atrasado",IF(AA13>7,"🟡 Atenção","🟢 Em dia")),IF(TODAY()>Z13,"🔴 Atrasado",IF(Z13-TODAY()<=3,"🟡 Atenção","🟢 Em dia")))) | AD13: =IF(OR(AC13="",H13=""),"",H13*AC13) | AF13: =IF(AC13>0,AC13,'⚙️ Config'!$B$10) -> 0.0075 | AG13: =H13*AF13 -> 271657.23 | AH13: =AG13*'⚙️ Config'!$B$11 -> 1358286.1 | AI13: =AH13*'⚙️ Config'!$B$12 -> 407485.84
A14: 11 | B14: ANA MAIS CONSULTORIA LTDA | C14: SP | D14: 19071758 | E14: 59.76 | F14: 🔴 ALTA | G14: R$ 30-50M | H14: 32608457 | I14: 1 | J14: 1.3 | K14: 2024 | L14: Receita da dívida ativa - IRRF | M14: 2024 | N14: COBRANCA | O14: =TEXT(D14,"00000000")&"0001" -> 190717580001 | P14: =IF(MOD(MID(O14,1,1)*5+MID(O14,2,1)*4+MID(O14,3,1)*3+MID(O14,4,1)*2+MID(O14,5,1)*9+MID(O14,6,1)*8+MID(O14,7,1)*7+MID(O14,8,1)*6+MID(O14,9,1)*5+MID(O14,10,1)*4+MID(O14,11,1)*3+MID(O14,12,1)*2,11)<2,0,11-MOD(MID(O14,1,1)*5+MID(O14,2,1)*4+MID(O14,3,1)*3+MID(O14,4,1)*2+MID(O14,5,1)*9+MID(O14,6,1)*8+MID(O14,7,1)*7+MID(O14,8,1)*6+MID(O14,9,1)*5+MID(O14,10,1)*4+MID(O14,11,1)*3+MID(O14,12,1)*2,11)) -> 4 | Q14: =IF(MOD(MID(O14,1,1)*6+MID(O14,2,1)*5+MID(O14,3,1)*4+MID(O14,4,1)*3+MID(O14,5,1)*2+MID(O14,6,1)*9+MID(O14,7,1)*8+MID(O14,8,1)*7+MID(O14,9,1)*6+MID(O14,10,1)*5+MID(O14,11,1)*4+MID(O14,12,1)*3+P14*2,11)<2,0,11-MOD(MID(O14,1,1)*6+MID(O14,2,1)*5+MID(O14,3,1)*4+MID(O14,4,1)*3+MID(O14,5,1)*2+MID(O14,6,1)*9+MID(O14,7,1)*8+MID(O14,8,1)*7+MID(O14,9,1)*6+MID(O14,10,1)*5+MID(O14,11,1)*4+MID(O14,12,1)*3+P14*2,11)) -> 9 | R14: =MID(O14,1,2)&"."&MID(O14,3,3)&"."&MID(O14,6,3)&"/"&MID(O14,9,4)&"-"&TEXT(P14,"0")&TEXT(Q14,"0") -> 19.071.758/0001-49 | T14: =IF(S14="","",IF(S14="Cadastrou","",XLOOKUP(S14,$BA$2:$BA$6,$BB$2:$BB$6,""))) | U14: =IF(S14="","",IF(S14="Cadastrou","",XLOOKUP(S14,$BA$2:$BA$6,$BC$2:$BC$6,""))) | V14: =IF(S14="","",XLOOKUP(S14,$BA$2:$BA$6,$BD$2:$BD$6,"")) | AA14: =IF(Y14="","",IF(INT(TODAY()-Y14)<0,"⚠️ Data futura",INT(TODAY()-Y14))) | AB14: =IF(AA14="","",IF(Z14="",IF(AA14>14,"🔴 Atrasado",IF(AA14>7,"🟡 Atenção","🟢 Em dia")),IF(TODAY()>Z14,"🔴 Atrasado",IF(Z14-TODAY()<=3,"🟡 Atenção","🟢 Em dia")))) | AD14: =IF(OR(AC14="",H14=""),"",H14*AC14) | AF14: =IF(AC14>0,AC14,'⚙️ Config'!$B$10) -> 0.0075 | AG14: =H14*AF14 -> 244563.43 | AH14: =AG14*'⚙️ Config'!$B$11 -> 1222817.1 | AI14: =AH14*'⚙️ Config'!$B$12 -> 366845.14
A15: 12 | B15: OVS IMPORTADORA LTDA. | C15: SP | D15: 03394819 | E15: 53.17 | F15: 🔴 ALTA | G15: R$ 20-30M | H15: 29079824 | I15: 2 | J15: 1.8 | K15: 2025 | L15: Receita da dívida ativa - Outras multas | M15: 2024 | N15: AJUIZADA_SEM_GAR|COBRANCA | O15: =TEXT(D15,"00000000")&"0001" -> 033948190001 | P15: =IF(MOD(MID(O15,1,1)*5+MID(O15,2,1)*4+MID(O15,3,1)*3+MID(O15,4,1)*2+MID(O15,5,1)*9+MID(O15,6,1)*8+MID(O15,7,1)*7+MID(O15,8,1)*6+MID(O15,9,1)*5+MID(O15,10,1)*4+MID(O15,11,1)*3+MID(O15,12,1)*2,11)<2,0,11-MOD(MID(O15,1,1)*5+MID(O15,2,1)*4+MID(O15,3,1)*3+MID(O15,4,1)*2+MID(O15,5,1)*9+MID(O15,6,1)*8+MID(O15,7,1)*7+MID(O15,8,1)*6+MID(O15,9,1)*5+MID(O15,10,1)*4+MID(O15,11,1)*3+MID(O15,12,1)*2,11)) -> 7 | Q15: =IF(MOD(MID(O15,1,1)*6+MID(O15,2,1)*5+MID(O15,3,1)*4+MID(O15,4,1)*3+MID(O15,5,1)*2+MID(O15,6,1)*9+MID(O15,7,1)*8+MID(O15,8,1)*7+MID(O15,9,1)*6+MID(O15,10,1)*5+MID(O15,11,1)*4+MID(O15,12,1)*3+P15*2,11)<2,0,11-MOD(MID(O15,1,1)*6+MID(O15,2,1)*5+MID(O15,3,1)*4+MID(O15,4,1)*3+MID(O15,5,1)*2+MID(O15,6,1)*9+MID(O15,7,1)*8+MID(O15,8,1)*7+MID(O15,9,1)*6+MID(O15,10,1)*5+MID(O15,11,1)*4+MID(O15,12,1)*3+P15*2,11)) -> 9 | R15: =MID(O15,1,2)&"."&MID(O15,3,3)&"."&MID(O15,6,3)&"/"&MID(O15,9,4)&"-"&TEXT(P15,"0")&TEXT(Q15,"0") -> 03.394.819/0001-79 | T15: =IF(S15="","",IF(S15="Cadastrou","",XLOOKUP(S15,$BA$2:$BA$6,$BB$2:$BB$6,""))) | U15: =IF(S15="","",IF(S15="Cadastrou","",XLOOKUP(S15,$BA$2:$BA$6,$BC$2:$BC$6,""))) | V15: =IF(S15="","",XLOOKUP(S15,$BA$2:$BA$6,$BD$2:$BD$6,"")) | AA15: =IF(Y15="","",IF(INT(TODAY()-Y15)<0,"⚠️ Data futura",INT(TODAY()-Y15))) | AB15: =IF(AA15="","",IF(Z15="",IF(AA15>14,"🔴 Atrasado",IF(AA15>7,"🟡 Atenção","🟢 Em dia")),IF(TODAY()>Z15,"🔴 Atrasado",IF(Z15-TODAY()<=3,"🟡 Atenção","🟢 Em dia")))) | AD15: =IF(OR(AC15="",H15=""),"",H15*AC15) | AF15: =IF(AC15>0,AC15,'⚙️ Config'!$B$10) -> 0.0075 | AG15: =H15*AF15 -> 218098.68 | AH15: =AG15*'⚙️ Config'!$B$11 -> 1090493.4 | AI15: =AH15*'⚙️ Config'!$B$12 -> 327148.02 | AJ15: 12952000 | AK15: Médio | AL15: Não | AO15: Francisco Emerson Maximiniano | AP15: Socio
A16: 13 | B16: WANMIX LTDA | C16: SP | D16: 17481813 | E16: 42.59 | F16: 🔴 ALTA | G16: R$ 20-30M | H16: 28863838 | I16: 2 | J16: 1.7 | K16: 2024 | L16: Receita da dívida ativa - CSLL | Receita da dívida ativa - IRPJ | M16: 2024 | N16: AJUIZADA_SEM_GAR | O16: =TEXT(D16,"00000000")&"0001" -> 174818130001 | P16: =IF(MOD(MID(O16,1,1)*5+MID(O16,2,1)*4+MID(O16,3,1)*3+MID(O16,4,1)*2+MID(O16,5,1)*9+MID(O16,6,1)*8+MID(O16,7,1)*7+MID(O16,8,1)*6+MID(O16,9,1)*5+MID(O16,10,1)*4+MID(O16,11,1)*3+MID(O16,12,1)*2,11)<2,0,11-MOD(MID(O16,1,1)*5+MID(O16,2,1)*4+MID(O16,3,1)*3+MID(O16,4,1)*2+MID(O16,5,1)*9+MID(O16,6,1)*8+MID(O16,7,1)*7+MID(O16,8,1)*6+MID(O16,9,1)*5+MID(O16,10,1)*4+MID(O16,11,1)*3+MID(O16,12,1)*2,11)) -> 4 | Q16: =IF(MOD(MID(O16,1,1)*6+MID(O16,2,1)*5+MID(O16,3,1)*4+MID(O16,4,1)*3+MID(O16,5,1)*2+MID(O16,6,1)*9+MID(O16,7,1)*8+MID(O16,8,1)*7+MID(O16,9,1)*6+MID(O16,10,1)*5+MID(O16,11,1)*4+MID(O16,12,1)*3+P16*2,11)<2,0,11-MOD(MID(O16,1,1)*6+MID(O16,2,1)*5+MID(O16,3,1)*4+MID(O16,4,1)*3+MID(O16,5,1)*2+MID(O16,6,1)*9+MID(O16,7,1)*8+MID(O16,8,1)*7+MID(O16,9,1)*6+MID(O16,10,1)*5+MID(O16,11,1)*4+MID(O16,12,1)*3+P16*2,11)) -> 3 | R16: =MID(O16,1,2)&"."&MID(O16,3,3)&"."&MID(O16,6,3)&"/"&MID(O16,9,4)&"-"&TEXT(P16,"0")&TEXT(Q16,"0") -> 17.481.813/0001-43 | T16: =IF(S16="","",IF(S16="Cadastrou","",XLOOKUP(S16,$BA$2:$BA$6,$BB$2:$BB$6,""))) | U16: =IF(S16="","",IF(S16="Cadastrou","",XLOOKUP(S16,$BA$2:$BA$6,$BC$2:$BC$6,""))) | V16: =IF(S16="","",XLOOKUP(S16,$BA$2:$BA$6,$BD$2:$BD$6,"")) | AA16: =IF(Y16="","",IF(INT(TODAY()-Y16)<0,"⚠️ Data futura",INT(TODAY()-Y16))) | AB16: =IF(AA16="","",IF(Z16="",IF(AA16>14,"🔴 Atrasado",IF(AA16>7,"🟡 Atenção","🟢 Em dia")),IF(TODAY()>Z16,"🔴 Atrasado",IF(Z16-TODAY()<=3,"🟡 Atenção","🟢 Em dia")))) | AD16: =IF(OR(AC16="",H16=""),"",H16*AC16) | AF16: =IF(AC16>0,AC16,'⚙️ Config'!$B$10) -> 0.0075 | AG16: =H16*AF16 -> 216478.78 | AH16: =AG16*'⚙️ Config'!$B$11 -> 1082393.9 | AI16: =AH16*'⚙️ Config'!$B$12 -> 324718.18 | AJ16: 4500000
A17: 14 | B17: CTR METAIS PRECIOSOS LTDA | C17: SP | D17: 45685839 | E17: 84.39 | F17: 🔴 ALTA | G17: R$ 20-30M | H17: 28256455 | I17: 1 | J17: 0.6 | K17: 2025 | L17: R D Ativa - Multa Isolada | M17: 2025 | N17: COBRANCA | O17: =TEXT(D17,"00000000")&"0001" -> 456858390001 | P17: =IF(MOD(MID(O17,1,1)*5+MID(O17,2,1)*4+MID(O17,3,1)*3+MID(O17,4,1)*2+MID(O17,5,1)*9+MID(O17,6,1)*8+MID(O17,7,1)*7+MID(O17,8,1)*6+MID(O17,9,1)*5+MID(O17,10,1)*4+MID(O17,11,1)*3+MID(O17,12,1)*2,11)<2,0,11-MOD(MID(O17,1,1)*5+MID(O17,2,1)*4+MID(O17,3,1)*3+MID(O17,4,1)*2+MID(O17,5,1)*9+MID(O17,6,1)*8+MID(O17,7,1)*7+MID(O17,8,1)*6+MID(O17,9,1)*5+MID(O17,10,1)*4+MID(O17,11,1)*3+MID(O17,12,1)*2,11)) -> 4 | Q17: =IF(MOD(MID(O17,1,1)*6+MID(O17,2,1)*5+MID(O17,3,1)*4+MID(O17,4,1)*3+MID(O17,5,1)*2+MID(O17,6,1)*9+MID(O17,7,1)*8+MID(O17,8,1)*7+MID(O17,9,1)*6+MID(O17,10,1)*5+MID(O17,11,1)*4+MID(O17,12,1)*3+P17*2,11)<2,0,11-MOD(MID(O17,1,1)*6+MID(O17,2,1)*5+MID(O17,3,1)*4+MID(O17,4,1)*3+MID(O17,5,1)*2+MID(O17,6,1)*9+MID(O17,7,1)*8+MID(O17,8,1)*7+MID(O17,9,1)*6+MID(O17,10,1)*5+MID(O17,11,1)*4+MID(O17,12,1)*3+P17*2,11)) -> 9 | R17: =MID(O17,1,2)&"."&MID(O17,3,3)&"."&MID(O17,6,3)&"/"&MID(O17,9,4)&"-"&TEXT(P17,"0")&TEXT(Q17,"0") -> 45.685.839/0001-49 | T17: =IF(S17="","",IF(S17="Cadastrou","",XLOOKUP(S17,$BA$2:$BA$6,$BB$2:$BB$6,""))) | U17: =IF(S17="","",IF(S17="Cadastrou","",XLOOKUP(S17,$BA$2:$BA$6,$BC$2:$BC$6,""))) | V17: =IF(S17="","",XLOOKUP(S17,$BA$2:$BA$6,$BD$2:$BD$6,"")) | AA17: =IF(Y17="","",IF(INT(TODAY()-Y17)<0,"⚠️ Data futura",INT(TODAY()-Y17))) | AB17: =IF(AA17="","",IF(Z17="",IF(AA17>14,"🔴 Atrasado",IF(AA17>7,"🟡 Atenção","🟢 Em dia")),IF(TODAY()>Z17,"🔴 Atrasado",IF(Z17-TODAY()<=3,"🟡 Atenção","🟢 Em dia")))) | AD17: =IF(OR(AC17="",H17=""),"",H17*AC17) | AF17: =IF(AC17>0,AC17,'⚙️ Config'!$B$10) -> 0.0075 | AG17: =H17*AF17 -> 211923.41 | AH17: =AG17*'⚙️ Config'!$B$11 -> 1059617.1 | AI17: =AH17*'⚙️ Config'!$B$12 -> 317885.12
A18: 15 | B18: VETOR COMERCIO DE COMBUSTIVEIS LTDA | C18: MS | D18: 04677033 | E18: 59.64 | F18: 🔴 ALTA | G18: R$ 20-30M | H18: 27848766 | I18: 1 | J18: 1.3 | K18: 2024 | L18: Receita da dívida ativa - IRRF | M18: 2024 | N18: AJUIZADA_SEM_GAR | O18: =TEXT(D18,"00000000")&"0001" -> 046770330001 | P18: =IF(MOD(MID(O18,1,1)*5+MID(O18,2,1)*4+MID(O18,3,1)*3+MID(O18,4,1)*2+MID(O18,5,1)*9+MID(O18,6,1)*8+MID(O18,7,1)*7+MID(O18,8,1)*6+MID(O18,9,1)*5+MID(O18,10,1)*4+MID(O18,11,1)*3+MID(O18,12,1)*2,11)<2,0,11-MOD(MID(O18,1,1)*5+MID(O18,2,1)*4+MID(O18,3,1)*3+MID(O18,4,1)*2+MID(O18,5,1)*9+MID(O18,6,1)*8+MID(O18,7,1)*7+MID(O18,8,1)*6+MID(O18,9,1)*5+MID(O18,10,1)*4+MID(O18,11,1)*3+MID(O18,12,1)*2,11)) -> 2 | Q18: =IF(MOD(MID(O18,1,1)*6+MID(O18,2,1)*5+MID(O18,3,1)*4+MID(O18,4,1)*3+MID(O18,5,1)*2+MID(O18,6,1)*9+MID(O18,7,1)*8+MID(O18,8,1)*7+MID(O18,9,1)*6+MID(O18,10,1)*5+MID(O18,11,1)*4+MID(O18,12,1)*3+P18*2,11)<2,0,11-MOD(MID(O18,1,1)*6+MID(O18,2,1)*5+MID(O18,3,1)*4+MID(O18,4,1)*3+MID(O18,5,1)*2+MID(O18,6,1)*9+MID(O18,7,1)*8+MID(O18,8,1)*7+MID(O18,9,1)*6+MID(O18,10,1)*5+MID(O18,11,1)*4+MID(O18,12,1)*3+P18*2,11)) -> 1 | R18: =MID(O18,1,2)&"."&MID(O18,3,3)&"."&MID(O18,6,3)&"/"&MID(O18,9,4)&"-"&TEXT(P18,"0")&TEXT(Q18,"0") -> 04.677.033/0001-21 | T18: =IF(S18="","",IF(S18="Cadastrou","",XLOOKUP(S18,$BA$2:$BA$6,$BB$2:$BB$6,""))) | U18: =IF(S18="","",IF(S18="Cadastrou","",XLOOKUP(S18,$BA$2:$BA$6,$BC$2:$BC$6,""))) | V18: =IF(S18="","",XLOOKUP(S18,$BA$2:$BA$6,$BD$2:$BD$6,"")) | AA18: =IF(Y18="","",IF(INT(TODAY()-Y18)<0,"⚠️ Data futura",INT(TODAY()-Y18))) | AB18: =IF(AA18="","",IF(Z18="",IF(AA18>14,"🔴 Atrasado",IF(AA18>7,"🟡 Atenção","🟢 Em dia")),IF(TODAY()>Z18,"🔴 Atrasado",IF(Z18-TODAY()<=3,"🟡 Atenção","🟢 Em dia")))) | AD18: =IF(OR(AC18="",H18=""),"",H18*AC18) | AF18: =IF(AC18>0,AC18,'⚙️ Config'!$B$10) -> 0.0075 | AG18: =H18*AF18 -> 208865.75 | AH18: =AG18*'⚙️ Config'!$B$11 -> 1044328.7 | AI18: =AH18*'⚙️ Config'!$B$12 -> 313298.62 | AJ18: 5147975 | AL18: Não
A19: 16 | B19: SUMATRA COMERCIO EXTERIOR LTDA | C19: SP | D19: 31235518 | E19: 54 | F19: 🔴 ALTA | G19: R$ 20-30M | H19: 24915563 | I19: 1 | J19: 1.6 | K19: 2024 | L19: Receita da dívida ativa - IRPJ | M19: 2024 | N19: AJUIZADA_SEM_GAR | O19: =TEXT(D19,"00000000")&"0001" -> 312355180001 | P19: =IF(MOD(MID(O19,1,1)*5+MID(O19,2,1)*4+MID(O19,3,1)*3+MID(O19,4,1)*2+MID(O19,5,1)*9+MID(O19,6,1)*8+MID(O19,7,1)*7+MID(O19,8,1)*6+MID(O19,9,1)*5+MID(O19,10,1)*4+MID(O19,11,1)*3+MID(O19,12,1)*2,11)<2,0,11-MOD(MID(O19,1,1)*5+MID(O19,2,1)*4+MID(O19,3,1)*3+MID(O19,4,1)*2+MID(O19,5,1)*9+MID(O19,6,1)*8+MID(O19,7,1)*7+MID(O19,8,1)*6+MID(O19,9,1)*5+MID(O19,10,1)*4+MID(O19,11,1)*3+MID(O19,12,1)*2,11)) -> 3 | Q19: =IF(MOD(MID(O19,1,1)*6+MID(O19,2,1)*5+MID(O19,3,1)*4+MID(O19,4,1)*3+MID(O19,5,1)*2+MID(O19,6,1)*9+MID(O19,7,1)*8+MID(O19,8,1)*7+MID(O19,9,1)*6+MID(O19,10,1)*5+MID(O19,11,1)*4+MID(O19,12,1)*3+P19*2,11)<2,0,11-MOD(MID(O19,1,1)*6+MID(O19,2,1)*5+MID(O19,3,1)*4+MID(O19,4,1)*3+MID(O19,5,1)*2+MID(O19,6,1)*9+MID(O19,7,1)*8+MID(O19,8,1)*7+MID(O19,9,1)*6+MID(O19,10,1)*5+MID(O19,11,1)*4+MID(O19,12,1)*3+P19*2,11)) -> 8 | R19: =MID(O19,1,2)&"."&MID(O19,3,3)&"."&MID(O19,6,3)&"/"&MID(O19,9,4)&"-"&TEXT(P19,"0")&TEXT(Q19,"0") -> 31.235.518/0001-38 | T19: =IF(S19="","",IF(S19="Cadastrou","",XLOOKUP(S19,$BA$2:$BA$6,$BB$2:$BB$6,""))) | U19: =IF(S19="","",IF(S19="Cadastrou","",XLOOKUP(S19,$BA$2:$BA$6,$BC$2:$BC$6,""))) | V19: =IF(S19="","",XLOOKUP(S19,$BA$2:$BA$6,$BD$2:$BD$6,"")) | AA19: =IF(Y19="","",IF(INT(TODAY()-Y19)<0,"⚠️ Data futura",INT(TODAY()-Y19))) | AB19: =IF(AA19="","",IF(Z19="",IF(AA19>14,"🔴 Atrasado",IF(AA19>7,"🟡 Atenção","🟢 Em dia")),IF(TODAY()>Z19,"🔴 Atrasado",IF(Z19-TODAY()<=3,"🟡 Atenção","🟢 Em dia")))) | AD19: =IF(OR(AC19="",H19=""),"",H19*AC19) | AF19: =IF(AC19>0,AC19,'⚙️ Config'!$B$10) -> 0.0075 | AG19: =H19*AF19 -> 186866.73 | AH19: =AG19*'⚙️ Config'!$B$11 -> 934333.63 | AI19: =AH19*'⚙️ Config'!$B$12 -> 280300.09 | AJ19: 9903208 | AL19: Não | AM19: 19 3661-9928 | AO19: Jose Roberto Zerneri
A20: 17 | B20: BARSOTTI SERVICOS DE PORTARIA LTDA | C20: SP | D20: 10468394 | E20: 69.71 | F20: 🔴 ALTA | G20: R$ 20-30M | H20: 24685772 | I20: 1 | J20: 1.6 | K20: 2025 | L20: Receita da dívida ativa - COFINS | R D Ativa - Contribuição Empresa/Empregador | R D Ativa - Multa Isolada | M20: 2024 | N20: AJUIZADA_SEM_GAR|OUTROS | O20: =TEXT(D20,"00000000")&"0001" -> 104683940001 | P20: =IF(MOD(MID(O20,1,1)*5+MID(O20,2,1)*4+MID(O20,3,1)*3+MID(O20,4,1)*2+MID(O20,5,1)*9+MID(O20,6,1)*8+MID(O20,7,1)*7+MID(O20,8,1)*6+MID(O20,9,1)*5+MID(O20,10,1)*4+MID(O20,11,1)*3+MID(O20,12,1)*2,11)<2,0,11-MOD(MID(O20,1,1)*5+MID(O20,2,1)*4+MID(O20,3,1)*3+MID(O20,4,1)*2+MID(O20,5,1)*9+MID(O20,6,1)*8+MID(O20,7,1)*7+MID(O20,8,1)*6+MID(O20,9,1)*5+MID(O20,10,1)*4+MID(O20,11,1)*3+MID(O20,12,1)*2,11)) -> 6 | Q20: =IF(MOD(MID(O20,1,1)*6+MID(O20,2,1)*5+MID(O20,3,1)*4+MID(O20,4,1)*3+MID(O20,5,1)*2+MID(O20,6,1)*9+MID(O20,7,1)*8+MID(O20,8,1)*7+MID(O20,9,1)*6+MID(O20,10,1)*5+MID(O20,11,1)*4+MID(O20,12,1)*3+P20*2,11)<2,0,11-MOD(MID(O20,1,1)*6+MID(O20,2,1)*5+MID(O20,3,1)*4+MID(O20,4,1)*3+MID(O20,5,1)*2+MID(O20,6,1)*9+MID(O20,7,1)*8+MID(O20,8,1)*7+MID(O20,9,1)*6+MID(O20,10,1)*5+MID(O20,11,1)*4+MID(O20,12,1)*3+P20*2,11)) -> 0 | R20: 8759416 | T20: =IF(S20="","",IF(S20="Cadastrou","",XLOOKUP(S20,$BA$2:$BA$6,$BB$2:$BB$6,""))) | U20: =IF(S20="","",IF(S20="Cadastrou","",XLOOKUP(S20,$BA$2:$BA$6,$BC$2:$BC$6,""))) | V20: =IF(S20="","",XLOOKUP(S20,$BA$2:$BA$6,$BD$2:$BD$6,"")) | AA20: =IF(Y20="","",IF(INT(TODAY()-Y20)<0,"⚠️ Data futura",INT(TODAY()-Y20))) | AB20: =IF(AA20="","",IF(Z20="",IF(AA20>14,"🔴 Atrasado",IF(AA20>7,"🟡 Atenção","🟢 Em dia")),IF(TODAY()>Z20,"🔴 Atrasado",IF(Z20-TODAY()<=3,"🟡 Atenção","🟢 Em dia")))) | AD20: =IF(OR(AC20="",H20=""),"",H20*AC20) | AF20: =IF(AC20>0,AC20,'⚙️ Config'!$B$10) -> 0.0075 | AG20: =H20*AF20 -> 185143.29 | AH20: =AG20*'⚙️ Config'!$B$11 -> 925716.45 | AI20: =AH20*'⚙️ Config'!$B$12 -> 277714.94 | AJ20: 990000 | AM20: (11) 2339-6642 | AN20: rh@grupobarsotti.com.br | AO20: JOSE VALDIR DE OLIVEIRA | AP20: Sócio-Administrador
A21: 18 | B21: KOPRUM INDUSTRIA E COMERCIO SA | C21: SP | D21: 08759416 | E21: 57.49 | F21: 🔴 ALTA | G21: R$ 20-30M | H21: 24060892 | I21: 1 | J21: 1.4 | K21: 2024 | L21: Receita da dívida ativa - CSLL | M21: 2024 | N21: AJUIZADA_SEM_GAR | O21: =TEXT(D21,"00000000")&"0001" -> 087594160001 | P21: =IF(MOD(MID(O21,1,1)*5+MID(O21,2,1)*4+MID(O21,3,1)*3+MID(O21,4,1)*2+MID(O21,5,1)*9+MID(O21,6,1)*8+MID(O21,7,1)*7+MID(O21,8,1)*6+MID(O21,9,1)*5+MID(O21,10,1)*4+MID(O21,11,1)*3+MID(O21,12,1)*2,11)<2,0,11-MOD(MID(O21,1,1)*5+MID(O21,2,1)*4+MID(O21,3,1)*3+MID(O21,4,1)*2+MID(O21,5,1)*9+MID(O21,6,1)*8+MID(O21,7,1)*7+MID(O21,8,1)*6+MID(O21,9,1)*5+MID(O21,10,1)*4+MID(O21,11,1)*3+MID(O21,12,1)*2,11)) -> 0 | Q21: =IF(MOD(MID(O21,1,1)*6+MID(O21,2,1)*5+MID(O21,3,1)*4+MID(O21,4,1)*3+MID(O21,5,1)*2+MID(O21,6,1)*9+MID(O21,7,1)*8+MID(O21,8,1)*7+MID(O21,9,1)*6+MID(O21,10,1)*5+MID(O21,11,1)*4+MID(O21,12,1)*3+P21*2,11)<2,0,11-MOD(MID(O21,1,1)*6+MID(O21,2,1)*5+MID(O21,3,1)*4+MID(O21,4,1)*3+MID(O21,5,1)*2+MID(O21,6,1)*9+MID(O21,7,1)*8+MID(O21,8,1)*7+MID(O21,9,1)*6+MID(O21,10,1)*5+MID(O21,11,1)*4+MID(O21,12,1)*3+P21*2,11)) -> 8 | R21: =MID(O21,1,2)&"."&MID(O21,3,3)&"."&MID(O21,6,3)&"/"&MID(O21,9,4)&"-"&TEXT(P21,"0")&TEXT(Q21,"0") -> 08.759.416/0001-08 | T21: =IF(S21="","",IF(S21="Cadastrou","",XLOOKUP(S21,$BA$2:$BA$6,$BB$2:$BB$6,""))) | U21: =IF(S21="","",IF(S21="Cadastrou","",XLOOKUP(S21,$BA$2:$BA$6,$BC$2:$BC$6,""))) | V21: =IF(S21="","",XLOOKUP(S21,$BA$2:$BA$6,$BD$2:$BD$6,"")) | AA21: =IF(Y21="","",IF(INT(TODAY()-Y21)<0,"⚠️ Data futura",INT(TODAY()-Y21))) | AB21: =IF(AA21="","",IF(Z21="",IF(AA21>14,"🔴 Atrasado",IF(AA21>7,"🟡 Atenção","🟢 Em dia")),IF(TODAY()>Z21,"🔴 Atrasado",IF(Z21-TODAY()<=3,"🟡 Atenção","🟢 Em dia")))) | AD21: =IF(OR(AC21="",H21=""),"",H21*AC21) | AF21: =IF(AC21>0,AC21,'⚙️ Config'!$B$10) -> 0.0075 | AG21: =H21*AF21 -> 180456.69 | AH21: =AG21*'⚙️ Config'!$B$11 -> 902283.46 | AI21: =AH21*'⚙️ Config'!$B$12 -> 270685.04 | AJ21: 17580000 | AM21: (31) 3438-7904 | AN21: legalizacao@britt.com.br | AO21: PAULO CESAR VERLY DA CRUZ | AP21: Diretor
A22: 19 | B22: CP CONSTRUCOES E PARTICIPACOES LTDA | C22: SP | D22: 07177497 | E22: 67.29 | F22: 🔴 ALTA | G22: R$ 20-30M | H22: 23340249 | I22: 1 | J22: 1 | K22: 2025 | L22: Receita da dívida ativa - CSLL | M22: 2025 | N22: COBRANCA | O22: =TEXT(D22,"00000000")&"0001" -> 071774970001 | P22: =IF(MOD(MID(O22,1,1)*5+MID(O22,2,1)*4+MID(O22,3,1)*3+MID(O22,4,1)*2+MID(O22,5,1)*9+MID(O22,6,1)*8+MID(O22,7,1)*7+MID(O22,8,1)*6+MID(O22,9,1)*5+MID(O22,10,1)*4+MID(O22,11,1)*3+MID(O22,12,1)*2,11)<2,0,11-MOD(MID(O22,1,1)*5+MID(O22,2,1)*4+MID(O22,3,1)*3+MID(O22,4,1)*2+MID(O22,5,1)*9+MID(O22,6,1)*8+MID(O22,7,1)*7+MID(O22,8,1)*6+MID(O22,9,1)*5+MID(O22,10,1)*4+MID(O22,11,1)*3+MID(O22,12,1)*2,11)) -> 6 | Q22: =IF(MOD(MID(O22,1,1)*6+MID(O22,2,1)*5+MID(O22,3,1)*4+MID(O22,4,1)*3+MID(O22,5,1)*2+MID(O22,6,1)*9+MID(O22,7,1)*8+MID(O22,8,1)*7+MID(O22,9,1)*6+MID(O22,10,1)*5+MID(O22,11,1)*4+MID(O22,12,1)*3+P22*2,11)<2,0,11-MOD(MID(O22,1,1)*6+MID(O22,2,1)*5+MID(O22,3,1)*4+MID(O22,4,1)*3+MID(O22,5,1)*2+MID(O22,6,1)*9+MID(O22,7,1)*8+MID(O22,8,1)*7+MID(O22,9,1)*6+MID(O22,10,1)*5+MID(O22,11,1)*4+MID(O22,12,1)*3+P22*2,11)) -> 7 | R22: =MID(O22,1,2)&"."&MID(O22,3,3)&"."&MID(O22,6,3)&"/"&MID(O22,9,4)&"-"&TEXT(P22,"0")&TEXT(Q22,"0") -> 07.177.497/0001-67 | T22: =IF(S22="","",IF(S22="Cadastrou","",XLOOKUP(S22,$BA$2:$BA$6,$BB$2:$BB$6,""))) | U22: =IF(S22="","",IF(S22="Cadastrou","",XLOOKUP(S22,$BA$2:$BA$6,$BC$2:$BC$6,""))) | V22: =IF(S22="","",XLOOKUP(S22,$BA$2:$BA$6,$BD$2:$BD$6,"")) | AA22: =IF(Y22="","",IF(INT(TODAY()-Y22)<0,"⚠️ Data futura",INT(TODAY()-Y22))) | AB22: =IF(AA22="","",IF(Z22="",IF(AA22>14,"🔴 Atrasado",IF(AA22>7,"🟡 Atenção","🟢 Em dia")),IF(TODAY()>Z22,"🔴 Atrasado",IF(Z22-TODAY()<=3,"🟡 Atenção","🟢 Em dia")))) | AD22: =IF(OR(AC22="",H22=""),"",H22*AC22) | AF22: =IF(AC22>0,AC22,'⚙️ Config'!$B$10) -> 0.0075 | AG22: =H22*AF22 -> 175051.86 | AH22: =AG22*'⚙️ Config'!$B$11 -> 875259.32 | AI22: =AH22*'⚙️ Config'!$B$12 -> 262577.8 | AJ22: 10361753 | AM22: (11) 3154-1500 | AN22: processos@swscontabil.com.br | AO22: ANDRE LOIFERMAN | AP22: Administrador
A23: 20 | B23: REGENCIA COMERCIO DE GENEROS ALIMENTICIOS LTDA | C23: SP | D23: 23866428 | E23: 57.43 | F23: 🔴 ALTA | G23: R$ 20-30M | H23: 22021035 | I23: 1 | J23: 1.4 | K23: 2024 | L23: Receita da dívida ativa - PIS | M23: 2024 | N23: AJUIZADA_SEM_GAR | O23: =TEXT(D23,"00000000")&"0001" -> 238664280001 | P23: =IF(MOD(MID(O23,1,1)*5+MID(O23,2,1)*4+MID(O23,3,1)*3+MID(O23,4,1)*2+MID(O23,5,1)*9+MID(O23,6,1)*8+MID(O23,7,1)*7+MID(O23,8,1)*6+MID(O23,9,1)*5+MID(O23,10,1)*4+MID(O23,11,1)*3+MID(O23,12,1)*2,11)<2,0,11-MOD(MID(O23,1,1)*5+MID(O23,2,1)*4+MID(O23,3,1)*3+MID(O23,4,1)*2+MID(O23,5,1)*9+MID(O23,6,1)*8+MID(O23,7,1)*7+MID(O23,8,1)*6+MID(O23,9,1)*5+MID(O23,10,1)*4+MID(O23,11,1)*3+MID(O23,12,1)*2,11)) -> 1 | Q23: =IF(MOD(MID(O23,1,1)*6+MID(O23,2,1)*5+MID(O23,3,1)*4+MID(O23,4,1)*3+MID(O23,5,1)*2+MID(O23,6,1)*9+MID(O23,7,1)*8+MID(O23,8,1)*7+MID(O23,9,1)*6+MID(O23,10,1)*5+MID(O23,11,1)*4+MID(O23,12,1)*3+P23*2,11)<2,0,11-MOD(MID(O23,1,1)*6+MID(O23,2,1)*5+MID(O23,3,1)*4+MID(O23,4,1)*3+MID(O23,5,1)*2+MID(O23,6,1)*9+MID(O23,7,1)*8+MID(O23,8,1)*7+MID(O23,9,1)*6+MID(O23,10,1)*5+MID(O23,11,1)*4+MID(O23,12,1)*3+P23*2,11)) -> 7 | R23: =MID(O23,1,2)&"."&MID(O23,3,3)&"."&MID(O23,6,3)&"/"&MID(O23,9,4)&"-"&TEXT(P23,"0")&TEXT(Q23,"0") -> 23.866.428/0001-17 | T23: =IF(S23="","",IF(S23="Cadastrou","",XLOOKUP(S23,$BA$2:$BA$6,$BB$2:$BB$6,""))) | U23: =IF(S23="","",IF(S23="Cadastrou","",XLOOKUP(S23,$BA$2:$BA$6,$BC$2:$BC$6,""))) | V23: =IF(S23="","",XLOOKUP(S23,$BA$2:$BA$6,$BD$2:$BD$6,"")) | AA23: =IF(Y23="","",IF(INT(TODAY()-Y23)<0,"⚠️ Data futura",INT(TODAY()-Y23))) | AB23: =IF(AA23="","",IF(Z23="",IF(AA23>14,"🔴 Atrasado",IF(AA23>7,"🟡 Atenção","🟢 Em dia")),IF(TODAY()>Z23,"🔴 Atrasado",IF(Z23-TODAY()<=3,"🟡 Atenção","🟢 Em dia")))) | AD23: =IF(OR(AC23="",H23=""),"",H23*AC23) | AF23: =IF(AC23>0,AC23,'⚙️ Config'!$B$10) -> 0.0075 | AG23: =H23*AF23 -> 165157.76 | AH23: =AG23*'⚙️ Config'!$B$11 -> 825788.8 | AI23: =AH23*'⚙️ Config'!$B$12 -> 247736.64 | AJ23: 1000 | AM23: (15) 3259-2634 | AN23: hazdelservicos@gmail.com | AO23: MARCIUS CESAR COSTA | AP23: Sócio-Administrador
A24: 21 | B24: ORIGINAL BRASIL COMERCIO IMPORTACAO E EXPORTACAO LTDA | C24: SP | D24: 72980642 | E24: 48.57 | F24: 🔴 ALTA | G24: R$ 20-30M | H24: 21282628 | I24: 1 | J24: 2 | K24: 2024 | L24: R D Ativa - Multa Isolada | M24: 2024 | N24: AJUIZADA_SEM_GAR | O24: =TEXT(D24,"00000000")&"0001" -> 729806420001 | P24: =IF(MOD(MID(O24,1,1)*5+MID(O24,2,1)*4+MID(O24,3,1)*3+MID(O24,4,1)*2+MID(O24,5,1)*9+MID(O24,6,1)*8+MID(O24,7,1)*7+MID(O24,8,1)*6+MID(O24,9,1)*5+MID(O24,10,1)*4+MID(O24,11,1)*3+MID(O24,12,1)*2,11)<2,0,11-MOD(MID(O24,1,1)*5+MID(O24,2,1)*4+MID(O24,3,1)*3+MID(O24,4,1)*2+MID(O24,5,1)*9+MID(O24,6,1)*8+MID(O24,7,1)*7+MID(O24,8,1)*6+MID(O24,9,1)*5+MID(O24,10,1)*4+MID(O24,11,1)*3+MID(O24,12,1)*2,11)) -> 0 | Q24: =IF(MOD(MID(O24,1,1)*6+MID(O24,2,1)*5+MID(O24,3,1)*4+MID(O24,4,1)*3+MID(O24,5,1)*2+MID(O24,6,1)*9+MID(O24,7,1)*8+MID(O24,8,1)*7+MID(O24,9,1)*6+MID(O24,10,1)*5+MID(O24,11,1)*4+MID(O24,12,1)*3+P24*2,11)<2,0,11-MOD(MID(O24,1,1)*6+MID(O24,2,1)*5+MID(O24,3,1)*4+MID(O24,4,1)*3+MID(O24,5,1)*2+MID(O24,6,1)*9+MID(O24,7,1)*8+MID(O24,8,1)*7+MID(O24,9,1)*6+MID(O24,10,1)*5+MID(O24,11,1)*4+MID(O24,12,1)*3+P24*2,11)) -> 5 | R24: =MID(O24,1,2)&"."&MID(O24,3,3)&"."&MID(O24,6,3)&"/"&MID(O24,9,4)&"-"&TEXT(P24,"0")&TEXT(Q24,"0") -> 72.980.642/0001-05 | T24: =IF(S24="","",IF(S24="Cadastrou","",XLOOKUP(S24,$BA$2:$BA$6,$BB$2:$BB$6,""))) | U24: =IF(S24="","",IF(S24="Cadastrou","",XLOOKUP(S24,$BA$2:$BA$6,$BC$2:$BC$6,""))) | V24: =IF(S24="","",XLOOKUP(S24,$BA$2:$BA$6,$BD$2:$BD$6,"")) | AA24: =IF(Y24="","",IF(INT(TODAY()-Y24)<0,"⚠️ Data futura",INT(TODAY()-Y24))) | AB24: =IF(AA24="","",IF(Z24="",IF(AA24>14,"🔴 Atrasado",IF(AA24>7,"🟡 Atenção","🟢 Em dia")),IF(TODAY()>Z24,"🔴 Atrasado",IF(Z24-TODAY()<=3,"🟡 Atenção","🟢 Em dia")))) | AD24: =IF(OR(AC24="",H24=""),"",H24*AC24) | AF24: =IF(AC24>0,AC24,'⚙️ Config'!$B$10) -> 0.0075 | AG24: =H24*AF24 -> 159619.71 | AH24: =AG24*'⚙️ Config'!$B$11 -> 798098.54 | AI24: =AH24*'⚙️ Config'!$B$12 -> 239429.56 | AJ24: 600000 | AM24: (11) 2657-4485 | AN24: apoio@originalbr.com.br | AO24: APARECIDO DONIZETI DA SILVA | AP24: Sócio-Administrador
A25: 22 | B25: VLADS INTERMEDIACOES E SERVICOS ADMINISTRATIVOS LTDA | C25: SP | D25: 28365646 | E25: 43.87 | F25: 🔴 ALTA | G25: R$ 20-30M | H25: 20121101 | I25: 2 | J25: 1.6 | K25: 2024 | L25: Receita da dívida ativa - CSLL | Receita da dívida ativa - IRPJ | M25: 2024 | N25: COBRANCA | O25: =TEXT(D25,"00000000")&"0001" -> 283656460001 | P25: =IF(MOD(MID(O25,1,1)*5+MID(O25,2,1)*4+MID(O25,3,1)*3+MID(O25,4,1)*2+MID(O25,5,1)*9+MID(O25,6,1)*8+MID(O25,7,1)*7+MID(O25,8,1)*6+MID(O25,9,1)*5+MID(O25,10,1)*4+MID(O25,11,1)*3+MID(O25,12,1)*2,11)<2,0,11-MOD(MID(O25,1,1)*5+MID(O25,2,1)*4+MID(O25,3,1)*3+MID(O25,4,1)*2+MID(O25,5,1)*9+MID(O25,6,1)*8+MID(O25,7,1)*7+MID(O25,8,1)*6+MID(O25,9,1)*5+MID(O25,10,1)*4+MID(O25,11,1)*3+MID(O25,12,1)*2,11)) -> 9 | Q25: =IF(MOD(MID(O25,1,1)*6+MID(O25,2,1)*5+MID(O25,3,1)*4+MID(O25,4,1)*3+MID(O25,5,1)*2+MID(O25,6,1)*9+MID(O25,7,1)*8+MID(O25,8,1)*7+MID(O25,9,1)*6+MID(O25,10,1)*5+MID(O25,11,1)*4+MID(O25,12,1)*3+P25*2,11)<2,0,11-MOD(MID(O25,1,1)*6+MID(O25,2,1)*5+MID(O25,3,1)*4+MID(O25,4,1)*3+MID(O25,5,1)*2+MID(O25,6,1)*9+MID(O25,7,1)*8+MID(O25,8,1)*7+MID(O25,9,1)*6+MID(O25,10,1)*5+MID(O25,11,1)*4+MID(O25,12,1)*3+P25*2,11)) -> 1 | R25: =MID(O25,1,2)&"."&MID(O25,3,3)&"."&MID(O25,6,3)&"/"&MID(O25,9,4)&"-"&TEXT(P25,"0")&TEXT(Q25,"0") -> 28.365.646/0001-91 | T25: =IF(S25="","",IF(S25="Cadastrou","",XLOOKUP(S25,$BA$2:$BA$6,$BB$2:$BB$6,""))) | U25: =IF(S25="","",IF(S25="Cadastrou","",XLOOKUP(S25,$BA$2:$BA$6,$BC$2:$BC$6,""))) | V25: =IF(S25="","",XLOOKUP(S25,$BA$2:$BA$6,$BD$2:$BD$6,"")) | AA25: =IF(Y25="","",IF(INT(TODAY()-Y25)<0,"⚠️ Data futura",INT(TODAY()-Y25))) | AB25: =IF(AA25="","",IF(Z25="",IF(AA25>14,"🔴 Atrasado",IF(AA25>7,"🟡 Atenção","🟢 Em dia")),IF(TODAY()>Z25,"🔴 Atrasado",IF(Z25-TODAY()<=3,"🟡 Atenção","🟢 Em dia")))) | AD25: =IF(OR(AC25="",H25=""),"",H25*AC25) | AF25: =IF(AC25>0,AC25,'⚙️ Config'!$B$10) -> 0.0075 | AG25: =H25*AF25 -> 150908.26 | AH25: =AG25*'⚙️ Config'!$B$11 -> 754541.3 | AI25: =AH25*'⚙️ Config'!$B$12 -> 226362.39 | AJ25: 150000 | AM25: (11) 3500-9994 | AN25: contato@dacbrasil.com | AO25: VLADMIR RODRIGUES DE SALES | AP25: Sócio-Administrador
A26: 23 | B26: ICBA INDUSTRIA E COMERCIO DE BANCOS AUTOMOTIVOS LTDA. | C26: SP | D26: 51966612 | E26: 47.37 | F26: 🔴 ALTA | G26: R$ 10-20M | H26: 19721771 | I26: 2 | J26: 1.4 | K26: 2024 | L26: Receita da dívida ativa - Imposto de Importação | IPI - Receita da dívida ativa | M26: 2024 | N26: AJUIZADA_SEM_GAR | O26: =TEXT(D26,"00000000")&"0001" -> 519666120001 | P26: =IF(MOD(MID(O26,1,1)*5+MID(O26,2,1)*4+MID(O26,3,1)*3+MID(O26,4,1)*2+MID(O26,5,1)*9+MID(O26,6,1)*8+MID(O26,7,1)*7+MID(O26,8,1)*6+MID(O26,9,1)*5+MID(O26,10,1)*4+MID(O26,11,1)*3+MID(O26,12,1)*2,11)<2,0,11-MOD(MID(O26,1,1)*5+MID(O26,2,1)*4+MID(O26,3,1)*3+MID(O26,4,1)*2+MID(O26,5,1)*9+MID(O26,6,1)*8+MID(O26,7,1)*7+MID(O26,8,1)*6+MID(O26,9,1)*5+MID(O26,10,1)*4+MID(O26,11,1)*3+MID(O26,12,1)*2,11)) -> 7 | Q26: =IF(MOD(MID(O26,1,1)*6+MID(O26,2,1)*5+MID(O26,3,1)*4+MID(O26,4,1)*3+MID(O26,5,1)*2+MID(O26,6,1)*9+MID(O26,7,1)*8+MID(O26,8,1)*7+MID(O26,9,1)*6+MID(O26,10,1)*5+MID(O26,11,1)*4+MID(O26,12,1)*3+P26*2,11)<2,0,11-MOD(MID(O26,1,1)*6+MID(O26,2,1)*5+MID(O26,3,1)*4+MID(O26,4,1)*3+MID(O26,5,1)*2+MID(O26,6,1)*9+MID(O26,7,1)*8+MID(O26,8,1)*7+MID(O26,9,1)*6+MID(O26,10,1)*5+MID(O26,11,1)*4+MID(O26,12,1)*3+P26*2,11)) -> 4 | R26: =MID(O26,1,2)&"."&MID(O26,3,3)&"."&MID(O26,6,3)&"/"&MID(O26,9,4)&"-"&TEXT(P26,"0")&TEXT(Q26,"0") -> 51.966.612/0001-74 | T26: =IF(S26="","",IF(S26="Cadastrou","",XLOOKUP(S26,$BA$2:$BA$6,$BB$2:$BB$6,""))) | U26: =IF(S26="","",IF(S26="Cadastrou","",XLOOKUP(S26,$BA$2:$BA$6,$BC$2:$BC$6,""))) | V26: =IF(S26="","",XLOOKUP(S26,$BA$2:$BA$6,$BD$2:$BD$6,"")) | AA26: =IF(Y26="","",IF(INT(TODAY()-Y26)<0,"⚠️ Data futura",INT(TODAY()-Y26))) | AB26: =IF(AA26="","",IF(Z26="",IF(AA26>14,"🔴 Atrasado",IF(AA26>7,"🟡 Atenção","🟢 Em dia")),IF(TODAY()>Z26,"🔴 Atrasado",IF(Z26-TODAY()<=3,"🟡 Atenção","🟢 Em dia")))) | AD26: =IF(OR(AC26="",H26=""),"",H26*AC26) | AF26: =IF(AC26>0,AC26,'⚙️ Config'!$B$10) -> 0.0075 | AG26: =H26*AF26 -> 147913.28 | AH26: =AG26*'⚙️ Config'!$B$11 -> 739566.41 | AI26: =AH26*'⚙️ Config'!$B$12 -> 221869.92 | AJ26: 63891397 | AM26: (11) 6160-9425 | AN26: mac@keiper.com.br | AO26: CRISTINA CEZAR BASTIANELLO | AP26: Administrador
A27: 24 | B27: AGROPECUARIA PONTE ALTA LTDA | C27: MS | D27: 00983080 | E27: 61.69 | F27: 🔴 ALTA | G27: R$ 10-20M | H27: 19252926 | I27: 1 | J27: 1.2 | K27: 2024 | L27: Receita da dívida ativa - CSLL | M27: 2024 | N27: AJUIZADA_SEM_GAR | O27: =TEXT(D27,"00000000")&"0001" -> 009830800001 | P27: =IF(MOD(MID(O27,1,1)*5+MID(O27,2,1)*4+MID(O27,3,1)*3+MID(O27,4,1)*2+MID(O27,5,1)*9+MID(O27,6,1)*8+MID(O27,7,1)*7+MID(O27,8,1)*6+MID(O27,9,1)*5+MID(O27,10,1)*4+MID(O27,11,1)*3+MID(O27,12,1)*2,11)<2,0,11-MOD(MID(O27,1,1)*5+MID(O27,2,1)*4+MID(O27,3,1)*3+MID(O27,4,1)*2+MID(O27,5,1)*9+MID(O27,6,1)*8+MID(O27,7,1)*7+MID(O27,8,1)*6+MID(O27,9,1)*5+MID(O27,10,1)*4+MID(O27,11,1)*3+MID(O27,12,1)*2,11)) -> 4 | Q27: =IF(MOD(MID(O27,1,1)*6+MID(O27,2,1)*5+MID(O27,3,1)*4+MID(O27,4,1)*3+MID(O27,5,1)*2+MID(O27,6,1)*9+MID(O27,7,1)*8+MID(O27,8,1)*7+MID(O27,9,1)*6+MID(O27,10,1)*5+MID(O27,11,1)*4+MID(O27,12,1)*3+P27*2,11)<2,0,11-MOD(MID(O27,1,1)*6+MID(O27,2,1)*5+MID(O27,3,1)*4+MID(O27,4,1)*3+MID(O27,5,1)*2+MID(O27,6,1)*9+MID(O27,7,1)*8+MID(O27,8,1)*7+MID(O27,9,1)*6+MID(O27,10,1)*5+MID(O27,11,1)*4+MID(O27,12,1)*3+P27*2,11)) -> 2 | R27: =MID(O27,1,2)&"."&MID(O27,3,3)&"."&MID(O27,6,3)&"/"&MID(O27,9,4)&"-"&TEXT(P27,"0")&TEXT(Q27,"0") -> 00.983.080/0001-42 | T27: =IF(S27="","",IF(S27="Cadastrou","",XLOOKUP(S27,$BA$2:$BA$6,$BB$2:$BB$6,""))) | U27: =IF(S27="","",IF(S27="Cadastrou","",XLOOKUP(S27,$BA$2:$BA$6,$BC$2:$BC$6,""))) | V27: =IF(S27="","",XLOOKUP(S27,$BA$2:$BA$6,$BD$2:$BD$6,"")) | AA27: =IF(Y27="","",IF(INT(TODAY()-Y27)<0,"⚠️ Data futura",INT(TODAY()-Y27))) | AB27: =IF(AA27="","",IF(Z27="",IF(AA27>14,"🔴 Atrasado",IF(AA27>7,"🟡 Atenção","🟢 Em dia")),IF(TODAY()>Z27,"🔴 Atrasado",IF(Z27-TODAY()<=3,"🟡 Atenção","🟢 Em dia")))) | AD27: =IF(OR(AC27="",H27=""),"",H27*AC27) | AF27: =IF(AC27>0,AC27,'⚙️ Config'!$B$10) -> 0.0075 | AG27: =H27*AF27 -> 144396.94 | AH27: =AG27*'⚙️ Config'!$B$11 -> 721984.71 | AI27: =AH27*'⚙️ Config'!$B$12 -> 216595.41 | AJ27: 300000 | AM27: (67) 3301-7312 | AN27: esccom@terra.com.br | AO27: PAULO RENATO KOVALSKI | AP27: Sócio-Administrador
A28: 25 | B28: EVINO COMERCIO DE VINHOS S.A. | C28: SP | D28: 17392519 | E28: 64.36 | F28: 🔴 ALTA | G28: R$ 10-20M | H28: 19183560 | I28: 2 | J28: 0.8 | K28: 2025 | L28: Receita da dívida ativa - PIS | Receita da dívida ativa - COFINS | M28: 2025 | N28: COBRANCA | O28: =TEXT(D28,"00000000")&"0001" -> 173925190001 | P28: =IF(MOD(MID(O28,1,1)*5+MID(O28,2,1)*4+MID(O28,3,1)*3+MID(O28,4,1)*2+MID(O28,5,1)*9+MID(O28,6,1)*8+MID(O28,7,1)*7+MID(O28,8,1)*6+MID(O28,9,1)*5+MID(O28,10,1)*4+MID(O28,11,1)*3+MID(O28,12,1)*2,11)<2,0,11-MOD(MID(O28,1,1)*5+MID(O28,2,1)*4+MID(O28,3,1)*3+MID(O28,4,1)*2+MID(O28,5,1)*9+MID(O28,6,1)*8+MID(O28,7,1)*7+MID(O28,8,1)*6+MID(O28,9,1)*5+MID(O28,10,1)*4+MID(O28,11,1)*3+MID(O28,12,1)*2,11)) -> 6 | Q28: =IF(MOD(MID(O28,1,1)*6+MID(O28,2,1)*5+MID(O28,3,1)*4+MID(O28,4,1)*3+MID(O28,5,1)*2+MID(O28,6,1)*9+MID(O28,7,1)*8+MID(O28,8,1)*7+MID(O28,9,1)*6+MID(O28,10,1)*5+MID(O28,11,1)*4+MID(O28,12,1)*3+P28*2,11)<2,0,11-MOD(MID(O28,1,1)*6+MID(O28,2,1)*5+MID(O28,3,1)*4+MID(O28,4,1)*3+MID(O28,5,1)*2+MID(O28,6,1)*9+MID(O28,7,1)*8+MID(O28,8,1)*7+MID(O28,9,1)*6+MID(O28,10,1)*5+MID(O28,11,1)*4+MID(O28,12,1)*3+P28*2,11)) -> 5 | R28: =MID(O28,1,2)&"."&MID(O28,3,3)&"."&MID(O28,6,3)&"/"&MID(O28,9,4)&"-"&TEXT(P28,"0")&TEXT(Q28,"0") -> 17.392.519/0001-65 | T28: =IF(S28="","",IF(S28="Cadastrou","",XLOOKUP(S28,$BA$2:$BA$6,$BB$2:$BB$6,""))) | U28: =IF(S28="","",IF(S28="Cadastrou","",XLOOKUP(S28,$BA$2:$BA$6,$BC$2:$BC$6,""))) | V28: =IF(S28="","",XLOOKUP(S28,$BA$2:$BA$6,$BD$2:$BD$6,"")) | AA28: =IF(Y28="","",IF(INT(TODAY()-Y28)<0,"⚠️ Data futura",INT(TODAY()-Y28))) | AB28: =IF(AA28="","",IF(Z28="",IF(AA28>14,"🔴 Atrasado",IF(AA28>7,"🟡 Atenção","🟢 Em dia")),IF(TODAY()>Z28,"🔴 Atrasado",IF(Z28-TODAY()<=3,"🟡 Atenção","🟢 Em dia")))) | AD28: =IF(OR(AC28="",H28=""),"",H28*AC28) | AF28: =IF(AC28>0,AC28,'⚙️ Config'!$B$10) -> 0.0075 | AG28: =H28*AF28 -> 143876.7 | AH28: =AG28*'⚙️ Config'!$B$11 -> 719383.49 | AI28: =AH28*'⚙️ Config'!$B$12 -> 215815.05 | AM28: (11) 4200-4999 | AN28: fiscal@evino.com.br | AO28: PATRICIA COULON PERIM | AP28: Diretor
A29: 26 | B29: TRANSPORTES EXECUTIVOS M.C. LTDA | C29: SP | D29: 19254407 | E29: 57.18 | F29: 🔴 ALTA | G29: R$ 10-20M | H29: 19012374 | I29: 2 | J29: 1 | K29: 2025 | L29: Receita da dívida ativa - CSLL | R D Ativa - Multa Isolada | M29: 2025 | N29: COBRANCA | O29: =TEXT(D29,"00000000")&"0001" -> 192544070001 | P29: =IF(MOD(MID(O29,1,1)*5+MID(O29,2,1)*4+MID(O29,3,1)*3+MID(O29,4,1)*2+MID(O29,5,1)*9+MID(O29,6,1)*8+MID(O29,7,1)*7+MID(O29,8,1)*6+MID(O29,9,1)*5+MID(O29,10,1)*4+MID(O29,11,1)*3+MID(O29,12,1)*2,11)<2,0,11-MOD(MID(O29,1,1)*5+MID(O29,2,1)*4+MID(O29,3,1)*3+MID(O29,4,1)*2+MID(O29,5,1)*9+MID(O29,6,1)*8+MID(O29,7,1)*7+MID(O29,8,1)*6+MID(O29,9,1)*5+MID(O29,10,1)*4+MID(O29,11,1)*3+MID(O29,12,1)*2,11)) -> 7 | Q29: =IF(MOD(MID(O29,1,1)*6+MID(O29,2,1)*5+MID(O29,3,1)*4+MID(O29,4,1)*3+MID(O29,5,1)*2+MID(O29,6,1)*9+MID(O29,7,1)*8+MID(O29,8,1)*7+MID(O29,9,1)*6+MID(O29,10,1)*5+MID(O29,11,1)*4+MID(O29,12,1)*3+P29*2,11)<2,0,11-MOD(MID(O29,1,1)*6+MID(O29,2,1)*5+MID(O29,3,1)*4+MID(O29,4,1)*3+MID(O29,5,1)*2+MID(O29,6,1)*9+MID(O29,7,1)*8+MID(O29,8,1)*7+MID(O29,9,1)*6+MID(O29,10,1)*5+MID(O29,11,1)*4+MID(O29,12,1)*3+P29*2,11)) -> 3 | R29: =MID(O29,1,2)&"."&MID(O29,3,3)&"."&MID(O29,6,3)&"/"&MID(O29,9,4)&"-"&TEXT(P29,"0")&TEXT(Q29,"0") -> 19.254.407/0001-73 | T29: =IF(S29="","",IF(S29="Cadastrou","",XLOOKUP(S29,$BA$2:$BA$6,$BB$2:$BB$6,""))) | U29: =IF(S29="","",IF(S29="Cadastrou","",XLOOKUP(S29,$BA$2:$BA$6,$BC$2:$BC$6,""))) | V29: =IF(S29="","",XLOOKUP(S29,$BA$2:$BA$6,$BD$2:$BD$6,"")) | AA29: =IF(Y29="","",IF(INT(TODAY()-Y29)<0,"⚠️ Data futura",INT(TODAY()-Y29))) | AB29: =IF(AA29="","",IF(Z29="",IF(AA29>14,"🔴 Atrasado",IF(AA29>7,"🟡 Atenção","🟢 Em dia")),IF(TODAY()>Z29,"🔴 Atrasado",IF(Z29-TODAY()<=3,"🟡 Atenção","🟢 Em dia")))) | AD29: =IF(OR(AC29="",H29=""),"",H29*AC29) | AF29: =IF(AC29>0,AC29,'⚙️ Config'!$B$10) -> 0.0075 | AG29: =H29*AF29 -> 142592.8 | AH29: =AG29*'⚙️ Config'!$B$11 -> 712964.02 | AI29: =AH29*'⚙️ Config'!$B$12 -> 213889.21 | AJ29: 5000000 | AM29: (11) 4115-5557 | AN29: transportesexecutivosmc@hotmail.com | AO29: PAULO RODRIGUES COELHO | AP29: Sócio-Administrador
A30: 27 | B30: ED FORT COMERCIAL IMPORTADORA E EXPORTADORA LTDA | C30: SP | D30: 01468951 | E30: 49.67 | F30: 🔴 ALTA | G30: R$ 10-20M | H30: 18787148 | I30: 1 | J30: 1.9 | K30: 2024 | L30: IPI - Receita da dívida ativa | M30: 2024 | N30: COBRANCA | O30: =TEXT(D30,"00000000")&"0001" -> 014689510001 | P30: =IF(MOD(MID(O30,1,1)*5+MID(O30,2,1)*4+MID(O30,3,1)*3+MID(O30,4,1)*2+MID(O30,5,1)*9+MID(O30,6,1)*8+MID(O30,7,1)*7+MID(O30,8,1)*6+MID(O30,9,1)*5+MID(O30,10,1)*4+MID(O30,11,1)*3+MID(O30,12,1)*2,11)<2,0,11-MOD(MID(O30,1,1)*5+MID(O30,2,1)*4+MID(O30,3,1)*3+MID(O30,4,1)*2+MID(O30,5,1)*9+MID(O30,6,1)*8+MID(O30,7,1)*7+MID(O30,8,1)*6+MID(O30,9,1)*5+MID(O30,10,1)*4+MID(O30,11,1)*3+MID(O30,12,1)*2,11)) -> 5 | Q30: =IF(MOD(MID(O30,1,1)*6+MID(O30,2,1)*5+MID(O30,3,1)*4+MID(O30,4,1)*3+MID(O30,5,1)*2+MID(O30,6,1)*9+MID(O30,7,1)*8+MID(O30,8,1)*7+MID(O30,9,1)*6+MID(O30,10,1)*5+MID(O30,11,1)*4+MID(O30,12,1)*3+P30*2,11)<2,0,11-MOD(MID(O30,1,1)*6+MID(O30,2,1)*5+MID(O30,3,1)*4+MID(O30,4,1)*3+MID(O30,5,1)*2+MID(O30,6,1)*9+MID(O30,7,1)*8+MID(O30,8,1)*7+MID(O30,9,1)*6+MID(O30,10,1)*5+MID(O30,11,1)*4+MID(O30,12,1)*3+P30*2,11)) -> 2 | R30: =MID(O30,1,2)&"."&MID(O30,3,3)&"."&MID(O30,6,3)&"/"&MID(O30,9,4)&"-"&TEXT(P30,"0")&TEXT(Q30,"0") -> 01.468.951/0001-52 | T30: =IF(S30="","",IF(S30="Cadastrou","",XLOOKUP(S30,$BA$2:$BA$6,$BB$2:$BB$6,""))) | U30: =IF(S30="","",IF(S30="Cadastrou","",XLOOKUP(S30,$BA$2:$BA$6,$BC$2:$BC$6,""))) | V30: =IF(S30="","",XLOOKUP(S30,$BA$2:$BA$6,$BD$2:$BD$6,"")) | AA30: =IF(Y30="","",IF(INT(TODAY()-Y30)<0,"⚠️ Data futura",INT(TODAY()-Y30))) | AB30: =IF(AA30="","",IF(Z30="",IF(AA30>14,"🔴 Atrasado",IF(AA30>7,"🟡 Atenção","🟢 Em dia")),IF(TODAY()>Z30,"🔴 Atrasado",IF(Z30-TODAY()<=3,"🟡 Atenção","🟢 Em dia")))) | AD30: =IF(OR(AC30="",H30=""),"",H30*AC30) | AF30: =IF(AC30>0,AC30,'⚙️ Config'!$B$10) -> 0.0075 | AG30: =H30*AF30 -> 140903.61 | AH30: =AG30*'⚙️ Config'!$B$11 -> 704518.04 | AI30: =AH30*'⚙️ Config'!$B$12 -> 211355.41 | AJ30: 800000 | AM30: (11) 3661-8500 | AN30: adm@spdccontabil.com.br
A31: 28 | B31: EPS EMPRESA PAULISTA DE SERVICOS S.A. | C31: SP | D31: 61244034 | E31: 86.55 | F31: 🔴 ALTA | G31: R$ 10-20M | H31: 17995601 | I31: 1 | J31: 0.9 | K31: 2025 | L31: Receita da dívida ativa - COFINS | R D Ativa - Glosa de Compensação Previdenciária | M31: 2025 | N31: AJUIZADA_SEM_GAR|OUTROS | O31: =TEXT(D31,"00000000")&"0001" -> 612440340001 | P31: =IF(MOD(MID(O31,1,1)*5+MID(O31,2,1)*4+MID(O31,3,1)*3+MID(O31,4,1)*2+MID(O31,5,1)*9+MID(O31,6,1)*8+MID(O31,7,1)*7+MID(O31,8,1)*6+MID(O31,9,1)*5+MID(O31,10,1)*4+MID(O31,11,1)*3+MID(O31,12,1)*2,11)<2,0,11-MOD(MID(O31,1,1)*5+MID(O31,2,1)*4+MID(O31,3,1)*3+MID(O31,4,1)*2+MID(O31,5,1)*9+MID(O31,6,1)*8+MID(O31,7,1)*7+MID(O31,8,1)*6+MID(O31,9,1)*5+MID(O31,10,1)*4+MID(O31,11,1)*3+MID(O31,12,1)*2,11)) -> 1 | Q31: =IF(MOD(MID(O31,1,1)*6+MID(O31,2,1)*5+MID(O31,3,1)*4+MID(O31,4,1)*3+MID(O31,5,1)*2+MID(O31,6,1)*9+MID(O31,7,1)*8+MID(O31,8,1)*7+MID(O31,9,1)*6+MID(O31,10,1)*5+MID(O31,11,1)*4+MID(O31,12,1)*3+P31*2,11)<2,0,11-MOD(MID(O31,1,1)*6+MID(O31,2,1)*5+MID(O31,3,1)*4+MID(O31,4,1)*3+MID(O31,5,1)*2+MID(O31,6,1)*9+MID(O31,7,1)*8+MID(O31,8,1)*7+MID(O31,9,1)*6+MID(O31,10,1)*5+MID(O31,11,1)*4+MID(O31,12,1)*3+P31*2,11)) -> 6 | R31: =MID(O31,1,2)&"."&MID(O31,3,3)&"."&MID(O31,6,3)&"/"&MID(O31,9,4)&"-"&TEXT(P31,"0")&TEXT(Q31,"0") -> 61.244.034/0001-16 | T31: =IF(S31="","",IF(S31="Cadastrou","",XLOOKUP(S31,$BA$2:$BA$6,$BB$2:$BB$6,""))) | U31: =IF(S31="","",IF(S31="Cadastrou","",XLOOKUP(S31,$BA$2:$BA$6,$BC$2:$BC$6,""))) | V31: =IF(S31="","",XLOOKUP(S31,$BA$2:$BA$6,$BD$2:$BD$6,"")) | AA31: =IF(Y31="","",IF(INT(TODAY()-Y31)<0,"⚠️ Data futura",INT(TODAY()-Y31))) | AB31: =IF(AA31="","",IF(Z31="",IF(AA31>14,"🔴 Atrasado",IF(AA31>7,"🟡 Atenção","🟢 Em dia")),IF(TODAY()>Z31,"🔴 Atrasado",IF(Z31-TODAY()<=3,"🟡 Atenção","🟢 Em dia")))) | AD31: =IF(OR(AC31="",H31=""),"",H31*AC31) | AF31: =IF(AC31>0,AC31,'⚙️ Config'!$B$10) -> 0.0075 | AG31: =H31*AF31 -> 134967.01 | AH31: =AG31*'⚙️ Config'!$B$11 -> 674835.05 | AI31: =AH31*'⚙️ Config'!$B$12 -> 202450.51 | AJ31: 21500000 | AM31: (11) 4785-1600 | AN31: controladoria@grupogtp.com.br | AO31: FRANKLIN KUPERMAN | AP31: Presidente
A32: 29 | B32: TINTAS MC LTDA | C32: SP | D32: 61149506 | E32: 74.11 | F32: 🔴 ALTA | G32: R$ 10-20M | H32: 17586178 | I32: 2 | J32: 0.6 | K32: 2025 | L32: Receita da dívida ativa - PIS | Receita da dívida ativa - COFINS | M32: 2025 | N32: COBRANCA | O32: =TEXT(D32,"00000000")&"0001" -> 611495060001 | P32: =IF(MOD(MID(O32,1,1)*5+MID(O32,2,1)*4+MID(O32,3,1)*3+MID(O32,4,1)*2+MID(O32,5,1)*9+MID(O32,6,1)*8+MID(O32,7,1)*7+MID(O32,8,1)*6+MID(O32,9,1)*5+MID(O32,10,1)*4+MID(O32,11,1)*3+MID(O32,12,1)*2,11)<2,0,11-MOD(MID(O32,1,1)*5+MID(O32,2,1)*4+MID(O32,3,1)*3+MID(O32,4,1)*2+MID(O32,5,1)*9+MID(O32,6,1)*8+MID(O32,7,1)*7+MID(O32,8,1)*6+MID(O32,9,1)*5+MID(O32,10,1)*4+MID(O32,11,1)*3+MID(O32,12,1)*2,11)) -> 5 | Q32: =IF(MOD(MID(O32,1,1)*6+MID(O32,2,1)*5+MID(O32,3,1)*4+MID(O32,4,1)*3+MID(O32,5,1)*2+MID(O32,6,1)*9+MID(O32,7,1)*8+MID(O32,8,1)*7+MID(O32,9,1)*6+MID(O32,10,1)*5+MID(O32,11,1)*4+MID(O32,12,1)*3+P32*2,11)<2,0,11-MOD(MID(O32,1,1)*6+MID(O32,2,1)*5+MID(O32,3,1)*4+MID(O32,4,1)*3+MID(O32,5,1)*2+MID(O32,6,1)*9+MID(O32,7,1)*8+MID(O32,8,1)*7+MID(O32,9,1)*6+MID(O32,10,1)*5+MID(O32,11,1)*4+MID(O32,12,1)*3+P32*2,11)) -> 1 | R32: =MID(O32,1,2)&"."&MID(O32,3,3)&"."&MID(O32,6,3)&"/"&MID(O32,9,4)&"-"&TEXT(P32,"0")&TEXT(Q32,"0") -> 61.149.506/0001-51 | T32: =IF(S32="","",IF(S32="Cadastrou","",XLOOKUP(S32,$BA$2:$BA$6,$BB$2:$BB$6,""))) | U32: =IF(S32="","",IF(S32="Cadastrou","",XLOOKUP(S32,$BA$2:$BA$6,$BC$2:$BC$6,""))) | V32: =IF(S32="","",XLOOKUP(S32,$BA$2:$BA$6,$BD$2:$BD$6,"")) | AA32: =IF(Y32="","",IF(INT(TODAY()-Y32)<0,"⚠️ Data futura",INT(TODAY()-Y32))) | AB32: =IF(AA32="","",IF(Z32="",IF(AA32>14,"🔴 Atrasado",IF(AA32>7,"🟡 Atenção","🟢 Em dia")),IF(TODAY()>Z32,"🔴 Atrasado",IF(Z32-TODAY()<=3,"🟡 Atenção","🟢 Em dia")))) | AD32: =IF(OR(AC32="",H32=""),"",H32*AC32) | AF32: =IF(AC32>0,AC32,'⚙️ Config'!$B$10) -> 0.0075 | AG32: =H32*AF32 -> 131896.33 | AH32: =AG32*'⚙️ Config'!$B$11 -> 659481.67 | AI32: =AH32*'⚙️ Config'!$B$12 -> 197844.5 | AJ32: 8722892 | AM32: (19) 8111-4665 | AN32: fiscal@tintasmc.com.br | AO32: JOSE ROBERTO BRUNO SILVA | AP32: Administrador
A33: 30 | B33: CEG COMERCIALIZADORA DE ETANOL SA | C33: SP | D33: 07308871 | E33: 51.65 | F33: 🔴 ALTA | G33: R$ 10-20M | H33: 17567739 | I33: 2 | J33: 1.2 | K33: 2025 | L33: Receita da dívida ativa - PIS | Receita da dívida ativa - COFINS | M33: 2025 | N33: AJUIZADA_SEM_GAR | O33: =TEXT(D33,"00000000")&"0001" -> 073088710001 | P33: =IF(MOD(MID(O33,1,1)*5+MID(O33,2,1)*4+MID(O33,3,1)*3+MID(O33,4,1)*2+MID(O33,5,1)*9+MID(O33,6,1)*8+MID(O33,7,1)*7+MID(O33,8,1)*6+MID(O33,9,1)*5+MID(O33,10,1)*4+MID(O33,11,1)*3+MID(O33,12,1)*2,11)<2,0,11-MOD(MID(O33,1,1)*5+MID(O33,2,1)*4+MID(O33,3,1)*3+MID(O33,4,1)*2+MID(O33,5,1)*9+MID(O33,6,1)*8+MID(O33,7,1)*7+MID(O33,8,1)*6+MID(O33,9,1)*5+MID(O33,10,1)*4+MID(O33,11,1)*3+MID(O33,12,1)*2,11)) -> 1 | Q33: =IF(MOD(MID(O33,1,1)*6+MID(O33,2,1)*5+MID(O33,3,1)*4+MID(O33,4,1)*3+MID(O33,5,1)*2+MID(O33,6,1)*9+MID(O33,7,1)*8+MID(O33,8,1)*7+MID(O33,9,1)*6+MID(O33,10,1)*5+MID(O33,11,1)*4+MID(O33,12,1)*3+P33*2,11)<2,0,11-MOD(MID(O33,1,1)*6+MID(O33,2,1)*5+MID(O33,3,1)*4+MID(O33,4,1)*3+MID(O33,5,1)*2+MID(O33,6,1)*9+MID(O33,7,1)*8+MID(O33,8,1)*7+MID(O33,9,1)*6+MID(O33,10,1)*5+MID(O33,11,1)*4+MID(O33,12,1)*3+P33*2,11)) -> 6 | R33: =MID(O33,1,2)&"."&MID(O33,3,3)&"."&MID(O33,6,3)&"/"&MID(O33,9,4)&"-"&TEXT(P33,"0")&TEXT(Q33,"0") -> 07.308.871/0001-16 | T33: =IF(S33="","",IF(S33="Cadastrou","",XLOOKUP(S33,$BA$2:$BA$6,$BB$2:$BB$6,""))) | U33: =IF(S33="","",IF(S33="Cadastrou","",XLOOKUP(S33,$BA$2:$BA$6,$BC$2:$BC$6,""))) | V33: =IF(S33="","",XLOOKUP(S33,$BA$2:$BA$6,$BD$2:$BD$6,"")) | AA33: =IF(Y33="","",IF(INT(TODAY()-Y33)<0,"⚠️ Data futura",INT(TODAY()-Y33))) | AB33: =IF(AA33="","",IF(Z33="",IF(AA33>14,"🔴 Atrasado",IF(AA33>7,"🟡 Atenção","🟢 Em dia")),IF(TODAY()>Z33,"🔴 Atrasado",IF(Z33-TODAY()<=3,"🟡 Atenção","🟢 Em dia")))) | AD33: =IF(OR(AC33="",H33=""),"",H33*AC33) | AF33: =IF(AC33>0,AC33,'⚙️ Config'!$B$10) -> 0.0075 | AG33: =H33*AF33 -> 131758.04 | AH33: =AG33*'⚙️ Config'!$B$11 -> 658790.21 | AI33: =AH33*'⚙️ Config'!$B$12 -> 197637.06 | AJ33: 10000020 | AM33: (11) 2935-6440 | AN33: adilson@adilcont.com.br | AO33: GLAUCIO WILSON GOMES DE OLIVEIRA | AP33: Presidente
A34: 31 | B34: BRAZIL CHILE COMERCIO DE PRODUTOS INDUSTRIALIZADOS LTDA | C34: SP | D34: 47168504 | E34: 45.47 | F34: 🔴 ALTA | G34: R$ 10-20M | H34: 17476456 | I34: 2 | J34: 1.5 | K34: 2024 | L34: Receita da dívida ativa - PIS | Receita da dívida ativa - COFINS | M34: 2024 | N34: AJUIZADA_SEM_GAR | O34: =TEXT(D34,"00000000")&"0001" -> 471685040001 | P34: =IF(MOD(MID(O34,1,1)*5+MID(O34,2,1)*4+MID(O34,3,1)*3+MID(O34,4,1)*2+MID(O34,5,1)*9+MID(O34,6,1)*8+MID(O34,7,1)*7+MID(O34,8,1)*6+MID(O34,9,1)*5+MID(O34,10,1)*4+MID(O34,11,1)*3+MID(O34,12,1)*2,11)<2,0,11-MOD(MID(O34,1,1)*5+MID(O34,2,1)*4+MID(O34,3,1)*3+MID(O34,4,1)*2+MID(O34,5,1)*9+MID(O34,6,1)*8+MID(O34,7,1)*7+MID(O34,8,1)*6+MID(O34,9,1)*5+MID(O34,10,1)*4+MID(O34,11,1)*3+MID(O34,12,1)*2,11)) -> 8 | Q34: =IF(MOD(MID(O34,1,1)*6+MID(O34,2,1)*5+MID(O34,3,1)*4+MID(O34,4,1)*3+MID(O34,5,1)*2+MID(O34,6,1)*9+MID(O34,7,1)*8+MID(O34,8,1)*7+MID(O34,9,1)*6+MID(O34,10,1)*5+MID(O34,11,1)*4+MID(O34,12,1)*3+P34*2,11)<2,0,11-MOD(MID(O34,1,1)*6+MID(O34,2,1)*5+MID(O34,3,1)*4+MID(O34,4,1)*3+MID(O34,5,1)*2+MID(O34,6,1)*9+MID(O34,7,1)*8+MID(O34,8,1)*7+MID(O34,9,1)*6+MID(O34,10,1)*5+MID(O34,11,1)*4+MID(O34,12,1)*3+P34*2,11)) -> 9 | R34: =MID(O34,1,2)&"."&MID(O34,3,3)&"."&MID(O34,6,3)&"/"&MID(O34,9,4)&"-"&TEXT(P34,"0")&TEXT(Q34,"0") -> 47.168.504/0001-89 | T34: =IF(S34="","",IF(S34="Cadastrou","",XLOOKUP(S34,$BA$2:$BA$6,$BB$2:$BB$6,""))) | U34: =IF(S34="","",IF(S34="Cadastrou","",XLOOKUP(S34,$BA$2:$BA$6,$BC$2:$BC$6,""))) | V34: =IF(S34="","",XLOOKUP(S34,$BA$2:$BA$6,$BD$2:$BD$6,"")) | AA34: =IF(Y34="","",IF(INT(TODAY()-Y34)<0,"⚠️ Data futura",INT(TODAY()-Y34))) | AB34: =IF(AA34="","",IF(Z34="",IF(AA34>14,"🔴 Atrasado",IF(AA34>7,"🟡 Atenção","🟢 Em dia")),IF(TODAY()>Z34,"🔴 Atrasado",IF(Z34-TODAY()<=3,"🟡 Atenção","🟢 Em dia")))) | AD34: =IF(OR(AC34="",H34=""),"",H34*AC34) | AF34: =IF(AC34>0,AC34,'⚙️ Config'!$B$10) -> 0.0075 | AG34: =H34*AF34 -> 131073.42 | AH34: =AG34*'⚙️ Config'!$B$11 -> 655367.11 | AI34: =AH34*'⚙️ Config'!$B$12 -> 196610.13 | AJ34: 150000 | AM34: (11) 9351-3085 | AN34: rclementinoarruda@gmail.com | AO34: JIHAN KAMAL TOHME | AP34: Sócio-Administrador
A35: 32 | B35: DESIDERIO PLANTOES MEDICOS LTDA | C35: SP | D35: 17875313 | E35: 38.46 | F35: 🔴 ALTA | G35: R$ 10-20M | H35: 17316467 | I35: 2 | J35: 2 | K35: 2024 | L35: R D Ativa - Contribuição Empresa/Empregador | M35: 2024 | N35: AJUIZADA_SEM_GAR | O35: =TEXT(D35,"00000000")&"0001" -> 178753130001 | P35: =IF(MOD(MID(O35,1,1)*5+MID(O35,2,1)*4+MID(O35,3,1)*3+MID(O35,4,1)*2+MID(O35,5,1)*9+MID(O35,6,1)*8+MID(O35,7,1)*7+MID(O35,8,1)*6+MID(O35,9,1)*5+MID(O35,10,1)*4+MID(O35,11,1)*3+MID(O35,12,1)*2,11)<2,0,11-MOD(MID(O35,1,1)*5+MID(O35,2,1)*4+MID(O35,3,1)*3+MID(O35,4,1)*2+MID(O35,5,1)*9+MID(O35,6,1)*8+MID(O35,7,1)*7+MID(O35,8,1)*6+MID(O35,9,1)*5+MID(O35,10,1)*4+MID(O35,11,1)*3+MID(O35,12,1)*2,11)) -> 9 | Q35: =IF(MOD(MID(O35,1,1)*6+MID(O35,2,1)*5+MID(O35,3,1)*4+MID(O35,4,1)*3+MID(O35,5,1)*2+MID(O35,6,1)*9+MID(O35,7,1)*8+MID(O35,8,1)*7+MID(O35,9,1)*6+MID(O35,10,1)*5+MID(O35,11,1)*4+MID(O35,12,1)*3+P35*2,11)<2,0,11-MOD(MID(O35,1,1)*6+MID(O35,2,1)*5+MID(O35,3,1)*4+MID(O35,4,1)*3+MID(O35,5,1)*2+MID(O35,6,1)*9+MID(O35,7,1)*8+MID(O35,8,1)*7+MID(O35,9,1)*6+MID(O35,10,1)*5+MID(O35,11,1)*4+MID(O35,12,1)*3+P35*2,11)) -> 6 | R35: =MID(O35,1,2)&"."&MID(O35,3,3)&"."&MID(O35,6,3)&"/"&MID(O35,9,4)&"-"&TEXT(P35,"0")&TEXT(Q35,"0") -> 17.875.313/0001-96 | T35: =IF(S35="","",IF(S35="Cadastrou","",XLOOKUP(S35,$BA$2:$BA$6,$BB$2:$BB$6,""))) | U35: =IF(S35="","",IF(S35="Cadastrou","",XLOOKUP(S35,$BA$2:$BA$6,$BC$2:$BC$6,""))) | V35: =IF(S35="","",XLOOKUP(S35,$BA$2:$BA$6,$BD$2:$BD$6,"")) | AA35: =IF(Y35="","",IF(INT(TODAY()-Y35)<0,"⚠️ Data futura",INT(TODAY()-Y35))) | AB35: =IF(AA35="","",IF(Z35="",IF(AA35>14,"🔴 Atrasado",IF(AA35>7,"🟡 Atenção","🟢 Em dia")),IF(TODAY()>Z35,"🔴 Atrasado",IF(Z35-TODAY()<=3,"🟡 Atenção","🟢 Em dia")))) | AD35: =IF(OR(AC35="",H35=""),"",H35*AC35) | AF35: =IF(AC35>0,AC35,'⚙️ Config'!$B$10) -> 0.0075 | AG35: =H35*AF35 -> 129873.5 | AH35: =AG35*'⚙️ Config'!$B$11 -> 649367.5 | AI35: =AH35*'⚙️ Config'!$B$12 -> 194810.25 | AM35: (16) 3916-5890 | AN35: marcio.souto@grupomscontabilidade.com.br | AO35: VAGNER LUIS DESIDERIO | AP35: Sócio-Administrador
A36: 33 | B36: NORTEL NETWORKS TELECOMUNICACOES DO BRASIL COMERCIO E SERVICOS LTDA | C36: SP | D36: 01993432 | E36: 50.88 | F36: 🔴 ALTA | G36: R$ 10-20M | H36: 16712222 | I36: 1 | J36: 1.8 | K36: 2024 | L36: IPI - Receita da dívida ativa | M36: 2024 | N36: COBRANCA | O36: =TEXT(D36,"00000000")&"0001" -> 019934320001 | P36: =IF(MOD(MID(O36,1,1)*5+MID(O36,2,1)*4+MID(O36,3,1)*3+MID(O36,4,1)*2+MID(O36,5,1)*9+MID(O36,6,1)*8+MID(O36,7,1)*7+MID(O36,8,1)*6+MID(O36,9,1)*5+MID(O36,10,1)*4+MID(O36,11,1)*3+MID(O36,12,1)*2,11)<2,0,11-MOD(MID(O36,1,1)*5+MID(O36,2,1)*4+MID(O36,3,1)*3+MID(O36,4,1)*2+MID(O36,5,1)*9+MID(O36,6,1)*8+MID(O36,7,1)*7+MID(O36,8,1)*6+MID(O36,9,1)*5+MID(O36,10,1)*4+MID(O36,11,1)*3+MID(O36,12,1)*2,11)) -> 0 | Q36: =IF(MOD(MID(O36,1,1)*6+MID(O36,2,1)*5+MID(O36,3,1)*4+MID(O36,4,1)*3+MID(O36,5,1)*2+MID(O36,6,1)*9+MID(O36,7,1)*8+MID(O36,8,1)*7+MID(O36,9,1)*6+MID(O36,10,1)*5+MID(O36,11,1)*4+MID(O36,12,1)*3+P36*2,11)<2,0,11-MOD(MID(O36,1,1)*6+MID(O36,2,1)*5+MID(O36,3,1)*4+MID(O36,4,1)*3+MID(O36,5,1)*2+MID(O36,6,1)*9+MID(O36,7,1)*8+MID(O36,8,1)*7+MID(O36,9,1)*6+MID(O36,10,1)*5+MID(O36,11,1)*4+MID(O36,12,1)*3+P36*2,11)) -> 3 | R36: =MID(O36,1,2)&"."&MID(O36,3,3)&"."&MID(O36,6,3)&"/"&MID(O36,9,4)&"-"&TEXT(P36,"0")&TEXT(Q36,"0") -> 01.993.432/0001-03 | T36: =IF(S36="","",IF(S36="Cadastrou","",XLOOKUP(S36,$BA$2:$BA$6,$BB$2:$BB$6,""))) | U36: =IF(S36="","",IF(S36="Cadastrou","",XLOOKUP(S36,$BA$2:$BA$6,$BC$2:$BC$6,""))) | V36: =IF(S36="","",XLOOKUP(S36,$BA$2:$BA$6,$BD$2:$BD$6,"")) | AA36: =IF(Y36="","",IF(INT(TODAY()-Y36)<0,"⚠️ Data futura",INT(TODAY()-Y36))) | AB36: =IF(AA36="","",IF(Z36="",IF(AA36>14,"🔴 Atrasado",IF(AA36>7,"🟡 Atenção","🟢 Em dia")),IF(TODAY()>Z36,"🔴 Atrasado",IF(Z36-TODAY()<=3,"🟡 Atenção","🟢 Em dia")))) | AD36: =IF(OR(AC36="",H36=""),"",H36*AC36) | AF36: =IF(AC36>0,AC36,'⚙️ Config'!$B$10) -> 0.0075 | AG36: =H36*AF36 -> 125341.67 | AH36: =AG36*'⚙️ Config'!$B$11 -> 626708.34 | AI36: =AH36*'⚙️ Config'!$B$12 -> 188012.5 | AJ36: 0 | AO36: RENATO DA SILVEIRA PAZOTTO Administrador
A37: 34 | B37: LUBRIN LUBRIFICACAO INDUSTRIAL LTDA | C37: SP | D37: 01078322 | E37: 61.62 | F37: 🔴 ALTA | G37: R$ 10-20M | H37: 16348297 | I37: 1 | J37: 1.2 | K37: 2025 | L37: Receita da dívida ativa - IRPJ | M37: 2025 | N37: AJUIZADA_SEM_GAR | O37: =TEXT(D37,"00000000")&"0001" -> 010783220001 | P37: =IF(MOD(MID(O37,1,1)*5+MID(O37,2,1)*4+MID(O37,3,1)*3+MID(O37,4,1)*2+MID(O37,5,1)*9+MID(O37,6,1)*8+MID(O37,7,1)*7+MID(O37,8,1)*6+MID(O37,9,1)*5+MID(O37,10,1)*4+MID(O37,11,1)*3+MID(O37,12,1)*2,11)<2,0,11-MOD(MID(O37,1,1)*5+MID(O37,2,1)*4+MID(O37,3,1)*3+MID(O37,4,1)*2+MID(O37,5,1)*9+MID(O37,6,1)*8+MID(O37,7,1)*7+MID(O37,8,1)*6+MID(O37,9,1)*5+MID(O37,10,1)*4+MID(O37,11,1)*3+MID(O37,12,1)*2,11)) -> 1 | Q37: =IF(MOD(MID(O37,1,1)*6+MID(O37,2,1)*5+MID(O37,3,1)*4+MID(O37,4,1)*3+MID(O37,5,1)*2+MID(O37,6,1)*9+MID(O37,7,1)*8+MID(O37,8,1)*7+MID(O37,9,1)*6+MID(O37,10,1)*5+MID(O37,11,1)*4+MID(O37,12,1)*3+P37*2,11)<2,0,11-MOD(MID(O37,1,1)*6+MID(O37,2,1)*5+MID(O37,3,1)*4+MID(O37,4,1)*3+MID(O37,5,1)*2+MID(O37,6,1)*9+MID(O37,7,1)*8+MID(O37,8,1)*7+MID(O37,9,1)*6+MID(O37,10,1)*5+MID(O37,11,1)*4+MID(O37,12,1)*3+P37*2,11)) -> 6 | R37: =MID(O37,1,2)&"."&MID(O37,3,3)&"."&MID(O37,6,3)&"/"&MID(O37,9,4)&"-"&TEXT(P37,"0")&TEXT(Q37,"0") -> 01.078.322/0001-16 | T37: =IF(S37="","",IF(S37="Cadastrou","",XLOOKUP(S37,$BA$2:$BA$6,$BB$2:$BB$6,""))) | U37: =IF(S37="","",IF(S37="Cadastrou","",XLOOKUP(S37,$BA$2:$BA$6,$BC$2:$BC$6,""))) | V37: =IF(S37="","",XLOOKUP(S37,$BA$2:$BA$6,$BD$2:$BD$6,"")) | AA37: =IF(Y37="","",IF(INT(TODAY()-Y37)<0,"⚠️ Data futura",INT(TODAY()-Y37))) | AB37: =IF(AA37="","",IF(Z37="",IF(AA37>14,"🔴 Atrasado",IF(AA37>7,"🟡 Atenção","🟢 Em dia")),IF(TODAY()>Z37,"🔴 Atrasado",IF(Z37-TODAY()<=3,"🟡 Atenção","🟢 Em dia")))) | AD37: =IF(OR(AC37="",H37=""),"",H37*AC37) | AF37: =IF(AC37>0,AC37,'⚙️ Config'!$B$10) -> 0.0075 | AG37: =H37*AF37 -> 122612.23 | AH37: =AG37*'⚙️ Config'!$B$11 -> 613061.14 | AI37: =AH37*'⚙️ Config'!$B$12 -> 183918.34 | AJ37: 250000 | AM37: (11) 5070-2260 | AN37: contato@lubrin.com.br | AO37: CARLOS CESAR NEGREIROS DE ALMENDRA FREITAS FILHO | AP37: Sócio-Administrador
A38: 35 | B38: EMPRESA AUTO VIACAO TABOAO LTDA | C38: SP | D38: 61541645 | E38: 76.51 | F38: 🔴 ALTA | G38: R$ 10-20M | H38: 16293163 | I38: 2 | J38: 0.9 | K38: 2025 | L38: R D Ativa -Multa Isolada Compensação Previdenciária Indevida | R D Ativa - Multa Regulamentar Descump Obrig Acessória Prev | R D Ativa - Glosa de Compensação Previdenciária | M38: 2025 | N38: AJUIZADA_SEM_GAR|COBRANCA|OUTROS | O38: =TEXT(D38,"00000000")&"0001" -> 615416450001 | P38: =IF(MOD(MID(O38,1,1)*5+MID(O38,2,1)*4+MID(O38,3,1)*3+MID(O38,4,1)*2+MID(O38,5,1)*9+MID(O38,6,1)*8+MID(O38,7,1)*7+MID(O38,8,1)*6+MID(O38,9,1)*5+MID(O38,10,1)*4+MID(O38,11,1)*3+MID(O38,12,1)*2,11)<2,0,11-MOD(MID(O38,1,1)*5+MID(O38,2,1)*4+MID(O38,3,1)*3+MID(O38,4,1)*2+MID(O38,5,1)*9+MID(O38,6,1)*8+MID(O38,7,1)*7+MID(O38,8,1)*6+MID(O38,9,1)*5+MID(O38,10,1)*4+MID(O38,11,1)*3+MID(O38,12,1)*2,11)) -> 2 | Q38: =IF(MOD(MID(O38,1,1)*6+MID(O38,2,1)*5+MID(O38,3,1)*4+MID(O38,4,1)*3+MID(O38,5,1)*2+MID(O38,6,1)*9+MID(O38,7,1)*8+MID(O38,8,1)*7+MID(O38,9,1)*6+MID(O38,10,1)*5+MID(O38,11,1)*4+MID(O38,12,1)*3+P38*2,11)<2,0,11-MOD(MID(O38,1,1)*6+MID(O38,2,1)*5+MID(O38,3,1)*4+MID(O38,4,1)*3+MID(O38,5,1)*2+MID(O38,6,1)*9+MID(O38,7,1)*8+MID(O38,8,1)*7+MID(O38,9,1)*6+MID(O38,10,1)*5+MID(O38,11,1)*4+MID(O38,12,1)*3+P38*2,11)) -> 6 | R38: =MID(O38,1,2)&"."&MID(O38,3,3)&"."&MID(O38,6,3)&"/"&MID(O38,9,4)&"-"&TEXT(P38,"0")&TEXT(Q38,"0") -> 61.541.645/0001-26 | T38: =IF(S38="","",IF(S38="Cadastrou","",XLOOKUP(S38,$BA$2:$BA$6,$BB$2:$BB$6,""))) | U38: =IF(S38="","",IF(S38="Cadastrou","",XLOOKUP(S38,$BA$2:$BA$6,$BC$2:$BC$6,""))) | V38: =IF(S38="","",XLOOKUP(S38,$BA$2:$BA$6,$BD$2:$BD$6,"")) | AA38: =IF(Y38="","",IF(INT(TODAY()-Y38)<0,"⚠️ Data futura",INT(TODAY()-Y38))) | AB38: =IF(AA38="","",IF(Z38="",IF(AA38>14,"🔴 Atrasado",IF(AA38>7,"🟡 Atenção","🟢 Em dia")),IF(TODAY()>Z38,"🔴 Atrasado",IF(Z38-TODAY()<=3,"🟡 Atenção","🟢 Em dia")))) | AD38: =IF(OR(AC38="",H38=""),"",H38*AC38) | AF38: =IF(AC38>0,AC38,'⚙️ Config'!$B$10) -> 0.0075 | AG38: =H38*AF38 -> 122198.72 | AH38: =AG38*'⚙️ Config'!$B$11 -> 610993.6 | AI38: =AH38*'⚙️ Config'!$B$12 -> 183298.08 | AJ38: 5800000 | AM38: (11) 6335-1627 | AO38: FRANCISCO PARENTE DOS SANTOS | AP38: Sócio-Administrador
A39: 36 | B39: HALCANTACA AGROPECUARIA E PARTICIPACOES LTDA. | C39: SP | D39: 01052837 | E39: 40.87 | F39: 🔴 ALTA | G39: R$ 10-20M | H39: 16256189 | I39: 2 | J39: 1.8 | K39: 2024 | L39: Receita da dívida ativa - ITR - Exercício 1997 e posteriores | M39: 2024 | N39: AJUIZADA_SEM_GAR | O39: =TEXT(D39,"00000000")&"0001" -> 010528370001 | P39: =IF(MOD(MID(O39,1,1)*5+MID(O39,2,1)*4+MID(O39,3,1)*3+MID(O39,4,1)*2+MID(O39,5,1)*9+MID(O39,6,1)*8+MID(O39,7,1)*7+MID(O39,8,1)*6+MID(O39,9,1)*5+MID(O39,10,1)*4+MID(O39,11,1)*3+MID(O39,12,1)*2,11)<2,0,11-MOD(MID(O39,1,1)*5+MID(O39,2,1)*4+MID(O39,3,1)*3+MID(O39,4,1)*2+MID(O39,5,1)*9+MID(O39,6,1)*8+MID(O39,7,1)*7+MID(O39,8,1)*6+MID(O39,9,1)*5+MID(O39,10,1)*4+MID(O39,11,1)*3+MID(O39,12,1)*2,11)) -> 4 | Q39: =IF(MOD(MID(O39,1,1)*6+MID(O39,2,1)*5+MID(O39,3,1)*4+MID(O39,4,1)*3+MID(O39,5,1)*2+MID(O39,6,1)*9+MID(O39,7,1)*8+MID(O39,8,1)*7+MID(O39,9,1)*6+MID(O39,10,1)*5+MID(O39,11,1)*4+MID(O39,12,1)*3+P39*2,11)<2,0,11-MOD(MID(O39,1,1)*6+MID(O39,2,1)*5+MID(O39,3,1)*4+MID(O39,4,1)*3+MID(O39,5,1)*2+MID(O39,6,1)*9+MID(O39,7,1)*8+MID(O39,8,1)*7+MID(O39,9,1)*6+MID(O39,10,1)*5+MID(O39,11,1)*4+MID(O39,12,1)*3+P39*2,11)) -> 7 | R39: =MID(O39,1,2)&"."&MID(O39,3,3)&"."&MID(O39,6,3)&"/"&MID(O39,9,4)&"-"&TEXT(P39,"0")&TEXT(Q39,"0") -> 01.052.837/0001-47 | T39: =IF(S39="","",IF(S39="Cadastrou","",XLOOKUP(S39,$BA$2:$BA$6,$BB$2:$BB$6,""))) | U39: =IF(S39="","",IF(S39="Cadastrou","",XLOOKUP(S39,$BA$2:$BA$6,$BC$2:$BC$6,""))) | V39: =IF(S39="","",XLOOKUP(S39,$BA$2:$BA$6,$BD$2:$BD$6,"")) | AA39: =IF(Y39="","",IF(INT(TODAY()-Y39)<0,"⚠️ Data futura",INT(TODAY()-Y39))) | AB39: =IF(AA39="","",IF(Z39="",IF(AA39>14,"🔴 Atrasado",IF(AA39>7,"🟡 Atenção","🟢 Em dia")),IF(TODAY()>Z39,"🔴 Atrasado",IF(Z39-TODAY()<=3,"🟡 Atenção","🟢 Em dia")))) | AD39: =IF(OR(AC39="",H39=""),"",H39*AC39) | AF39: =IF(AC39>0,AC39,'⚙️ Config'!$B$10) -> 0.0075 | AG39: =H39*AF39 -> 121921.42 | AH39: =AG39*'⚙️ Config'!$B$11 -> 609607.09 | AI39: =AH39*'⚙️ Config'!$B$12 -> 182882.13 | AJ39: 4288658 | AM39: (16) 9149-0126 | AN39: halcantaca@halcantaca.com.br | AO39: EDUARDO DE MAGALHAES MENDONCA | AP39: Sócio-Administrador
A40: 37 | B40: PCBOX SERVICOS DE INFORMATICA LTDA. | C40: SP | D40: 05362376 | E40: 47.27 | F40: 🔴 ALTA | G40: R$ 10-20M | H40: 15761255 | I40: 2 | J40: 1.4 | K40: 2024 | L40: Receita da dívida ativa - CSLL | Receita da dívida ativa - IRPJ | M40: 2024 | N40: COBRANCA | O40: =TEXT(D40,"00000000")&"0001" -> 053623760001 | P40: =IF(MOD(MID(O40,1,1)*5+MID(O40,2,1)*4+MID(O40,3,1)*3+MID(O40,4,1)*2+MID(O40,5,1)*9+MID(O40,6,1)*8+MID(O40,7,1)*7+MID(O40,8,1)*6+MID(O40,9,1)*5+MID(O40,10,1)*4+MID(O40,11,1)*3+MID(O40,12,1)*2,11)<2,0,11-MOD(MID(O40,1,1)*5+MID(O40,2,1)*4+MID(O40,3,1)*3+MID(O40,4,1)*2+MID(O40,5,1)*9+MID(O40,6,1)*8+MID(O40,7,1)*7+MID(O40,8,1)*6+MID(O40,9,1)*5+MID(O40,10,1)*4+MID(O40,11,1)*3+MID(O40,12,1)*2,11)) -> 6 | Q40: =IF(MOD(MID(O40,1,1)*6+MID(O40,2,1)*5+MID(O40,3,1)*4+MID(O40,4,1)*3+MID(O40,5,1)*2+MID(O40,6,1)*9+MID(O40,7,1)*8+MID(O40,8,1)*7+MID(O40,9,1)*6+MID(O40,10,1)*5+MID(O40,11,1)*4+MID(O40,12,1)*3+P40*2,11)<2,0,11-MOD(MID(O40,1,1)*6+MID(O40,2,1)*5+MID(O40,3,1)*4+MID(O40,4,1)*3+MID(O40,5,1)*2+MID(O40,6,1)*9+MID(O40,7,1)*8+MID(O40,8,1)*7+MID(O40,9,1)*6+MID(O40,10,1)*5+MID(O40,11,1)*4+MID(O40,12,1)*3+P40*2,11)) -> 0 | R40: =MID(O40,1,2)&"."&MID(O40,3,3)&"."&MID(O40,6,3)&"/"&MID(O40,9,4)&"-"&TEXT(P40,"0")&TEXT(Q40,"0") -> 05.362.376/0001-60 | T40: =IF(S40="","",IF(S40="Cadastrou","",XLOOKUP(S40,$BA$2:$BA$6,$BB$2:$BB$6,""))) | U40: =IF(S40="","",IF(S40="Cadastrou","",XLOOKUP(S40,$BA$2:$BA$6,$BC$2:$BC$6,""))) | V40: =IF(S40="","",XLOOKUP(S40,$BA$2:$BA$6,$BD$2:$BD$6,"")) | AA40: =IF(Y40="","",IF(INT(TODAY()-Y40)<0,"⚠️ Data futura",INT(TODAY()-Y40))) | AB40: =IF(AA40="","",IF(Z40="",IF(AA40>14,"🔴 Atrasado",IF(AA40>7,"🟡 Atenção","🟢 Em dia")),IF(TODAY()>Z40,"🔴 Atrasado",IF(Z40-TODAY()<=3,"🟡 Atenção","🟢 Em dia")))) | AD40: =IF(OR(AC40="",H40=""),"",H40*AC40) | AF40: =IF(AC40>0,AC40,'⚙️ Config'!$B$10) -> 0.0075 | AG40: =H40*AF40 -> 118209.42 | AH40: =AG40*'⚙️ Config'!$B$11 -> 591047.08 | AI40: =AH40*'⚙️ Config'!$B$12 -> 177314.12 | AJ40: 300000 | AM40: (11) 3732-5500 | AO40: ISABEL CRISTINA CREPALDI SANTOS | AP40: Sócio-Administrador
A41: 38 | B41: WINTER GESTAO E CONSULTORIA MEDICA LTDA | C41: SP | D41: 26392666 | E41: 54.16 | F41: 🔴 ALTA | G41: R$ 10-20M | H41: 15454607 | I41: 2 | J41: 1.1 | K41: 2025 | L41: Receita da dívida ativa - CSLL | Receita da dívida ativa - IRPJ | M41: 2025 | N41: COBRANCA | O41: =TEXT(D41,"00000000")&"0001" -> 263926660001 | P41: =IF(MOD(MID(O41,1,1)*5+MID(O41,2,1)*4+MID(O41,3,1)*3+MID(O41,4,1)*2+MID(O41,5,1)*9+MID(O41,6,1)*8+MID(O41,7,1)*7+MID(O41,8,1)*6+MID(O41,9,1)*5+MID(O41,10,1)*4+MID(O41,11,1)*3+MID(O41,12,1)*2,11)<2,0,11-MOD(MID(O41,1,1)*5+MID(O41,2,1)*4+MID(O41,3,1)*3+MID(O41,4,1)*2+MID(O41,5,1)*9+MID(O41,6,1)*8+MID(O41,7,1)*7+MID(O41,8,1)*6+MID(O41,9,1)*5+MID(O41,10,1)*4+MID(O41,11,1)*3+MID(O41,12,1)*2,11)) -> 2 | Q41: =IF(MOD(MID(O41,1,1)*6+MID(O41,2,1)*5+MID(O41,3,1)*4+MID(O41,4,1)*3+MID(O41,5,1)*2+MID(O41,6,1)*9+MID(O41,7,1)*8+MID(O41,8,1)*7+MID(O41,9,1)*6+MID(O41,10,1)*5+MID(O41,11,1)*4+MID(O41,12,1)*3+P41*2,11)<2,0,11-MOD(MID(O41,1,1)*6+MID(O41,2,1)*5+MID(O41,3,1)*4+MID(O41,4,1)*3+MID(O41,5,1)*2+MID(O41,6,1)*9+MID(O41,7,1)*8+MID(O41,8,1)*7+MID(O41,9,1)*6+MID(O41,10,1)*5+MID(O41,11,1)*4+MID(O41,12,1)*3+P41*2,11)) -> 6 | R41: =MID(O41,1,2)&"."&MID(O41,3,3)&"."&MID(O41,6,3)&"/"&MID(O41,9,4)&"-"&TEXT(P41,"0")&TEXT(Q41,"0") -> 26.392.666/0001-26 | T41: =IF(S41="","",IF(S41="Cadastrou","",XLOOKUP(S41,$BA$2:$BA$6,$BB$2:$BB$6,""))) | U41: =IF(S41="","",IF(S41="Cadastrou","",XLOOKUP(S41,$BA$2:$BA$6,$BC$2:$BC$6,""))) | V41: =IF(S41="","",XLOOKUP(S41,$BA$2:$BA$6,$BD$2:$BD$6,"")) | AA41: =IF(Y41="","",IF(INT(TODAY()-Y41)<0,"⚠️ Data futura",INT(TODAY()-Y41))) | AB41: =IF(AA41="","",IF(Z41="",IF(AA41>14,"🔴 Atrasado",IF(AA41>7,"🟡 Atenção","🟢 Em dia")),IF(TODAY()>Z41,"🔴 Atrasado",IF(Z41-TODAY()<=3,"🟡 Atenção","🟢 Em dia")))) | AD41: =IF(OR(AC41="",H41=""),"",H41*AC41) | AF41: =IF(AC41>0,AC41,'⚙️ Config'!$B$10) -> 0.0075 | AG41: =H41*AF41 -> 115909.56 | AH41: =AG41*'⚙️ Config'!$B$11 -> 579547.78 | AI41: =AH41*'⚙️ Config'!$B$12 -> 173864.33
A42: 39 | B42: NEXUS VIGILANCIA LTDA | C42: SP | D42: 06911840 | E42: 107.91 | F42: 🔴 ALTA | G42: R$ 10-20M | H42: 15309974 | I42: 1 | J42: 0.3 | K42: 2025 | L42: Receita da dívida ativa - Outras multas | M42: 2025 | N42: AJUIZADA_SEM_GAR | O42: =TEXT(D42,"00000000")&"0001" -> 069118400001 | P42: =IF(MOD(MID(O42,1,1)*5+MID(O42,2,1)*4+MID(O42,3,1)*3+MID(O42,4,1)*2+MID(O42,5,1)*9+MID(O42,6,1)*8+MID(O42,7,1)*7+MID(O42,8,1)*6+MID(O42,9,1)*5+MID(O42,10,1)*4+MID(O42,11,1)*3+MID(O42,12,1)*2,11)<2,0,11-MOD(MID(O42,1,1)*5+MID(O42,2,1)*4+MID(O42,3,1)*3+MID(O42,4,1)*2+MID(O42,5,1)*9+MID(O42,6,1)*8+MID(O42,7,1)*7+MID(O42,8,1)*6+MID(O42,9,1)*5+MID(O42,10,1)*4+MID(O42,11,1)*3+MID(O42,12,1)*2,11)) -> 9 | Q42: =IF(MOD(MID(O42,1,1)*6+MID(O42,2,1)*5+MID(O42,3,1)*4+MID(O42,4,1)*3+MID(O42,5,1)*2+MID(O42,6,1)*9+MID(O42,7,1)*8+MID(O42,8,1)*7+MID(O42,9,1)*6+MID(O42,10,1)*5+MID(O42,11,1)*4+MID(O42,12,1)*3+P42*2,11)<2,0,11-MOD(MID(O42,1,1)*6+MID(O42,2,1)*5+MID(O42,3,1)*4+MID(O42,4,1)*3+MID(O42,5,1)*2+MID(O42,6,1)*9+MID(O42,7,1)*8+MID(O42,8,1)*7+MID(O42,9,1)*6+MID(O42,10,1)*5+MID(O42,11,1)*4+MID(O42,12,1)*3+P42*2,11)) -> 2 | R42: =MID(O42,1,2)&"."&MID(O42,3,3)&"."&MID(O42,6,3)&"/"&MID(O42,9,4)&"-"&TEXT(P42,"0")&TEXT(Q42,"0") -> 06.911.840/0001-92 | T42: =IF(S42="","",IF(S42="Cadastrou","",XLOOKUP(S42,$BA$2:$BA$6,$BB$2:$BB$6,""))) | U42: =IF(S42="","",IF(S42="Cadastrou","",XLOOKUP(S42,$BA$2:$BA$6,$BC$2:$BC$6,""))) | V42: =IF(S42="","",XLOOKUP(S42,$BA$2:$BA$6,$BD$2:$BD$6,"")) | AA42: =IF(Y42="","",IF(INT(TODAY()-Y42)<0,"⚠️ Data futura",INT(TODAY()-Y42))) | AB42: =IF(AA42="","",IF(Z42="",IF(AA42>14,"🔴 Atrasado",IF(AA42>7,"🟡 Atenção","🟢 Em dia")),IF(TODAY()>Z42,"🔴 Atrasado",IF(Z42-TODAY()<=3,"🟡 Atenção","🟢 Em dia")))) | AD42: =IF(OR(AC42="",H42=""),"",H42*AC42) | AF42: =IF(AC42>0,AC42,'⚙️ Config'!$B$10) -> 0.0075 | AG42: =H42*AF42 -> 114824.8 | AH42: =AG42*'⚙️ Config'!$B$11 -> 574124.02 | AI42: =AH42*'⚙️ Config'!$B$12 -> 172237.21 | AJ42: 2749998 | AM42: (31) 3439-6900 | AO42: ROMIR BARBOSA GUERRA | AP42: Sócio-Administrador
A43: 40 | B43: CLOUD2B DESENVOLVIMENTO DE SOFTWARES LTDA | C43: SP | D43: 20719500 | E43: 50.84 | F43: 🔴 ALTA | G43: R$ 10-20M | H43: 15287032 | I43: 1 | J43: 1.8 | K43: 2024 | L43: Receita da dívida ativa - Multa - CLT | M43: 2024 | N43: COBRANCA | O43: =TEXT(D43,"00000000")&"0001" -> 207195000001 | P43: =IF(MOD(MID(O43,1,1)*5+MID(O43,2,1)*4+MID(O43,3,1)*3+MID(O43,4,1)*2+MID(O43,5,1)*9+MID(O43,6,1)*8+MID(O43,7,1)*7+MID(O43,8,1)*6+MID(O43,9,1)*5+MID(O43,10,1)*4+MID(O43,11,1)*3+MID(O43,12,1)*2,11)<2,0,11-MOD(MID(O43,1,1)*5+MID(O43,2,1)*4+MID(O43,3,1)*3+MID(O43,4,1)*2+MID(O43,5,1)*9+MID(O43,6,1)*8+MID(O43,7,1)*7+MID(O43,8,1)*6+MID(O43,9,1)*5+MID(O43,10,1)*4+MID(O43,11,1)*3+MID(O43,12,1)*2,11)) -> 9 | Q43: =IF(MOD(MID(O43,1,1)*6+MID(O43,2,1)*5+MID(O43,3,1)*4+MID(O43,4,1)*3+MID(O43,5,1)*2+MID(O43,6,1)*9+MID(O43,7,1)*8+MID(O43,8,1)*7+MID(O43,9,1)*6+MID(O43,10,1)*5+MID(O43,11,1)*4+MID(O43,12,1)*3+P43*2,11)<2,0,11-MOD(MID(O43,1,1)*6+MID(O43,2,1)*5+MID(O43,3,1)*4+MID(O43,4,1)*3+MID(O43,5,1)*2+MID(O43,6,1)*9+MID(O43,7,1)*8+MID(O43,8,1)*7+MID(O43,9,1)*6+MID(O43,10,1)*5+MID(O43,11,1)*4+MID(O43,12,1)*3+P43*2,11)) -> 5 | R43: =MID(O43,1,2)&"."&MID(O43,3,3)&"."&MID(O43,6,3)&"/"&MID(O43,9,4)&"-"&TEXT(P43,"0")&TEXT(Q43,"0") -> 20.719.500/0001-95 | T43: =IF(S43="","",IF(S43="Cadastrou","",XLOOKUP(S43,$BA$2:$BA$6,$BB$2:$BB$6,""))) | U43: =IF(S43="","",IF(S43="Cadastrou","",XLOOKUP(S43,$BA$2:$BA$6,$BC$2:$BC$6,""))) | V43: =IF(S43="","",XLOOKUP(S43,$BA$2:$BA$6,$BD$2:$BD$6,"")) | AA43: =IF(Y43="","",IF(INT(TODAY()-Y43)<0,"⚠️ Data futura",INT(TODAY()-Y43))) | AB43: =IF(AA43="","",IF(Z43="",IF(AA43>14,"🔴 Atrasado",IF(AA43>7,"🟡 Atenção","🟢 Em dia")),IF(TODAY()>Z43,"🔴 Atrasado",IF(Z43-TODAY()<=3,"🟡 Atenção","🟢 Em dia")))) | AD43: =IF(OR(AC43="",H43=""),"",H43*AC43) | AF43: =IF(AC43>0,AC43,'⚙️ Config'!$B$10) -> 0.0075 | AG43: =H43*AF43 -> 114652.74 | AH43: =AG43*'⚙️ Config'!$B$11 -> 573263.71 | AI43: =AH43*'⚙️ Config'!$B$12 -> 171979.11
A44: 41 | B44: DISTRIBUIDORA DE BEBIDAS OVIDIO LTDA | C44: MS | D44: 15429905 | E44: 49.28 | F44: 🔴 ALTA | G44: R$ 10-20M | H44: 14752679 | I44: 2 | J44: 1.3 | K44: 2024 | L44: Receita da dívida ativa - PIS | Receita da dívida ativa - COFINS | M44: 2024 | N44: AJUIZADA_SEM_GAR | O44: =TEXT(D44,"00000000")&"0001" -> 154299050001 | P44: =IF(MOD(MID(O44,1,1)*5+MID(O44,2,1)*4+MID(O44,3,1)*3+MID(O44,4,1)*2+MID(O44,5,1)*9+MID(O44,6,1)*8+MID(O44,7,1)*7+MID(O44,8,1)*6+MID(O44,9,1)*5+MID(O44,10,1)*4+MID(O44,11,1)*3+MID(O44,12,1)*2,11)<2,0,11-MOD(MID(O44,1,1)*5+MID(O44,2,1)*4+MID(O44,3,1)*3+MID(O44,4,1)*2+MID(O44,5,1)*9+MID(O44,6,1)*8+MID(O44,7,1)*7+MID(O44,8,1)*6+MID(O44,9,1)*5+MID(O44,10,1)*4+MID(O44,11,1)*3+MID(O44,12,1)*2,11)) -> 5 | Q44: =IF(MOD(MID(O44,1,1)*6+MID(O44,2,1)*5+MID(O44,3,1)*4+MID(O44,4,1)*3+MID(O44,5,1)*2+MID(O44,6,1)*9+MID(O44,7,1)*8+MID(O44,8,1)*7+MID(O44,9,1)*6+MID(O44,10,1)*5+MID(O44,11,1)*4+MID(O44,12,1)*3+P44*2,11)<2,0,11-MOD(MID(O44,1,1)*6+MID(O44,2,1)*5+MID(O44,3,1)*4+MID(O44,4,1)*3+MID(O44,5,1)*2+MID(O44,6,1)*9+MID(O44,7,1)*8+MID(O44,8,1)*7+MID(O44,9,1)*6+MID(O44,10,1)*5+MID(O44,11,1)*4+MID(O44,12,1)*3+P44*2,11)) -> 9 | R44: =MID(O44,1,2)&"."&MID(O44,3,3)&"."&MID(O44,6,3)&"/"&MID(O44,9,4)&"-"&TEXT(P44,"0")&TEXT(Q44,"0") -> 15.429.905/0001-59 | T44: =IF(S44="","",IF(S44="Cadastrou","",XLOOKUP(S44,$BA$2:$BA$6,$BB$2:$BB$6,""))) | U44: =IF(S44="","",IF(S44="Cadastrou","",XLOOKUP(S44,$BA$2:$BA$6,$BC$2:$BC$6,""))) | V44: =IF(S44="","",XLOOKUP(S44,$BA$2:$BA$6,$BD$2:$BD$6,"")) | AA44: =IF(Y44="","",IF(INT(TODAY()-Y44)<0,"⚠️ Data futura",INT(TODAY()-Y44))) | AB44: =IF(AA44="","",IF(Z44="",IF(AA44>14,"🔴 Atrasado",IF(AA44>7,"🟡 Atenção","🟢 Em dia")),IF(TODAY()>Z44,"🔴 Atrasado",IF(Z44-TODAY()<=3,"🟡 Atenção","🟢 Em dia")))) | AD44: =IF(OR(AC44="",H44=""),"",H44*AC44) | AF44: =IF(AC44>0,AC44,'⚙️ Config'!$B$10) -> 0.0075 | AG44: =H44*AF44 -> 110645.09 | AH44: =AG44*'⚙️ Config'!$B$11 -> 553225.47 | AI44: =AH44*'⚙️ Config'!$B$12 -> 165967.64 | AJ44: 2500000 | AO44: BRAS ANTONIO OVIDIO | AP44: Sócio-Administrador
A45: 42 | B45: J. DE A. CASTRO COBRANCAS | C45: SP | D45: 00324837 | E45: 40.82 | F45: 🔴 ALTA | G45: R$ 10-20M | H45: 14514589 | I45: 2 | J45: 1.8 | K45: 2024 | L45: Receita da dívida ativa - IRRF | M45: 2024 | N45: COBRANCA | O45: =TEXT(D45,"00000000")&"0001" -> 003248370001 | P45: =IF(MOD(MID(O45,1,1)*5+MID(O45,2,1)*4+MID(O45,3,1)*3+MID(O45,4,1)*2+MID(O45,5,1)*9+MID(O45,6,1)*8+MID(O45,7,1)*7+MID(O45,8,1)*6+MID(O45,9,1)*5+MID(O45,10,1)*4+MID(O45,11,1)*3+MID(O45,12,1)*2,11)<2,0,11-MOD(MID(O45,1,1)*5+MID(O45,2,1)*4+MID(O45,3,1)*3+MID(O45,4,1)*2+MID(O45,5,1)*9+MID(O45,6,1)*8+MID(O45,7,1)*7+MID(O45,8,1)*6+MID(O45,9,1)*5+MID(O45,10,1)*4+MID(O45,11,1)*3+MID(O45,12,1)*2,11)) -> 9 | Q45: =IF(MOD(MID(O45,1,1)*6+MID(O45,2,1)*5+MID(O45,3,1)*4+MID(O45,4,1)*3+MID(O45,5,1)*2+MID(O45,6,1)*9+MID(O45,7,1)*8+MID(O45,8,1)*7+MID(O45,9,1)*6+MID(O45,10,1)*5+MID(O45,11,1)*4+MID(O45,12,1)*3+P45*2,11)<2,0,11-MOD(MID(O45,1,1)*6+MID(O45,2,1)*5+MID(O45,3,1)*4+MID(O45,4,1)*3+MID(O45,5,1)*2+MID(O45,6,1)*9+MID(O45,7,1)*8+MID(O45,8,1)*7+MID(O45,9,1)*6+MID(O45,10,1)*5+MID(O45,11,1)*4+MID(O45,12,1)*3+P45*2,11)) -> 6 | R45: =MID(O45,1,2)&"."&MID(O45,3,3)&"."&MID(O45,6,3)&"/"&MID(O45,9,4)&"-"&TEXT(P45,"0")&TEXT(Q45,"0") -> 00.324.837/0001-96 | T45: =IF(S45="","",IF(S45="Cadastrou","",XLOOKUP(S45,$BA$2:$BA$6,$BB$2:$BB$6,""))) | U45: =IF(S45="","",IF(S45="Cadastrou","",XLOOKUP(S45,$BA$2:$BA$6,$BC$2:$BC$6,""))) | V45: =IF(S45="","",XLOOKUP(S45,$BA$2:$BA$6,$BD$2:$BD$6,"")) | AA45: =IF(Y45="","",IF(INT(TODAY()-Y45)<0,"⚠️ Data futura",INT(TODAY()-Y45))) | AB45: =IF(AA45="","",IF(Z45="",IF(AA45>14,"🔴 Atrasado",IF(AA45>7,"🟡 Atenção","🟢 Em dia")),IF(TODAY()>Z45,"🔴 Atrasado",IF(Z45-TODAY()<=3,"🟡 Atenção","🟢 Em dia")))) | AD45: =IF(OR(AC45="",H45=""),"",H45*AC45) | AF45: =IF(AC45>0,AC45,'⚙️ Config'!$B$10) -> 0.0075 | AG45: =H45*AF45 -> 108859.42 | AH45: =AG45*'⚙️ Config'!$B$11 -> 544297.1 | AI45: =AH45*'⚙️ Config'!$B$12 -> 163289.13
A46: 43 | B46: PLAYER EMPREENDIMENTOS ESPORTIVOS E CULTURAIS LTDA | C46: SP | D46: 02934076 | E46: 39.53 | F46: 🔴 ALTA | G46: R$ 10-20M | H46: 13447082 | I46: 2 | J46: 1.9 | K46: 2024 | L46: Receita da dívida ativa - IRPJ | Receita da dívida ativa - IRRF | M46: 2024 | N46: COBRANCA | O46: =TEXT(D46,"00000000")&"0001" -> 029340760001 | P46: =IF(MOD(MID(O46,1,1)*5+MID(O46,2,1)*4+MID(O46,3,1)*3+MID(O46,4,1)*2+MID(O46,5,1)*9+MID(O46,6,1)*8+MID(O46,7,1)*7+MID(O46,8,1)*6+MID(O46,9,1)*5+MID(O46,10,1)*4+MID(O46,11,1)*3+MID(O46,12,1)*2,11)<2,0,11-MOD(MID(O46,1,1)*5+MID(O46,2,1)*4+MID(O46,3,1)*3+MID(O46,4,1)*2+MID(O46,5,1)*9+MID(O46,6,1)*8+MID(O46,7,1)*7+MID(O46,8,1)*6+MID(O46,9,1)*5+MID(O46,10,1)*4+MID(O46,11,1)*3+MID(O46,12,1)*2,11)) -> 1 | Q46: =IF(MOD(MID(O46,1,1)*6+MID(O46,2,1)*5+MID(O46,3,1)*4+MID(O46,4,1)*3+MID(O46,5,1)*2+MID(O46,6,1)*9+MID(O46,7,1)*8+MID(O46,8,1)*7+MID(O46,9,1)*6+MID(O46,10,1)*5+MID(O46,11,1)*4+MID(O46,12,1)*3+P46*2,11)<2,0,11-MOD(MID(O46,1,1)*6+MID(O46,2,1)*5+MID(O46,3,1)*4+MID(O46,4,1)*3+MID(O46,5,1)*2+MID(O46,6,1)*9+MID(O46,7,1)*8+MID(O46,8,1)*7+MID(O46,9,1)*6+MID(O46,10,1)*5+MID(O46,11,1)*4+MID(O46,12,1)*3+P46*2,11)) -> 0 | R46: =MID(O46,1,2)&"."&MID(O46,3,3)&"."&MID(O46,6,3)&"/"&MID(O46,9,4)&"-"&TEXT(P46,"0")&TEXT(Q46,"0") -> 02.934.076/0001-10 | T46: =IF(S46="","",IF(S46="Cadastrou","",XLOOKUP(S46,$BA$2:$BA$6,$BB$2:$BB$6,""))) | U46: =IF(S46="","",IF(S46="Cadastrou","",XLOOKUP(S46,$BA$2:$BA$6,$BC$2:$BC$6,""))) | V46: =IF(S46="","",XLOOKUP(S46,$BA$2:$BA$6,$BD$2:$BD$6,"")) | AA46: =IF(Y46="","",IF(INT(TODAY()-Y46)<0,"⚠️ Data futura",INT(TODAY()-Y46))) | AB46: =IF(AA46="","",IF(Z46="",IF(AA46>14,"🔴 Atrasado",IF(AA46>7,"🟡 Atenção","🟢 Em dia")),IF(TODAY()>Z46,"🔴 Atrasado",IF(Z46-TODAY()<=3,"🟡 Atenção","🟢 Em dia")))) | AD46: =IF(OR(AC46="",H46=""),"",H46*AC46) | AF46: =IF(AC46>0,AC46,'⚙️ Config'!$B$10) -> 0.0075 | AG46: =H46*AF46 -> 100853.11 | AH46: =AG46*'⚙️ Config'!$B$11 -> 504265.57 | AI46: =AH46*'⚙️ Config'!$B$12 -> 151279.67
A47: 44 | B47: KUX ALIMENTOS LTDA | C47: SP | D47: 18499051 | E47: 57.2 | F47: 🔴 ALTA | G47: R$ 10-20M | H47: 13333541 | I47: 1 | J47: 1.4 | K47: 2024 | L47: IPI - Receita da dívida ativa | M47: 2024 | N47: RETOMAR_AJUIZ | O47: =TEXT(D47,"00000000")&"0001" -> 184990510001 | P47: =IF(MOD(MID(O47,1,1)*5+MID(O47,2,1)*4+MID(O47,3,1)*3+MID(O47,4,1)*2+MID(O47,5,1)*9+MID(O47,6,1)*8+MID(O47,7,1)*7+MID(O47,8,1)*6+MID(O47,9,1)*5+MID(O47,10,1)*4+MID(O47,11,1)*3+MID(O47,12,1)*2,11)<2,0,11-MOD(MID(O47,1,1)*5+MID(O47,2,1)*4+MID(O47,3,1)*3+MID(O47,4,1)*2+MID(O47,5,1)*9+MID(O47,6,1)*8+MID(O47,7,1)*7+MID(O47,8,1)*6+MID(O47,9,1)*5+MID(O47,10,1)*4+MID(O47,11,1)*3+MID(O47,12,1)*2,11)) -> 7 | Q47: =IF(MOD(MID(O47,1,1)*6+MID(O47,2,1)*5+MID(O47,3,1)*4+MID(O47,4,1)*3+MID(O47,5,1)*2+MID(O47,6,1)*9+MID(O47,7,1)*8+MID(O47,8,1)*7+MID(O47,9,1)*6+MID(O47,10,1)*5+MID(O47,11,1)*4+MID(O47,12,1)*3+P47*2,11)<2,0,11-MOD(MID(O47,1,1)*6+MID(O47,2,1)*5+MID(O47,3,1)*4+MID(O47,4,1)*3+MID(O47,5,1)*2+MID(O47,6,1)*9+MID(O47,7,1)*8+MID(O47,8,1)*7+MID(O47,9,1)*6+MID(O47,10,1)*5+MID(O47,11,1)*4+MID(O47,12,1)*3+P47*2,11)) -> 5 | R47: =MID(O47,1,2)&"."&MID(O47,3,3)&"."&MID(O47,6,3)&"/"&MID(O47,9,4)&"-"&TEXT(P47,"0")&TEXT(Q47,"0") -> 18.499.051/0001-75 | T47: =IF(S47="","",IF(S47="Cadastrou","",XLOOKUP(S47,$BA$2:$BA$6,$BB$2:$BB$6,""))) | U47: =IF(S47="","",IF(S47="Cadastrou","",XLOOKUP(S47,$BA$2:$BA$6,$BC$2:$BC$6,""))) | V47: =IF(S47="","",XLOOKUP(S47,$BA$2:$BA$6,$BD$2:$BD$6,"")) | AA47: =IF(Y47="","",IF(INT(TODAY()-Y47)<0,"⚠️ Data futura",INT(TODAY()-Y47))) | AB47: =IF(AA47="","",IF(Z47="",IF(AA47>14,"🔴 Atrasado",IF(AA47>7,"🟡 Atenção","🟢 Em dia")),IF(TODAY()>Z47,"🔴 Atrasado",IF(Z47-TODAY()<=3,"🟡 Atenção","🟢 Em dia")))) | AD47: =IF(OR(AC47="",H47=""),"",H47*AC47) | AF47: =IF(AC47>0,AC47,'⚙️ Config'!$B$10) -> 0.0075 | AG47: =H47*AF47 -> 100001.56 | AH47: =AG47*'⚙️ Config'!$B$11 -> 500007.78 | AI47: =AH47*'⚙️ Config'!$B$12 -> 150002.33 | AJ47: 300000 | AM47: (16) 3944-3125 | AO47: JOSE ABILIO MARIN FERNANDEZ | AP47: Sócio-Administrador
A48: 45 | B48: CONTA UM TECNOLOGIA E SERVICOS DE PAGAMENTO SA | C48: SP | D48: 20704998 | E48: 54.1 | F48: 🔴 ALTA | G48: R$ 10-20M | H48: 13190529 | I48: 2 | J48: 1.1 | K48: 2025 | L48: Receita da dívida ativa - CSLL | Receita da dívida ativa - IRPJ | M48: 2025 | N48: COBRANCA | O48: =TEXT(D48,"00000000")&"0001" -> 207049980001 | P48: =IF(MOD(MID(O48,1,1)*5+MID(O48,2,1)*4+MID(O48,3,1)*3+MID(O48,4,1)*2+MID(O48,5,1)*9+MID(O48,6,1)*8+MID(O48,7,1)*7+MID(O48,8,1)*6+MID(O48,9,1)*5+MID(O48,10,1)*4+MID(O48,11,1)*3+MID(O48,12,1)*2,11)<2,0,11-MOD(MID(O48,1,1)*5+MID(O48,2,1)*4+MID(O48,3,1)*3+MID(O48,4,1)*2+MID(O48,5,1)*9+MID(O48,6,1)*8+MID(O48,7,1)*7+MID(O48,8,1)*6+MID(O48,9,1)*5+MID(O48,10,1)*4+MID(O48,11,1)*3+MID(O48,12,1)*2,11)) -> 1 | Q48: =IF(MOD(MID(O48,1,1)*6+MID(O48,2,1)*5+MID(O48,3,1)*4+MID(O48,4,1)*3+MID(O48,5,1)*2+MID(O48,6,1)*9+MID(O48,7,1)*8+MID(O48,8,1)*7+MID(O48,9,1)*6+MID(O48,10,1)*5+MID(O48,11,1)*4+MID(O48,12,1)*3+P48*2,11)<2,0,11-MOD(MID(O48,1,1)*6+MID(O48,2,1)*5+MID(O48,3,1)*4+MID(O48,4,1)*3+MID(O48,5,1)*2+MID(O48,6,1)*9+MID(O48,7,1)*8+MID(O48,8,1)*7+MID(O48,9,1)*6+MID(O48,10,1)*5+MID(O48,11,1)*4+MID(O48,12,1)*3+P48*2,11)) -> 2 | R48: =MID(O48,1,2)&"."&MID(O48,3,3)&"."&MID(O48,6,3)&"/"&MID(O48,9,4)&"-"&TEXT(P48,"0")&TEXT(Q48,"0") -> 20.704.998/0001-12 | T48: =IF(S48="","",IF(S48="Cadastrou","",XLOOKUP(S48,$BA$2:$BA$6,$BB$2:$BB$6,""))) | U48: =IF(S48="","",IF(S48="Cadastrou","",XLOOKUP(S48,$BA$2:$BA$6,$BC$2:$BC$6,""))) | V48: =IF(S48="","",XLOOKUP(S48,$BA$2:$BA$6,$BD$2:$BD$6,"")) | AA48: =IF(Y48="","",IF(INT(TODAY()-Y48)<0,"⚠️ Data futura",INT(TODAY()-Y48))) | AB48: =IF(AA48="","",IF(Z48="",IF(AA48>14,"🔴 Atrasado",IF(AA48>7,"🟡 Atenção","🟢 Em dia")),IF(TODAY()>Z48,"🔴 Atrasado",IF(Z48-TODAY()<=3,"🟡 Atenção","🟢 Em dia")))) | AD48: =IF(OR(AC48="",H48=""),"",H48*AC48) | AF48: =IF(AC48>0,AC48,'⚙️ Config'!$B$10) -> 0.0075 | AG48: =H48*AF48 -> 98928.971 | AH48: =AG48*'⚙️ Config'!$B$11 -> 494644.85 | AI48: =AH48*'⚙️ Config'!$B$12 -> 148393.46 | AJ48: 10000000 | AM48: (11) 4706-2451 | AO48: GUSTAVO SALVESTRINI DA CUNHA | AP48: Diretor
A49: 46 | B49: SESTINI MERCANTIL LTDA | C49: SP | D49: 00501618 | E49: 45.35 | F49: 🔴 ALTA | G49: R$ 10-20M | H49: 13091585 | I49: 2 | J49: 1.5 | K49: 2024 | L49: Receita da dívida ativa - Imposto de Importação | M49: 2024 | N49: AJUIZADA_SEM_GAR | O49: =TEXT(D49,"00000000")&"0001" -> 005016180001 | P49: =IF(MOD(MID(O49,1,1)*5+MID(O49,2,1)*4+MID(O49,3,1)*3+MID(O49,4,1)*2+MID(O49,5,1)*9+MID(O49,6,1)*8+MID(O49,7,1)*7+MID(O49,8,1)*6+MID(O49,9,1)*5+MID(O49,10,1)*4+MID(O49,11,1)*3+MID(O49,12,1)*2,11)<2,0,11-MOD(MID(O49,1,1)*5+MID(O49,2,1)*4+MID(O49,3,1)*3+MID(O49,4,1)*2+MID(O49,5,1)*9+MID(O49,6,1)*8+MID(O49,7,1)*7+MID(O49,8,1)*6+MID(O49,9,1)*5+MID(O49,10,1)*4+MID(O49,11,1)*3+MID(O49,12,1)*2,11)) -> 3 | Q49: =IF(MOD(MID(O49,1,1)*6+MID(O49,2,1)*5+MID(O49,3,1)*4+MID(O49,4,1)*3+MID(O49,5,1)*2+MID(O49,6,1)*9+MID(O49,7,1)*8+MID(O49,8,1)*7+MID(O49,9,1)*6+MID(O49,10,1)*5+MID(O49,11,1)*4+MID(O49,12,1)*3+P49*2,11)<2,0,11-MOD(MID(O49,1,1)*6+MID(O49,2,1)*5+MID(O49,3,1)*4+MID(O49,4,1)*3+MID(O49,5,1)*2+MID(O49,6,1)*9+MID(O49,7,1)*8+MID(O49,8,1)*7+MID(O49,9,1)*6+MID(O49,10,1)*5+MID(O49,11,1)*4+MID(O49,12,1)*3+P49*2,11)) -> 5 | R49: =MID(O49,1,2)&"."&MID(O49,3,3)&"."&MID(O49,6,3)&"/"&MID(O49,9,4)&"-"&TEXT(P49,"0")&TEXT(Q49,"0") -> 00.501.618/0001-35 | T49: =IF(S49="","",IF(S49="Cadastrou","",XLOOKUP(S49,$BA$2:$BA$6,$BB$2:$BB$6,""))) | U49: =IF(S49="","",IF(S49="Cadastrou","",XLOOKUP(S49,$BA$2:$BA$6,$BC$2:$BC$6,""))) | V49: =IF(S49="","",XLOOKUP(S49,$BA$2:$BA$6,$BD$2:$BD$6,"")) | AA49: =IF(Y49="","",IF(INT(TODAY()-Y49)<0,"⚠️ Data futura",INT(TODAY()-Y49))) | AB49: =IF(AA49="","",IF(Z49="",IF(AA49>14,"🔴 Atrasado",IF(AA49>7,"🟡 Atenção","🟢 Em dia")),IF(TODAY()>Z49,"🔴 Atrasado",IF(Z49-TODAY()<=3,"🟡 Atenção","🟢 Em dia")))) | AD49: =IF(OR(AC49="",H49=""),"",H49*AC49) | AF49: =IF(AC49>0,AC49,'⚙️ Config'!$B$10) -> 0.0075 | AG49: =H49*AF49 -> 98186.886 | AH49: =AG49*'⚙️ Config'!$B$11 -> 490934.43 | AI49: =AH49*'⚙️ Config'!$B$12 -> 147280.33 | AJ49: 95119730 | AM49: (11) 3123-1600 | AO49: PAULO HENRIQUE PEREIRA DAMIAO | AP49: Administrador
A50: 47 | B50: FRIGOPOTI FRIGORIFICO POTI LTDA | C50: SP | D50: 05116902 | E50: 60.35 | F50: 🔴 ALTA | G50: R$ 10-20M | H50: 12931222 | I50: 2 | J50: 1.1 | K50: 2025 | L50: R D Ativa - Contribuição Previdenciária Sobre Receita Bruta | R D Ativa - Contribuição Empresa/Empregador | M50: 2025 | N50: COBRANCA | O50: =TEXT(D50,"00000000")&"0001" -> 051169020001 | P50: =IF(MOD(MID(O50,1,1)*5+MID(O50,2,1)*4+MID(O50,3,1)*3+MID(O50,4,1)*2+MID(O50,5,1)*9+MID(O50,6,1)*8+MID(O50,7,1)*7+MID(O50,8,1)*6+MID(O50,9,1)*5+MID(O50,10,1)*4+MID(O50,11,1)*3+MID(O50,12,1)*2,11)<2,0,11-MOD(MID(O50,1,1)*5+MID(O50,2,1)*4+MID(O50,3,1)*3+MID(O50,4,1)*2+MID(O50,5,1)*9+MID(O50,6,1)*8+MID(O50,7,1)*7+MID(O50,8,1)*6+MID(O50,9,1)*5+MID(O50,10,1)*4+MID(O50,11,1)*3+MID(O50,12,1)*2,11)) -> 0 | Q50: =IF(MOD(MID(O50,1,1)*6+MID(O50,2,1)*5+MID(O50,3,1)*4+MID(O50,4,1)*3+MID(O50,5,1)*2+MID(O50,6,1)*9+MID(O50,7,1)*8+MID(O50,8,1)*7+MID(O50,9,1)*6+MID(O50,10,1)*5+MID(O50,11,1)*4+MID(O50,12,1)*3+P50*2,11)<2,0,11-MOD(MID(O50,1,1)*6+MID(O50,2,1)*5+MID(O50,3,1)*4+MID(O50,4,1)*3+MID(O50,5,1)*2+MID(O50,6,1)*9+MID(O50,7,1)*8+MID(O50,8,1)*7+MID(O50,9,1)*6+MID(O50,10,1)*5+MID(O50,11,1)*4+MID(O50,12,1)*3+P50*2,11)) -> 1 | R50: =MID(O50,1,2)&"."&MID(O50,3,3)&"."&MID(O50,6,3)&"/"&MID(O50,9,4)&"-"&TEXT(P50,"0")&TEXT(Q50,"0") -> 05.116.902/0001-01 | T50: =IF(S50="","",IF(S50="Cadastrou","",XLOOKUP(S50,$BA$2:$BA$6,$BB$2:$BB$6,""))) | U50: =IF(S50="","",IF(S50="Cadastrou","",XLOOKUP(S50,$BA$2:$BA$6,$BC$2:$BC$6,""))) | V50: =IF(S50="","",XLOOKUP(S50,$BA$2:$BA$6,$BD$2:$BD$6,"")) | AA50: =IF(Y50="","",IF(INT(TODAY()-Y50)<0,"⚠️ Data futura",INT(TODAY()-Y50))) | AB50: =IF(AA50="","",IF(Z50="",IF(AA50>14,"🔴 Atrasado",IF(AA50>7,"🟡 Atenção","🟢 Em dia")),IF(TODAY()>Z50,"🔴 Atrasado",IF(Z50-TODAY()<=3,"🟡 Atenção","🟢 Em dia")))) | AD50: =IF(OR(AC50="",H50=""),"",H50*AC50) | AF50: =IF(AC50>0,AC50,'⚙️ Config'!$B$10) -> 0.0075 | AG50: =H50*AF50 -> 96984.164 | AH50: =AG50*'⚙️ Config'!$B$11 -> 484920.82 | AI50: =AH50*'⚙️ Config'!$B$12 -> 145476.25 | AJ50: 230000 | AO50: ERNESTO LUCIO CALEGARE | AP50: Sócio-Administrador
A51: 48 | B51: GAMP GRUPO DE APOIO A MEDICINA PREVENTIVA E A SAUDE PUBLICA | C51: SP | D51: 09549061 | E51: 43.68 | F51: 🔴 ALTA | G51: R$ 10-20M | H51: 12805915 | I51: 2 | J51: 1.6 | K51: 2024 | L51: Receita da dívida ativa - Multa - CLT | M51: 2024 | N51: COBRANCA | O51: =TEXT(D51,"00000000")&"0001" -> 095490610001 | P51: =IF(MOD(MID(O51,1,1)*5+MID(O51,2,1)*4+MID(O51,3,1)*3+MID(O51,4,1)*2+MID(O51,5,1)*9+MID(O51,6,1)*8+MID(O51,7,1)*7+MID(O51,8,1)*6+MID(O51,9,1)*5+MID(O51,10,1)*4+MID(O51,11,1)*3+MID(O51,12,1)*2,11)<2,0,11-MOD(MID(O51,1,1)*5+MID(O51,2,1)*4+MID(O51,3,1)*3+MID(O51,4,1)*2+MID(O51,5,1)*9+MID(O51,6,1)*8+MID(O51,7,1)*7+MID(O51,8,1)*6+MID(O51,9,1)*5+MID(O51,10,1)*4+MID(O51,11,1)*3+MID(O51,12,1)*2,11)) -> 8 | Q51: =IF(MOD(MID(O51,1,1)*6+MID(O51,2,1)*5+MID(O51,3,1)*4+MID(O51,4,1)*3+MID(O51,5,1)*2+MID(O51,6,1)*9+MID(O51,7,1)*8+MID(O51,8,1)*7+MID(O51,9,1)*6+MID(O51,10,1)*5+MID(O51,11,1)*4+MID(O51,12,1)*3+P51*2,11)<2,0,11-MOD(MID(O51,1,1)*6+MID(O51,2,1)*5+MID(O51,3,1)*4+MID(O51,4,1)*3+MID(O51,5,1)*2+MID(O51,6,1)*9+MID(O51,7,1)*8+MID(O51,8,1)*7+MID(O51,9,1)*6+MID(O51,10,1)*5+MID(O51,11,1)*4+MID(O51,12,1)*3+P51*2,11)) -> 7 | R51: =MID(O51,1,2)&"."&MID(O51,3,3)&"."&MID(O51,6,3)&"/"&MID(O51,9,4)&"-"&TEXT(P51,"0")&TEXT(Q51,"0") -> 09.549.061/0001-87 | T51: =IF(S51="","",IF(S51="Cadastrou","",XLOOKUP(S51,$BA$2:$BA$6,$BB$2:$BB$6,""))) | U51: =IF(S51="","",IF(S51="Cadastrou","",XLOOKUP(S51,$BA$2:$BA$6,$BC$2:$BC$6,""))) | V51: =IF(S51="","",XLOOKUP(S51,$BA$2:$BA$6,$BD$2:$BD$6,"")) | AA51: =IF(Y51="","",IF(INT(TODAY()-Y51)<0,"⚠️ Data futura",INT(TODAY()-Y51))) | AB51: =IF(AA51="","",IF(Z51="",IF(AA51>14,"🔴 Atrasado",IF(AA51>7,"🟡 Atenção","🟢 Em dia")),IF(TODAY()>Z51,"🔴 Atrasado",IF(Z51-TODAY()<=3,"🟡 Atenção","🟢 Em dia")))) | AD51: =IF(OR(AC51="",H51=""),"",H51*AC51) | AF51: =IF(AC51>0,AC51,'⚙️ Config'!$B$10) -> 0.0075 | AG51: =H51*AF51 -> 96044.36 | AH51: =AG51*'⚙️ Config'!$B$11 -> 480221.8 | AI51: =AH51*'⚙️ Config'!$B$12 -> 144066.54
A52: 49 | B52: PROMOCIA MARKETING PROMOCIONAL INCENTIVO PUBLICIDADE E PROPAGANDA LTDA. | C52: SP | D52: 08264743 | E52: 54.09 | F52: 🔴 ALTA | G52: R$ 10-20M | H52: 12696962 | I52: 2 | J52: 1.1 | K52: 2025 | L52: Receita da dívida ativa - PIS | Receita da dívida ativa - COFINS | M52: 2025 | N52: COBRANCA | O52: =TEXT(D52,"00000000")&"0001" -> 082647430001 | P52: =IF(MOD(MID(O52,1,1)*5+MID(O52,2,1)*4+MID(O52,3,1)*3+MID(O52,4,1)*2+MID(O52,5,1)*9+MID(O52,6,1)*8+MID(O52,7,1)*7+MID(O52,8,1)*6+MID(O52,9,1)*5+MID(O52,10,1)*4+MID(O52,11,1)*3+MID(O52,12,1)*2,11)<2,0,11-MOD(MID(O52,1,1)*5+MID(O52,2,1)*4+MID(O52,3,1)*3+MID(O52,4,1)*2+MID(O52,5,1)*9+MID(O52,6,1)*8+MID(O52,7,1)*7+MID(O52,8,1)*6+MID(O52,9,1)*5+MID(O52,10,1)*4+MID(O52,11,1)*3+MID(O52,12,1)*2,11)) -> 8 | Q52: =IF(MOD(MID(O52,1,1)*6+MID(O52,2,1)*5+MID(O52,3,1)*4+MID(O52,4,1)*3+MID(O52,5,1)*2+MID(O52,6,1)*9+MID(O52,7,1)*8+MID(O52,8,1)*7+MID(O52,9,1)*6+MID(O52,10,1)*5+MID(O52,11,1)*4+MID(O52,12,1)*3+P52*2,11)<2,0,11-MOD(MID(O52,1,1)*6+MID(O52,2,1)*5+MID(O52,3,1)*4+MID(O52,4,1)*3+MID(O52,5,1)*2+MID(O52,6,1)*9+MID(O52,7,1)*8+MID(O52,8,1)*7+MID(O52,9,1)*6+MID(O52,10,1)*5+MID(O52,11,1)*4+MID(O52,12,1)*3+P52*2,11)) -> 0 | R52: =MID(O52,1,2)&"."&MID(O52,3,3)&"."&MID(O52,6,3)&"/"&MID(O52,9,4)&"-"&TEXT(P52,"0")&TEXT(Q52,"0") -> 08.264.743/0001-80 | T52: =IF(S52="","",IF(S52="Cadastrou","",XLOOKUP(S52,$BA$2:$BA$6,$BB$2:$BB$6,""))) | U52: =IF(S52="","",IF(S52="Cadastrou","",XLOOKUP(S52,$BA$2:$BA$6,$BC$2:$BC$6,""))) | V52: =IF(S52="","",XLOOKUP(S52,$BA$2:$BA$6,$BD$2:$BD$6,"")) | AA52: =IF(Y52="","",IF(INT(TODAY()-Y52)<0,"⚠️ Data futura",INT(TODAY()-Y52))) | AB52: =IF(AA52="","",IF(Z52="",IF(AA52>14,"🔴 Atrasado",IF(AA52>7,"🟡 Atenção","🟢 Em dia")),IF(TODAY()>Z52,"🔴 Atrasado",IF(Z52-TODAY()<=3,"🟡 Atenção","🟢 Em dia")))) | AD52: =IF(OR(AC52="",H52=""),"",H52*AC52) | AF52: =IF(AC52>0,AC52,'⚙️ Config'!$B$10) -> 0.0075 | AG52: =H52*AF52 -> 95227.216 | AH52: =AG52*'⚙️ Config'!$B$11 -> 476136.08 | AI52: =AH52*'⚙️ Config'!$B$12 -> 142840.82 | AJ52: 340000 | AM52: (11) 3429-5585 | AO52: MANOEL LUIZ MARQUES | AP52: Sócio-Administrador
A53: 50 | B53: COMERCIO DE BEBIDAS GRAN DOURADOS LTDA | C53: MS | D53: 15407117 | E53: 55.34 | F53: 🔴 ALTA | G53: R$ 10-20M | H53: 12634494 | I53: 1 | J53: 1.5 | K53: 2024 | L53: Receita da dívida ativa - PIS | M53: 2024 | N53: AJUIZADA_SEM_GAR | O53: =TEXT(D53,"00000000")&"0001" -> 154071170001 | P53: =IF(MOD(MID(O53,1,1)*5+MID(O53,2,1)*4+MID(O53,3,1)*3+MID(O53,4,1)*2+MID(O53,5,1)*9+MID(O53,6,1)*8+MID(O53,7,1)*7+MID(O53,8,1)*6+MID(O53,9,1)*5+MID(O53,10,1)*4+MID(O53,11,1)*3+MID(O53,12,1)*2,11)<2,0,11-MOD(MID(O53,1,1)*5+MID(O53,2,1)*4+MID(O53,3,1)*3+MID(O53,4,1)*2+MID(O53,5,1)*9+MID(O53,6,1)*8+MID(O53,7,1)*7+MID(O53,8,1)*6+MID(O53,9,1)*5+MID(O53,10,1)*4+MID(O53,11,1)*3+MID(O53,12,1)*2,11)) -> 6 | Q53: =IF(MOD(MID(O53,1,1)*6+MID(O53,2,1)*5+MID(O53,3,1)*4+MID(O53,4,1)*3+MID(O53,5,1)*2+MID(O53,6,1)*9+MID(O53,7,1)*8+MID(O53,8,1)*7+MID(O53,9,1)*6+MID(O53,10,1)*5+MID(O53,11,1)*4+MID(O53,12,1)*3+P53*2,11)<2,0,11-MOD(MID(O53,1,1)*6+MID(O53,2,1)*5+MID(O53,3,1)*4+MID(O53,4,1)*3+MID(O53,5,1)*2+MID(O53,6,1)*9+MID(O53,7,1)*8+MID(O53,8,1)*7+MID(O53,9,1)*6+MID(O53,10,1)*5+MID(O53,11,1)*4+MID(O53,12,1)*3+P53*2,11)) -> 1 | R53: =MID(O53,1,2)&"."&MID(O53,3,3)&"."&MID(O53,6,3)&"/"&MID(O53,9,4)&"-"&TEXT(P53,"0")&TEXT(Q53,"0") -> 15.407.117/0001-61 | T53: =IF(S53="","",IF(S53="Cadastrou","",XLOOKUP(S53,$BA$2:$BA$6,$BB$2:$BB$6,""))) | U53: =IF(S53="","",IF(S53="Cadastrou","",XLOOKUP(S53,$BA$2:$BA$6,$BC$2:$BC$6,""))) | V53: =IF(S53="","",XLOOKUP(S53,$BA$2:$BA$6,$BD$2:$BD$6,"")) | AA53: =IF(Y53="","",IF(INT(TODAY()-Y53)<0,"⚠️ Data futura",INT(TODAY()-Y53))) | AB53: =IF(AA53="","",IF(Z53="",IF(AA53>14,"🔴 Atrasado",IF(AA53>7,"🟡 Atenção","🟢 Em dia")),IF(TODAY()>Z53,"🔴 Atrasado",IF(Z53-TODAY()<=3,"🟡 Atenção","🟢 Em dia")))) | AD53: =IF(OR(AC53="",H53=""),"",H53*AC53) | AF53: =IF(AC53>0,AC53,'⚙️ Config'!$B$10) -> 0.0075 | AG53: =H53*AF53 -> 94758.703 | AH53: =AG53*'⚙️ Config'!$B$11 -> 473793.52 | AI53: =AH53*'⚙️ Config'!$B$12 -> 142138.06 | AJ53: 2500000 | AM53: (67) 3411-5000 | AO53: LUCIANO PEDROSO MARIANO | AP53: Sócio-Administrador
A54: 51 | B54: MP TERRAPLENAGEM ENGENHARIA TRANSPORTES E CONSTRUCOES LTDA | C54: SP | D54: 01885848 | E54: 88.11 | F54: 🔴 ALTA | G54: R$ 10-20M | H54: 12434707 | I54: 2 | J54: 0.4 | K54: 2025 | L54: Receita da dívida ativa - CSLL | Receita da dívida ativa - IRPJ | M54: 2025 | N54: AJUIZADA_SEM_GAR | O54: =TEXT(D54,"00000000")&"0001" -> 018858480001 | P54: =IF(MOD(MID(O54,1,1)*5+MID(O54,2,1)*4+MID(O54,3,1)*3+MID(O54,4,1)*2+MID(O54,5,1)*9+MID(O54,6,1)*8+MID(O54,7,1)*7+MID(O54,8,1)*6+MID(O54,9,1)*5+MID(O54,10,1)*4+MID(O54,11,1)*3+MID(O54,12,1)*2,11)<2,0,11-MOD(MID(O54,1,1)*5+MID(O54,2,1)*4+MID(O54,3,1)*3+MID(O54,4,1)*2+MID(O54,5,1)*9+MID(O54,6,1)*8+MID(O54,7,1)*7+MID(O54,8,1)*6+MID(O54,9,1)*5+MID(O54,10,1)*4+MID(O54,11,1)*3+MID(O54,12,1)*2,11)) -> 0 | Q54: =IF(MOD(MID(O54,1,1)*6+MID(O54,2,1)*5+MID(O54,3,1)*4+MID(O54,4,1)*3+MID(O54,5,1)*2+MID(O54,6,1)*9+MID(O54,7,1)*8+MID(O54,8,1)*7+MID(O54,9,1)*6+MID(O54,10,1)*5+MID(O54,11,1)*4+MID(O54,12,1)*3+P54*2,11)<2,0,11-MOD(MID(O54,1,1)*6+MID(O54,2,1)*5+MID(O54,3,1)*4+MID(O54,4,1)*3+MID(O54,5,1)*2+MID(O54,6,1)*9+MID(O54,7,1)*8+MID(O54,8,1)*7+MID(O54,9,1)*6+MID(O54,10,1)*5+MID(O54,11,1)*4+MID(O54,12,1)*3+P54*2,11)) -> 8 | R54: =MID(O54,1,2)&"."&MID(O54,3,3)&"."&MID(O54,6,3)&"/"&MID(O54,9,4)&"-"&TEXT(P54,"0")&TEXT(Q54,"0") -> 01.885.848/0001-08 | T54: =IF(S54="","",IF(S54="Cadastrou","",XLOOKUP(S54,$BA$2:$BA$6,$BB$2:$BB$6,""))) | U54: =IF(S54="","",IF(S54="Cadastrou","",XLOOKUP(S54,$BA$2:$BA$6,$BC$2:$BC$6,""))) | V54: =IF(S54="","",XLOOKUP(S54,$BA$2:$BA$6,$BD$2:$BD$6,"")) | AA54: =IF(Y54="","",IF(INT(TODAY()-Y54)<0,"⚠️ Data futura",INT(TODAY()-Y54))) | AB54: =IF(AA54="","",IF(Z54="",IF(AA54>14,"🔴 Atrasado",IF(AA54>7,"🟡 Atenção","🟢 Em dia")),IF(TODAY()>Z54,"🔴 Atrasado",IF(Z54-TODAY()<=3,"🟡 Atenção","🟢 Em dia")))) | AD54: =IF(OR(AC54="",H54=""),"",H54*AC54) | AF54: =IF(AC54>0,AC54,'⚙️ Config'!$B$10) -> 0.0075 | AG54: =H54*AF54 -> 93260.301 | AH54: =AG54*'⚙️ Config'!$B$11 -> 466301.51 | AI54: =AH54*'⚙️ Config'!$B$12 -> 139890.45 | AJ54: 100000 | AM54: (11) 3901-9191 | AO54: ALEX SANDRO MARTINS PIRO | AP54: Sócio-Administrador
A55: 52 | B55: PREMIER FOODS LTDA | C55: SP | D55: 23285781 | E55: 68.66 | F55: 🔴 ALTA | G55: R$ 10-20M | H55: 12279189 | I55: 2 | J55: 0.7 | K55: 2025 | L55: R D Ativa - Contribuição Previdenciária Sobre Receita Bruta | R D Ativa - Contribuição Terceiros - Senar | M55: 2025 | N55: COBRANCA | O55: =TEXT(D55,"00000000")&"0001" -> 232857810001 | P55: =IF(MOD(MID(O55,1,1)*5+MID(O55,2,1)*4+MID(O55,3,1)*3+MID(O55,4,1)*2+MID(O55,5,1)*9+MID(O55,6,1)*8+MID(O55,7,1)*7+MID(O55,8,1)*6+MID(O55,9,1)*5+MID(O55,10,1)*4+MID(O55,11,1)*3+MID(O55,12,1)*2,11)<2,0,11-MOD(MID(O55,1,1)*5+MID(O55,2,1)*4+MID(O55,3,1)*3+MID(O55,4,1)*2+MID(O55,5,1)*9+MID(O55,6,1)*8+MID(O55,7,1)*7+MID(O55,8,1)*6+MID(O55,9,1)*5+MID(O55,10,1)*4+MID(O55,11,1)*3+MID(O55,12,1)*2,11)) -> 0 | Q55: =IF(MOD(MID(O55,1,1)*6+MID(O55,2,1)*5+MID(O55,3,1)*4+MID(O55,4,1)*3+MID(O55,5,1)*2+MID(O55,6,1)*9+MID(O55,7,1)*8+MID(O55,8,1)*7+MID(O55,9,1)*6+MID(O55,10,1)*5+MID(O55,11,1)*4+MID(O55,12,1)*3+P55*2,11)<2,0,11-MOD(MID(O55,1,1)*6+MID(O55,2,1)*5+MID(O55,3,1)*4+MID(O55,4,1)*3+MID(O55,5,1)*2+MID(O55,6,1)*9+MID(O55,7,1)*8+MID(O55,8,1)*7+MID(O55,9,1)*6+MID(O55,10,1)*5+MID(O55,11,1)*4+MID(O55,12,1)*3+P55*2,11)) -> 3 | R55: =MID(O55,1,2)&"."&MID(O55,3,3)&"."&MID(O55,6,3)&"/"&MID(O55,9,4)&"-"&TEXT(P55,"0")&TEXT(Q55,"0") -> 23.285.781/0001-03 | T55: =IF(S55="","",IF(S55="Cadastrou","",XLOOKUP(S55,$BA$2:$BA$6,$BB$2:$BB$6,""))) | U55: =IF(S55="","",IF(S55="Cadastrou","",XLOOKUP(S55,$BA$2:$BA$6,$BC$2:$BC$6,""))) | V55: =IF(S55="","",XLOOKUP(S55,$BA$2:$BA$6,$BD$2:$BD$6,"")) | AA55: =IF(Y55="","",IF(INT(TODAY()-Y55)<0,"⚠️ Data futura",INT(TODAY()-Y55))) | AB55: =IF(AA55="","",IF(Z55="",IF(AA55>14,"🔴 Atrasado",IF(AA55>7,"🟡 Atenção","🟢 Em dia")),IF(TODAY()>Z55,"🔴 Atrasado",IF(Z55-TODAY()<=3,"🟡 Atenção","🟢 Em dia")))) | AD55: =IF(OR(AC55="",H55=""),"",H55*AC55) | AF55: =IF(AC55>0,AC55,'⚙️ Config'!$B$10) -> 0.0075 | AG55: =H55*AF55 -> 92093.919 | AH55: =AG55*'⚙️ Config'!$B$11 -> 460469.6 | AI55: =AH55*'⚙️ Config'!$B$12 -> 138140.88
A56: 53 | B56: MEUVALE GESTAO ADMINISTRATIVA LTDA | C56: SP | D56: 18678159 | E56: 54.08 | F56: 🔴 ALTA | G56: R$ 10-20M | H56: 12130227 | I56: 2 | J56: 1.1 | K56: 2025 | L56: Receita da dívida ativa - CSLL | Receita da dívida ativa - IRPJ | M56: 2025 | N56: COBRANCA | O56: =TEXT(D56,"00000000")&"0001" -> 186781590001 | P56: =IF(MOD(MID(O56,1,1)*5+MID(O56,2,1)*4+MID(O56,3,1)*3+MID(O56,4,1)*2+MID(O56,5,1)*9+MID(O56,6,1)*8+MID(O56,7,1)*7+MID(O56,8,1)*6+MID(O56,9,1)*5+MID(O56,10,1)*4+MID(O56,11,1)*3+MID(O56,12,1)*2,11)<2,0,11-MOD(MID(O56,1,1)*5+MID(O56,2,1)*4+MID(O56,3,1)*3+MID(O56,4,1)*2+MID(O56,5,1)*9+MID(O56,6,1)*8+MID(O56,7,1)*7+MID(O56,8,1)*6+MID(O56,9,1)*5+MID(O56,10,1)*4+MID(O56,11,1)*3+MID(O56,12,1)*2,11)) -> 2 | Q56: =IF(MOD(MID(O56,1,1)*6+MID(O56,2,1)*5+MID(O56,3,1)*4+MID(O56,4,1)*3+MID(O56,5,1)*2+MID(O56,6,1)*9+MID(O56,7,1)*8+MID(O56,8,1)*7+MID(O56,9,1)*6+MID(O56,10,1)*5+MID(O56,11,1)*4+MID(O56,12,1)*3+P56*2,11)<2,0,11-MOD(MID(O56,1,1)*6+MID(O56,2,1)*5+MID(O56,3,1)*4+MID(O56,4,1)*3+MID(O56,5,1)*2+MID(O56,6,1)*9+MID(O56,7,1)*8+MID(O56,8,1)*7+MID(O56,9,1)*6+MID(O56,10,1)*5+MID(O56,11,1)*4+MID(O56,12,1)*3+P56*2,11)) -> 5 | R56: =MID(O56,1,2)&"."&MID(O56,3,3)&"."&MID(O56,6,3)&"/"&MID(O56,9,4)&"-"&TEXT(P56,"0")&TEXT(Q56,"0") -> 18.678.159/0001-25 | T56: =IF(S56="","",IF(S56="Cadastrou","",XLOOKUP(S56,$BA$2:$BA$6,$BB$2:$BB$6,""))) | U56: =IF(S56="","",IF(S56="Cadastrou","",XLOOKUP(S56,$BA$2:$BA$6,$BC$2:$BC$6,""))) | V56: =IF(S56="","",XLOOKUP(S56,$BA$2:$BA$6,$BD$2:$BD$6,"")) | AA56: =IF(Y56="","",IF(INT(TODAY()-Y56)<0,"⚠️ Data futura",INT(TODAY()-Y56))) | AB56: =IF(AA56="","",IF(Z56="",IF(AA56>14,"🔴 Atrasado",IF(AA56>7,"🟡 Atenção","🟢 Em dia")),IF(TODAY()>Z56,"🔴 Atrasado",IF(Z56-TODAY()<=3,"🟡 Atenção","🟢 Em dia")))) | AD56: =IF(OR(AC56="",H56=""),"",H56*AC56) | AF56: =IF(AC56>0,AC56,'⚙️ Config'!$B$10) -> 0.0075 | AG56: =H56*AF56 -> 90976.705 | AH56: =AG56*'⚙️ Config'!$B$11 -> 454883.53 | AI56: =AH56*'⚙️ Config'!$B$12 -> 136465.06
A57: 54 | B57: ASSOCIACAO ESCOLA DO FUTURO | C57: SP | D57: 08604054 | E57: 51.58 | F57: 🔴 ALTA | G57: R$ 10-20M | H57: 11947676 | I57: 2 | J57: 1.7 | K57: 2025 | L57: R D Ativa - Contribuição Empresa/Empregador | M57: 2024 | N57: AJUIZADA_SEM_GAR|COBRANCA | O57: =TEXT(D57,"00000000")&"0001" -> 086040540001 | P57: =IF(MOD(MID(O57,1,1)*5+MID(O57,2,1)*4+MID(O57,3,1)*3+MID(O57,4,1)*2+MID(O57,5,1)*9+MID(O57,6,1)*8+MID(O57,7,1)*7+MID(O57,8,1)*6+MID(O57,9,1)*5+MID(O57,10,1)*4+MID(O57,11,1)*3+MID(O57,12,1)*2,11)<2,0,11-MOD(MID(O57,1,1)*5+MID(O57,2,1)*4+MID(O57,3,1)*3+MID(O57,4,1)*2+MID(O57,5,1)*9+MID(O57,6,1)*8+MID(O57,7,1)*7+MID(O57,8,1)*6+MID(O57,9,1)*5+MID(O57,10,1)*4+MID(O57,11,1)*3+MID(O57,12,1)*2,11)) -> 7 | Q57: =IF(MOD(MID(O57,1,1)*6+MID(O57,2,1)*5+MID(O57,3,1)*4+MID(O57,4,1)*3+MID(O57,5,1)*2+MID(O57,6,1)*9+MID(O57,7,1)*8+MID(O57,8,1)*7+MID(O57,9,1)*6+MID(O57,10,1)*5+MID(O57,11,1)*4+MID(O57,12,1)*3+P57*2,11)<2,0,11-MOD(MID(O57,1,1)*6+MID(O57,2,1)*5+MID(O57,3,1)*4+MID(O57,4,1)*3+MID(O57,5,1)*2+MID(O57,6,1)*9+MID(O57,7,1)*8+MID(O57,8,1)*7+MID(O57,9,1)*6+MID(O57,10,1)*5+MID(O57,11,1)*4+MID(O57,12,1)*3+P57*2,11)) -> 8 | R57: =MID(O57,1,2)&"."&MID(O57,3,3)&"."&MID(O57,6,3)&"/"&MID(O57,9,4)&"-"&TEXT(P57,"0")&TEXT(Q57,"0") -> 08.604.054/0001-78 | T57: =IF(S57="","",IF(S57="Cadastrou","",XLOOKUP(S57,$BA$2:$BA$6,$BB$2:$BB$6,""))) | U57: =IF(S57="","",IF(S57="Cadastrou","",XLOOKUP(S57,$BA$2:$BA$6,$BC$2:$BC$6,""))) | V57: =IF(S57="","",XLOOKUP(S57,$BA$2:$BA$6,$BD$2:$BD$6,"")) | AA57: =IF(Y57="","",IF(INT(TODAY()-Y57)<0,"⚠️ Data futura",INT(TODAY()-Y57))) | AB57: =IF(AA57="","",IF(Z57="",IF(AA57>14,"🔴 Atrasado",IF(AA57>7,"🟡 Atenção","🟢 Em dia")),IF(TODAY()>Z57,"🔴 Atrasado",IF(Z57-TODAY()<=3,"🟡 Atenção","🟢 Em dia")))) | AD57: =IF(OR(AC57="",H57=""),"",H57*AC57) | AF57: =IF(AC57>0,AC57,'⚙️ Config'!$B$10) -> 0.0075 | AG57: =H57*AF57 -> 89607.57 | AH57: =AG57*'⚙️ Config'!$B$11 -> 448037.85 | AI57: =AH57*'⚙️ Config'!$B$12 -> 134411.36 | AM57: (11) 3813-9748 | AO57: LUIZ CARLOS MUNIZ | AP57: Presidente
A58: 55 | B58: GAMA SERVICOS E NEGOCIOS LTDA | C58: SP | D58: 05867976 | E58: 56.74 | F58: 🔴 ALTA | G58: R$ 10-20M | H58: 11481542 | I58: 2 | J58: 1.1 | K58: 2025 | L58: R D Ativa - Multa Isolada | M58: 2025 | N58: COBRANCA | O58: =TEXT(D58,"00000000")&"0001" -> 058679760001 | P58: =IF(MOD(MID(O58,1,1)*5+MID(O58,2,1)*4+MID(O58,3,1)*3+MID(O58,4,1)*2+MID(O58,5,1)*9+MID(O58,6,1)*8+MID(O58,7,1)*7+MID(O58,8,1)*6+MID(O58,9,1)*5+MID(O58,10,1)*4+MID(O58,11,1)*3+MID(O58,12,1)*2,11)<2,0,11-MOD(MID(O58,1,1)*5+MID(O58,2,1)*4+MID(O58,3,1)*3+MID(O58,4,1)*2+MID(O58,5,1)*9+MID(O58,6,1)*8+MID(O58,7,1)*7+MID(O58,8,1)*6+MID(O58,9,1)*5+MID(O58,10,1)*4+MID(O58,11,1)*3+MID(O58,12,1)*2,11)) -> 8 | Q58: =IF(MOD(MID(O58,1,1)*6+MID(O58,2,1)*5+MID(O58,3,1)*4+MID(O58,4,1)*3+MID(O58,5,1)*2+MID(O58,6,1)*9+MID(O58,7,1)*8+MID(O58,8,1)*7+MID(O58,9,1)*6+MID(O58,10,1)*5+MID(O58,11,1)*4+MID(O58,12,1)*3+P58*2,11)<2,0,11-MOD(MID(O58,1,1)*6+MID(O58,2,1)*5+MID(O58,3,1)*4+MID(O58,4,1)*3+MID(O58,5,1)*2+MID(O58,6,1)*9+MID(O58,7,1)*8+MID(O58,8,1)*7+MID(O58,9,1)*6+MID(O58,10,1)*5+MID(O58,11,1)*4+MID(O58,12,1)*3+P58*2,11)) -> 0 | R58: =MID(O58,1,2)&"."&MID(O58,3,3)&"."&MID(O58,6,3)&"/"&MID(O58,9,4)&"-"&TEXT(P58,"0")&TEXT(Q58,"0") -> 05.867.976/0001-80 | T58: =IF(S58="","",IF(S58="Cadastrou","",XLOOKUP(S58,$BA$2:$BA$6,$BB$2:$BB$6,""))) | U58: =IF(S58="","",IF(S58="Cadastrou","",XLOOKUP(S58,$BA$2:$BA$6,$BC$2:$BC$6,""))) | V58: =IF(S58="","",XLOOKUP(S58,$BA$2:$BA$6,$BD$2:$BD$6,"")) | AA58: =IF(Y58="","",IF(INT(TODAY()-Y58)<0,"⚠️ Data futura",INT(TODAY()-Y58))) | AB58: =IF(AA58="","",IF(Z58="",IF(AA58>14,"🔴 Atrasado",IF(AA58>7,"🟡 Atenção","🟢 Em dia")),IF(TODAY()>Z58,"🔴 Atrasado",IF(Z58-TODAY()<=3,"🟡 Atenção","🟢 Em dia")))) | AD58: =IF(OR(AC58="",H58=""),"",H58*AC58) | AF58: =IF(AC58>0,AC58,'⚙️ Config'!$B$10) -> 0.0075 | AG58: =H58*AF58 -> 86111.565 | AH58: =AG58*'⚙️ Config'!$B$11 -> 430557.83 | AI58: =AH58*'⚙️ Config'!$B$12 -> 129167.35 | AJ58: 532000 | AM58: (11) 4984-4884 | AO58: ALDO GALESCO JUNIOR | AP58: Sócio-Administrador
A59: 56 | B59: CONTRATA CONSTRUCOES E COMERCIO LTDA | C59: SP | D59: 44907418 | E59: 49.19 | F59: 🔴 ALTA | G59: R$ 10-20M | H59: 11282663 | I59: 2 | J59: 1.3 | K59: 2024 | L59: Receita da dívida ativa - IRPJ | Receita da dívida ativa - COFINS | M59: 2024 | N59: AJUIZADA_SEM_GAR | O59: =TEXT(D59,"00000000")&"0001" -> 449074180001 | P59: =IF(MOD(MID(O59,1,1)*5+MID(O59,2,1)*4+MID(O59,3,1)*3+MID(O59,4,1)*2+MID(O59,5,1)*9+MID(O59,6,1)*8+MID(O59,7,1)*7+MID(O59,8,1)*6+MID(O59,9,1)*5+MID(O59,10,1)*4+MID(O59,11,1)*3+MID(O59,12,1)*2,11)<2,0,11-MOD(MID(O59,1,1)*5+MID(O59,2,1)*4+MID(O59,3,1)*3+MID(O59,4,1)*2+MID(O59,5,1)*9+MID(O59,6,1)*8+MID(O59,7,1)*7+MID(O59,8,1)*6+MID(O59,9,1)*5+MID(O59,10,1)*4+MID(O59,11,1)*3+MID(O59,12,1)*2,11)) -> 5 | Q59: =IF(MOD(MID(O59,1,1)*6+MID(O59,2,1)*5+MID(O59,3,1)*4+MID(O59,4,1)*3+MID(O59,5,1)*2+MID(O59,6,1)*9+MID(O59,7,1)*8+MID(O59,8,1)*7+MID(O59,9,1)*6+MID(O59,10,1)*5+MID(O59,11,1)*4+MID(O59,12,1)*3+P59*2,11)<2,0,11-MOD(MID(O59,1,1)*6+MID(O59,2,1)*5+MID(O59,3,1)*4+MID(O59,4,1)*3+MID(O59,5,1)*2+MID(O59,6,1)*9+MID(O59,7,1)*8+MID(O59,8,1)*7+MID(O59,9,1)*6+MID(O59,10,1)*5+MID(O59,11,1)*4+MID(O59,12,1)*3+P59*2,11)) -> 2 | R59: =MID(O59,1,2)&"."&MID(O59,3,3)&"."&MID(O59,6,3)&"/"&MID(O59,9,4)&"-"&TEXT(P59,"0")&TEXT(Q59,"0") -> 44.907.418/0001-52 | T59: =IF(S59="","",IF(S59="Cadastrou","",XLOOKUP(S59,$BA$2:$BA$6,$BB$2:$BB$6,""))) | U59: =IF(S59="","",IF(S59="Cadastrou","",XLOOKUP(S59,$BA$2:$BA$6,$BC$2:$BC$6,""))) | V59: =IF(S59="","",XLOOKUP(S59,$BA$2:$BA$6,$BD$2:$BD$6,"")) | AA59: =IF(Y59="","",IF(INT(TODAY()-Y59)<0,"⚠️ Data futura",INT(TODAY()-Y59))) | AB59: =IF(AA59="","",IF(Z59="",IF(AA59>14,"🔴 Atrasado",IF(AA59>7,"🟡 Atenção","🟢 Em dia")),IF(TODAY()>Z59,"🔴 Atrasado",IF(Z59-TODAY()<=3,"🟡 Atenção","🟢 Em dia")))) | AD59: =IF(OR(AC59="",H59=""),"",H59*AC59) | AF59: =IF(AC59>0,AC59,'⚙️ Config'!$B$10) -> 0.0075 | AG59: =H59*AF59 -> 84619.971 | AH59: =AG59*'⚙️ Config'!$B$11 -> 423099.85 | AI59: =AH59*'⚙️ Config'!$B$12 -> 126929.96 | AM59: (11) 3258-0968 | AO59: CAROLINA ROSSI ZAMPINI | AP59: Sócio-Administrador
A60: 57 | B60: INCLUA DENTAL LTDA | C60: SP | D60: 40121595 | E60: 73.94 | F60: 🔴 ALTA | G60: R$ 10-20M | H60: 11202191 | I60: 2 | J60: 0.6 | K60: 2025 | L60: Receita da dívida ativa - CSLL | Receita da dívida ativa - IRPJ | M60: 2025 | N60: COBRANCA | O60: =TEXT(D60,"00000000")&"0001" -> 401215950001 | P60: =IF(MOD(MID(O60,1,1)*5+MID(O60,2,1)*4+MID(O60,3,1)*3+MID(O60,4,1)*2+MID(O60,5,1)*9+MID(O60,6,1)*8+MID(O60,7,1)*7+MID(O60,8,1)*6+MID(O60,9,1)*5+MID(O60,10,1)*4+MID(O60,11,1)*3+MID(O60,12,1)*2,11)<2,0,11-MOD(MID(O60,1,1)*5+MID(O60,2,1)*4+MID(O60,3,1)*3+MID(O60,4,1)*2+MID(O60,5,1)*9+MID(O60,6,1)*8+MID(O60,7,1)*7+MID(O60,8,1)*6+MID(O60,9,1)*5+MID(O60,10,1)*4+MID(O60,11,1)*3+MID(O60,12,1)*2,11)) -> 5 | Q60: =IF(MOD(MID(O60,1,1)*6+MID(O60,2,1)*5+MID(O60,3,1)*4+MID(O60,4,1)*3+MID(O60,5,1)*2+MID(O60,6,1)*9+MID(O60,7,1)*8+MID(O60,8,1)*7+MID(O60,9,1)*6+MID(O60,10,1)*5+MID(O60,11,1)*4+MID(O60,12,1)*3+P60*2,11)<2,0,11-MOD(MID(O60,1,1)*6+MID(O60,2,1)*5+MID(O60,3,1)*4+MID(O60,4,1)*3+MID(O60,5,1)*2+MID(O60,6,1)*9+MID(O60,7,1)*8+MID(O60,8,1)*7+MID(O60,9,1)*6+MID(O60,10,1)*5+MID(O60,11,1)*4+MID(O60,12,1)*3+P60*2,11)) -> 8 | R60: =MID(O60,1,2)&"."&MID(O60,3,3)&"."&MID(O60,6,3)&"/"&MID(O60,9,4)&"-"&TEXT(P60,"0")&TEXT(Q60,"0") -> 40.121.595/0001-58 | T60: =IF(S60="","",IF(S60="Cadastrou","",XLOOKUP(S60,$BA$2:$BA$6,$BB$2:$BB$6,""))) | U60: =IF(S60="","",IF(S60="Cadastrou","",XLOOKUP(S60,$BA$2:$BA$6,$BC$2:$BC$6,""))) | V60: =IF(S60="","",XLOOKUP(S60,$BA$2:$BA$6,$BD$2:$BD$6,"")) | AA60: =IF(Y60="","",IF(INT(TODAY()-Y60)<0,"⚠️ Data futura",INT(TODAY()-Y60))) | AB60: =IF(AA60="","",IF(Z60="",IF(AA60>14,"🔴 Atrasado",IF(AA60>7,"🟡 Atenção","🟢 Em dia")),IF(TODAY()>Z60,"🔴 Atrasado",IF(Z60-TODAY()<=3,"🟡 Atenção","🟢 Em dia")))) | AD60: =IF(OR(AC60="",H60=""),"",H60*AC60) | AF60: =IF(AC60>0,AC60,'⚙️ Config'!$B$10) -> 0.0075 | AG60: =H60*AF60 -> 84016.436 | AH60: =AG60*'⚙️ Config'!$B$11 -> 420082.18 | AI60: =AH60*'⚙️ Config'!$B$12 -> 126024.65 | AJ60: 1000 | AM60: (11) 3231-0704 | AO60: VICTOR FISS | AP60: Administrador
A61: 58 | B61: AQUAFEED NUTRICAO ANIMAL S.A. | C61: MS | D61: 13274958 | E61: 64.14 | F61: 🔴 ALTA | G61: R$ 10-20M | H61: 11105780 | I61: 2 | J61: 0.8 | K61: 2025 | L61: Receita da dívida ativa - CSLL | Receita da dívida ativa - IRPJ | M61: 2025 | N61: COBRANCA | O61: =TEXT(D61,"00000000")&"0001" -> 132749580001 | P61: =IF(MOD(MID(O61,1,1)*5+MID(O61,2,1)*4+MID(O61,3,1)*3+MID(O61,4,1)*2+MID(O61,5,1)*9+MID(O61,6,1)*8+MID(O61,7,1)*7+MID(O61,8,1)*6+MID(O61,9,1)*5+MID(O61,10,1)*4+MID(O61,11,1)*3+MID(O61,12,1)*2,11)<2,0,11-MOD(MID(O61,1,1)*5+MID(O61,2,1)*4+MID(O61,3,1)*3+MID(O61,4,1)*2+MID(O61,5,1)*9+MID(O61,6,1)*8+MID(O61,7,1)*7+MID(O61,8,1)*6+MID(O61,9,1)*5+MID(O61,10,1)*4+MID(O61,11,1)*3+MID(O61,12,1)*2,11)) -> 1 | Q61: =IF(MOD(MID(O61,1,1)*6+MID(O61,2,1)*5+MID(O61,3,1)*4+MID(O61,4,1)*3+MID(O61,5,1)*2+MID(O61,6,1)*9+MID(O61,7,1)*8+MID(O61,8,1)*7+MID(O61,9,1)*6+MID(O61,10,1)*5+MID(O61,11,1)*4+MID(O61,12,1)*3+P61*2,11)<2,0,11-MOD(MID(O61,1,1)*6+MID(O61,2,1)*5+MID(O61,3,1)*4+MID(O61,4,1)*3+MID(O61,5,1)*2+MID(O61,6,1)*9+MID(O61,7,1)*8+MID(O61,8,1)*7+MID(O61,9,1)*6+MID(O61,10,1)*5+MID(O61,11,1)*4+MID(O61,12,1)*3+P61*2,11)) -> 2 | R61: =MID(O61,1,2)&"."&MID(O61,3,3)&"."&MID(O61,6,3)&"/"&MID(O61,9,4)&"-"&TEXT(P61,"0")&TEXT(Q61,"0") -> 13.274.958/0001-12 | T61: =IF(S61="","",IF(S61="Cadastrou","",XLOOKUP(S61,$BA$2:$BA$6,$BB$2:$BB$6,""))) | U61: =IF(S61="","",IF(S61="Cadastrou","",XLOOKUP(S61,$BA$2:$BA$6,$BC$2:$BC$6,""))) | V61: =IF(S61="","",XLOOKUP(S61,$BA$2:$BA$6,$BD$2:$BD$6,"")) | AA61: =IF(Y61="","",IF(INT(TODAY()-Y61)<0,"⚠️ Data futura",INT(TODAY()-Y61))) | AB61: =IF(AA61="","",IF(Z61="",IF(AA61>14,"🔴 Atrasado",IF(AA61>7,"🟡 Atenção","🟢 Em dia")),IF(TODAY()>Z61,"🔴 Atrasado",IF(Z61-TODAY()<=3,"🟡 Atenção","🟢 Em dia")))) | AD61: =IF(OR(AC61="",H61=""),"",H61*AC61) | AF61: =IF(AC61>0,AC61,'⚙️ Config'!$B$10) -> 0.0075 | AG61: =H61*AF61 -> 83293.353 | AH61: =AG61*'⚙️ Config'!$B$11 -> 416466.77 | AI61: =AH61*'⚙️ Config'!$B$12 -> 124940.03 | AJ61: 19005922 | AM61: (11) 3123-2106 | AO61: MARCOS VINICIUS FARINA PALUDO | AP61: Diretor
A62: 59 | B62: GP GUARDA PATRIMONIAL DE MINAS GERAIS LTDA | C62: SP | D62: 10403744 | E62: 64.05 | F62: 🔴 ALTA | G62: R$ 10-20M | H62: 11032126 | I62: 1 | J62: 1.1 | K62: 2025 | L62: R D Ativa - Glosa de Compensação Previdenciária | M62: 2025 | N62: COBRANCA | O62: =TEXT(D62,"00000000")&"0001" -> 104037440001 | P62: =IF(MOD(MID(O62,1,1)*5+MID(O62,2,1)*4+MID(O62,3,1)*3+MID(O62,4,1)*2+MID(O62,5,1)*9+MID(O62,6,1)*8+MID(O62,7,1)*7+MID(O62,8,1)*6+MID(O62,9,1)*5+MID(O62,10,1)*4+MID(O62,11,1)*3+MID(O62,12,1)*2,11)<2,0,11-MOD(MID(O62,1,1)*5+MID(O62,2,1)*4+MID(O62,3,1)*3+MID(O62,4,1)*2+MID(O62,5,1)*9+MID(O62,6,1)*8+MID(O62,7,1)*7+MID(O62,8,1)*6+MID(O62,9,1)*5+MID(O62,10,1)*4+MID(O62,11,1)*3+MID(O62,12,1)*2,11)) -> 0 | Q62: =IF(MOD(MID(O62,1,1)*6+MID(O62,2,1)*5+MID(O62,3,1)*4+MID(O62,4,1)*3+MID(O62,5,1)*2+MID(O62,6,1)*9+MID(O62,7,1)*8+MID(O62,8,1)*7+MID(O62,9,1)*6+MID(O62,10,1)*5+MID(O62,11,1)*4+MID(O62,12,1)*3+P62*2,11)<2,0,11-MOD(MID(O62,1,1)*6+MID(O62,2,1)*5+MID(O62,3,1)*4+MID(O62,4,1)*3+MID(O62,5,1)*2+MID(O62,6,1)*9+MID(O62,7,1)*8+MID(O62,8,1)*7+MID(O62,9,1)*6+MID(O62,10,1)*5+MID(O62,11,1)*4+MID(O62,12,1)*3+P62*2,11)) -> 0 | R62: =MID(O62,1,2)&"."&MID(O62,3,3)&"."&MID(O62,6,3)&"/"&MID(O62,9,4)&"-"&TEXT(P62,"0")&TEXT(Q62,"0") -> 10.403.744/0001-00 | T62: =IF(S62="","",IF(S62="Cadastrou","",XLOOKUP(S62,$BA$2:$BA$6,$BB$2:$BB$6,""))) | U62: =IF(S62="","",IF(S62="Cadastrou","",XLOOKUP(S62,$BA$2:$BA$6,$BC$2:$BC$6,""))) | V62: =IF(S62="","",XLOOKUP(S62,$BA$2:$BA$6,$BD$2:$BD$6,"")) | AA62: =IF(Y62="","",IF(INT(TODAY()-Y62)<0,"⚠️ Data futura",INT(TODAY()-Y62))) | AB62: =IF(AA62="","",IF(Z62="",IF(AA62>14,"🔴 Atrasado",IF(AA62>7,"🟡 Atenção","🟢 Em dia")),IF(TODAY()>Z62,"🔴 Atrasado",IF(Z62-TODAY()<=3,"🟡 Atenção","🟢 Em dia")))) | AD62: =IF(OR(AC62="",H62=""),"",H62*AC62) | AF62: =IF(AC62>0,AC62,'⚙️ Config'!$B$10) -> 0.0075 | AG62: =H62*AF62 -> 82740.948 | AH62: =AG62*'⚙️ Config'!$B$11 -> 413704.74 | AI62: =AH62*'⚙️ Config'!$B$12 -> 124111.42 | AJ62: 120000 | AM62: (11) 4858-9085 | AO62: MILTON PAULO BECHERI | AP62: Sócio-Administrador
A63: 60 | B63: CALCARIO BELA VISTA LTDA | C63: MS | D63: 09225584 | E63: 39.46 | F63: 🔴 ALTA | G63: R$ 10-20M | H63: 10949330 | I63: 2 | J63: 1.9 | K63: 2024 | L63: Receita da dívida ativa - CSLL | Receita da dívida ativa - IRPJ | M63: 2024 | N63: AJUIZADA_SEM_GAR | O63: =TEXT(D63,"00000000")&"0001" -> 092255840001 | P63: =IF(MOD(MID(O63,1,1)*5+MID(O63,2,1)*4+MID(O63,3,1)*3+MID(O63,4,1)*2+MID(O63,5,1)*9+MID(O63,6,1)*8+MID(O63,7,1)*7+MID(O63,8,1)*6+MID(O63,9,1)*5+MID(O63,10,1)*4+MID(O63,11,1)*3+MID(O63,12,1)*2,11)<2,0,11-MOD(MID(O63,1,1)*5+MID(O63,2,1)*4+MID(O63,3,1)*3+MID(O63,4,1)*2+MID(O63,5,1)*9+MID(O63,6,1)*8+MID(O63,7,1)*7+MID(O63,8,1)*6+MID(O63,9,1)*5+MID(O63,10,1)*4+MID(O63,11,1)*3+MID(O63,12,1)*2,11)) -> 7 | Q63: =IF(MOD(MID(O63,1,1)*6+MID(O63,2,1)*5+MID(O63,3,1)*4+MID(O63,4,1)*3+MID(O63,5,1)*2+MID(O63,6,1)*9+MID(O63,7,1)*8+MID(O63,8,1)*7+MID(O63,9,1)*6+MID(O63,10,1)*5+MID(O63,11,1)*4+MID(O63,12,1)*3+P63*2,11)<2,0,11-MOD(MID(O63,1,1)*6+MID(O63,2,1)*5+MID(O63,3,1)*4+MID(O63,4,1)*3+MID(O63,5,1)*2+MID(O63,6,1)*9+MID(O63,7,1)*8+MID(O63,8,1)*7+MID(O63,9,1)*6+MID(O63,10,1)*5+MID(O63,11,1)*4+MID(O63,12,1)*3+P63*2,11)) -> 8 | R63: =MID(O63,1,2)&"."&MID(O63,3,3)&"."&MID(O63,6,3)&"/"&MID(O63,9,4)&"-"&TEXT(P63,"0")&TEXT(Q63,"0") -> 09.225.584/0001-78 | T63: =IF(S63="","",IF(S63="Cadastrou","",XLOOKUP(S63,$BA$2:$BA$6,$BB$2:$BB$6,""))) | U63: =IF(S63="","",IF(S63="Cadastrou","",XLOOKUP(S63,$BA$2:$BA$6,$BC$2:$BC$6,""))) | V63: =IF(S63="","",XLOOKUP(S63,$BA$2:$BA$6,$BD$2:$BD$6,"")) | AA63: =IF(Y63="","",IF(INT(TODAY()-Y63)<0,"⚠️ Data futura",INT(TODAY()-Y63))) | AB63: =IF(AA63="","",IF(Z63="",IF(AA63>14,"🔴 Atrasado",IF(AA63>7,"🟡 Atenção","🟢 Em dia")),IF(TODAY()>Z63,"🔴 Atrasado",IF(Z63-TODAY()<=3,"🟡 Atenção","🟢 Em dia")))) | AD63: =IF(OR(AC63="",H63=""),"",H63*AC63) | AF63: =IF(AC63>0,AC63,'⚙️ Config'!$B$10) -> 0.0075 | AG63: =H63*AF63 -> 82119.976 | AH63: =AG63*'⚙️ Config'!$B$11 -> 410599.88 | AI63: =AH63*'⚙️ Config'!$B$12 -> 123179.96 | AJ63: 6415398 | AM63: (67) 3439-1500 | AO63: ANA PAULA DE CARVALHO VILLELA DE ANDRADE GONCALVES DIAS | AP63: Administrador
A64: 61 | B64: RILTY ENGENHARIA LTDA | C64: SP | D64: 20059339 | E64: 65.29 | F64: 🔴 ALTA | G64: R$ 10-20M | H64: 10642620 | I64: 2 | J64: 1.1 | K64: 2025 | L64: Receita da dívida ativa - CSLL | Receita da dívida ativa - IRPJ | M64: 2025 | N64: AJUIZADA_SEM_GAR|OUTROS | O64: =TEXT(D64,"00000000")&"0001" -> 200593390001 | P64: =IF(MOD(MID(O64,1,1)*5+MID(O64,2,1)*4+MID(O64,3,1)*3+MID(O64,4,1)*2+MID(O64,5,1)*9+MID(O64,6,1)*8+MID(O64,7,1)*7+MID(O64,8,1)*6+MID(O64,9,1)*5+MID(O64,10,1)*4+MID(O64,11,1)*3+MID(O64,12,1)*2,11)<2,0,11-MOD(MID(O64,1,1)*5+MID(O64,2,1)*4+MID(O64,3,1)*3+MID(O64,4,1)*2+MID(O64,5,1)*9+MID(O64,6,1)*8+MID(O64,7,1)*7+MID(O64,8,1)*6+MID(O64,9,1)*5+MID(O64,10,1)*4+MID(O64,11,1)*3+MID(O64,12,1)*2,11)) -> 7 | Q64: =IF(MOD(MID(O64,1,1)*6+MID(O64,2,1)*5+MID(O64,3,1)*4+MID(O64,4,1)*3+MID(O64,5,1)*2+MID(O64,6,1)*9+MID(O64,7,1)*8+MID(O64,8,1)*7+MID(O64,9,1)*6+MID(O64,10,1)*5+MID(O64,11,1)*4+MID(O64,12,1)*3+P64*2,11)<2,0,11-MOD(MID(O64,1,1)*6+MID(O64,2,1)*5+MID(O64,3,1)*4+MID(O64,4,1)*3+MID(O64,5,1)*2+MID(O64,6,1)*9+MID(O64,7,1)*8+MID(O64,8,1)*7+MID(O64,9,1)*6+MID(O64,10,1)*5+MID(O64,11,1)*4+MID(O64,12,1)*3+P64*2,11)) -> 0 | R64: =MID(O64,1,2)&"."&MID(O64,3,3)&"."&MID(O64,6,3)&"/"&MID(O64,9,4)&"-"&TEXT(P64,"0")&TEXT(Q64,"0") -> 20.059.339/0001-70 | T64: =IF(S64="","",IF(S64="Cadastrou","",XLOOKUP(S64,$BA$2:$BA$6,$BB$2:$BB$6,""))) | U64: =IF(S64="","",IF(S64="Cadastrou","",XLOOKUP(S64,$BA$2:$BA$6,$BC$2:$BC$6,""))) | V64: =IF(S64="","",XLOOKUP(S64,$BA$2:$BA$6,$BD$2:$BD$6,"")) | AA64: =IF(Y64="","",IF(INT(TODAY()-Y64)<0,"⚠️ Data futura",INT(TODAY()-Y64))) | AB64: =IF(AA64="","",IF(Z64="",IF(AA64>14,"🔴 Atrasado",IF(AA64>7,"🟡 Atenção","🟢 Em dia")),IF(TODAY()>Z64,"🔴 Atrasado",IF(Z64-TODAY()<=3,"🟡 Atenção","🟢 Em dia")))) | AD64: =IF(OR(AC64="",H64=""),"",H64*AC64) | AF64: =IF(AC64>0,AC64,'⚙️ Config'!$B$10) -> 0.0075 | AG64: =H64*AF64 -> 79819.652 | AH64: =AG64*'⚙️ Config'!$B$11 -> 399098.26 | AI64: =AH64*'⚙️ Config'!$B$12 -> 119729.48 | AJ64: 8000000 | AM64: (11) 2548-0599 | AO64: LUIZ GUSTAVO MARTINS | AP64: Sócio-Administrador
A65: 62 | B65: SP TRADE COMERCIAL IMPORTACAO E EXPORTACAO LTDA | C65: SP | D65: 06114131 | E65: 49.45 | F65: 🔴 ALTA | G65: R$ 10-20M | H65: 10630201 | I65: 1 | J65: 1.9 | K65: 2024 | L65: R D Ativa - Multa Isolada | M65: 2024 | N65: COBRANCA | O65: =TEXT(D65,"00000000")&"0001" -> 061141310001 | P65: =IF(MOD(MID(O65,1,1)*5+MID(O65,2,1)*4+MID(O65,3,1)*3+MID(O65,4,1)*2+MID(O65,5,1)*9+MID(O65,6,1)*8+MID(O65,7,1)*7+MID(O65,8,1)*6+MID(O65,9,1)*5+MID(O65,10,1)*4+MID(O65,11,1)*3+MID(O65,12,1)*2,11)<2,0,11-MOD(MID(O65,1,1)*5+MID(O65,2,1)*4+MID(O65,3,1)*3+MID(O65,4,1)*2+MID(O65,5,1)*9+MID(O65,6,1)*8+MID(O65,7,1)*7+MID(O65,8,1)*6+MID(O65,9,1)*5+MID(O65,10,1)*4+MID(O65,11,1)*3+MID(O65,12,1)*2,11)) -> 8 | Q65: =IF(MOD(MID(O65,1,1)*6+MID(O65,2,1)*5+MID(O65,3,1)*4+MID(O65,4,1)*3+MID(O65,5,1)*2+MID(O65,6,1)*9+MID(O65,7,1)*8+MID(O65,8,1)*7+MID(O65,9,1)*6+MID(O65,10,1)*5+MID(O65,11,1)*4+MID(O65,12,1)*3+P65*2,11)<2,0,11-MOD(MID(O65,1,1)*6+MID(O65,2,1)*5+MID(O65,3,1)*4+MID(O65,4,1)*3+MID(O65,5,1)*2+MID(O65,6,1)*9+MID(O65,7,1)*8+MID(O65,8,1)*7+MID(O65,9,1)*6+MID(O65,10,1)*5+MID(O65,11,1)*4+MID(O65,12,1)*3+P65*2,11)) -> 6 | R65: =MID(O65,1,2)&"."&MID(O65,3,3)&"."&MID(O65,6,3)&"/"&MID(O65,9,4)&"-"&TEXT(P65,"0")&TEXT(Q65,"0") -> 06.114.131/0001-86 | T65: =IF(S65="","",IF(S65="Cadastrou","",XLOOKUP(S65,$BA$2:$BA$6,$BB$2:$BB$6,""))) | U65: =IF(S65="","",IF(S65="Cadastrou","",XLOOKUP(S65,$BA$2:$BA$6,$BC$2:$BC$6,""))) | V65: =IF(S65="","",XLOOKUP(S65,$BA$2:$BA$6,$BD$2:$BD$6,"")) | AA65: =IF(Y65="","",IF(INT(TODAY()-Y65)<0,"⚠️ Data futura",INT(TODAY()-Y65))) | AB65: =IF(AA65="","",IF(Z65="",IF(AA65>14,"🔴 Atrasado",IF(AA65>7,"🟡 Atenção","🟢 Em dia")),IF(TODAY()>Z65,"🔴 Atrasado",IF(Z65-TODAY()<=3,"🟡 Atenção","🟢 Em dia")))) | AD65: =IF(OR(AC65="",H65=""),"",H65*AC65) | AF65: =IF(AC65>0,AC65,'⚙️ Config'!$B$10) -> 0.0075 | AG65: =H65*AF65 -> 79726.505 | AH65: =AG65*'⚙️ Config'!$B$11 -> 398632.53 | AI65: =AH65*'⚙️ Config'!$B$12 -> 119589.76
A66: 63 | B66: RESINOR RESINAS SINTETICAS SA | C66: SP | D66: 09119447 | E66: 64.03 | F66: 🔴 ALTA | G66: R$ 10-20M | H66: 10608542 | I66: 1 | J66: 1.1 | K66: 2025 | L66: IPI - Receita da dívida ativa | M66: 2025 | N66: COBRANCA | O66: =TEXT(D66,"00000000")&"0001" -> 091194470001 | P66: =IF(MOD(MID(O66,1,1)*5+MID(O66,2,1)*4+MID(O66,3,1)*3+MID(O66,4,1)*2+MID(O66,5,1)*9+MID(O66,6,1)*8+MID(O66,7,1)*7+MID(O66,8,1)*6+MID(O66,9,1)*5+MID(O66,10,1)*4+MID(O66,11,1)*3+MID(O66,12,1)*2,11)<2,0,11-MOD(MID(O66,1,1)*5+MID(O66,2,1)*4+MID(O66,3,1)*3+MID(O66,4,1)*2+MID(O66,5,1)*9+MID(O66,6,1)*8+MID(O66,7,1)*7+MID(O66,8,1)*6+MID(O66,9,1)*5+MID(O66,10,1)*4+MID(O66,11,1)*3+MID(O66,12,1)*2,11)) -> 5 | Q66: =IF(MOD(MID(O66,1,1)*6+MID(O66,2,1)*5+MID(O66,3,1)*4+MID(O66,4,1)*3+MID(O66,5,1)*2+MID(O66,6,1)*9+MID(O66,7,1)*8+MID(O66,8,1)*7+MID(O66,9,1)*6+MID(O66,10,1)*5+MID(O66,11,1)*4+MID(O66,12,1)*3+P66*2,11)<2,0,11-MOD(MID(O66,1,1)*6+MID(O66,2,1)*5+MID(O66,3,1)*4+MID(O66,4,1)*3+MID(O66,5,1)*2+MID(O66,6,1)*9+MID(O66,7,1)*8+MID(O66,8,1)*7+MID(O66,9,1)*6+MID(O66,10,1)*5+MID(O66,11,1)*4+MID(O66,12,1)*3+P66*2,11)) -> 9 | R66: =MID(O66,1,2)&"."&MID(O66,3,3)&"."&MID(O66,6,3)&"/"&MID(O66,9,4)&"-"&TEXT(P66,"0")&TEXT(Q66,"0") -> 09.119.447/0001-59 | T66: =IF(S66="","",IF(S66="Cadastrou","",XLOOKUP(S66,$BA$2:$BA$6,$BB$2:$BB$6,""))) | U66: =IF(S66="","",IF(S66="Cadastrou","",XLOOKUP(S66,$BA$2:$BA$6,$BC$2:$BC$6,""))) | V66: =IF(S66="","",XLOOKUP(S66,$BA$2:$BA$6,$BD$2:$BD$6,"")) | AA66: =IF(Y66="","",IF(INT(TODAY()-Y66)<0,"⚠️ Data futura",INT(TODAY()-Y66))) | AB66: =IF(AA66="","",IF(Z66="",IF(AA66>14,"🔴 Atrasado",IF(AA66>7,"🟡 Atenção","🟢 Em dia")),IF(TODAY()>Z66,"🔴 Atrasado",IF(Z66-TODAY()<=3,"🟡 Atenção","🟢 Em dia")))) | AD66: =IF(OR(AC66="",H66=""),"",H66*AC66) | AF66: =IF(AC66>0,AC66,'⚙️ Config'!$B$10) -> 0.0075 | AG66: =H66*AF66 -> 79564.065 | AH66: =AG66*'⚙️ Config'!$B$11 -> 397820.33 | AI66: =AH66*'⚙️ Config'!$B$12 -> 119346.1
A67: 64 | B67: APIS DELTA LTDA | C67: SP | D67: 01940049 | E67: 66.95 | F67: 🔴 ALTA | G67: R$ 10-20M | H67: 10596743 | I67: 1 | J67: 1 | K67: 2025 | L67: IPI - Receita da dívida ativa | M67: 2025 | N67: AJUIZADA_SEM_GAR | O67: =TEXT(D67,"00000000")&"0001" -> 019400490001 | P67: =IF(MOD(MID(O67,1,1)*5+MID(O67,2,1)*4+MID(O67,3,1)*3+MID(O67,4,1)*2+MID(O67,5,1)*9+MID(O67,6,1)*8+MID(O67,7,1)*7+MID(O67,8,1)*6+MID(O67,9,1)*5+MID(O67,10,1)*4+MID(O67,11,1)*3+MID(O67,12,1)*2,11)<2,0,11-MOD(MID(O67,1,1)*5+MID(O67,2,1)*4+MID(O67,3,1)*3+MID(O67,4,1)*2+MID(O67,5,1)*9+MID(O67,6,1)*8+MID(O67,7,1)*7+MID(O67,8,1)*6+MID(O67,9,1)*5+MID(O67,10,1)*4+MID(O67,11,1)*3+MID(O67,12,1)*2,11)) -> 9 | Q67: =IF(MOD(MID(O67,1,1)*6+MID(O67,2,1)*5+MID(O67,3,1)*4+MID(O67,4,1)*3+MID(O67,5,1)*2+MID(O67,6,1)*9+MID(O67,7,1)*8+MID(O67,8,1)*7+MID(O67,9,1)*6+MID(O67,10,1)*5+MID(O67,11,1)*4+MID(O67,12,1)*3+P67*2,11)<2,0,11-MOD(MID(O67,1,1)*6+MID(O67,2,1)*5+MID(O67,3,1)*4+MID(O67,4,1)*3+MID(O67,5,1)*2+MID(O67,6,1)*9+MID(O67,7,1)*8+MID(O67,8,1)*7+MID(O67,9,1)*6+MID(O67,10,1)*5+MID(O67,11,1)*4+MID(O67,12,1)*3+P67*2,11)) -> 7 | R67: =MID(O67,1,2)&"."&MID(O67,3,3)&"."&MID(O67,6,3)&"/"&MID(O67,9,4)&"-"&TEXT(P67,"0")&TEXT(Q67,"0") -> 01.940.049/0001-97 | T67: =IF(S67="","",IF(S67="Cadastrou","",XLOOKUP(S67,$BA$2:$BA$6,$BB$2:$BB$6,""))) | U67: =IF(S67="","",IF(S67="Cadastrou","",XLOOKUP(S67,$BA$2:$BA$6,$BC$2:$BC$6,""))) | V67: =IF(S67="","",XLOOKUP(S67,$BA$2:$BA$6,$BD$2:$BD$6,"")) | AA67: =IF(Y67="","",IF(INT(TODAY()-Y67)<0,"⚠️ Data futura",INT(TODAY()-Y67))) | AB67: =IF(AA67="","",IF(Z67="",IF(AA67>14,"🔴 Atrasado",IF(AA67>7,"🟡 Atenção","🟢 Em dia")),IF(TODAY()>Z67,"🔴 Atrasado",IF(Z67-TODAY()<=3,"🟡 Atenção","🟢 Em dia")))) | AD67: =IF(OR(AC67="",H67=""),"",H67*AC67) | AF67: =IF(AC67>0,AC67,'⚙️ Config'!$B$10) -> 0.0075 | AG67: =H67*AF67 -> 79475.572 | AH67: =AG67*'⚙️ Config'!$B$11 -> 397377.86 | AI67: =AH67*'⚙️ Config'!$B$12 -> 119213.36 | AJ67: 9808613 | AM67: (11) 4056-2300 | AO67: SILVIA MOREIRA SILVA | AP67: Administrador
A68: 65 | B68: COMERCIAL FORT METAL FERRAGENS E FERRAMENTAS LTDA | C68: SP | D68: 01436308 | E68: 39.44 | F68: 🔴 ALTA | G68: R$ 10-20M | H68: 10142581 | I68: 2 | J68: 1.9 | K68: 2024 | L68: Receita da dívida ativa - IRPJ | Receita da dívida ativa - IRRF | M68: 2024 | N68: COBRANCA | O68: =TEXT(D68,"00000000")&"0001" -> 014363080001 | P68: =IF(MOD(MID(O68,1,1)*5+MID(O68,2,1)*4+MID(O68,3,1)*3+MID(O68,4,1)*2+MID(O68,5,1)*9+MID(O68,6,1)*8+MID(O68,7,1)*7+MID(O68,8,1)*6+MID(O68,9,1)*5+MID(O68,10,1)*4+MID(O68,11,1)*3+MID(O68,12,1)*2,11)<2,0,11-MOD(MID(O68,1,1)*5+MID(O68,2,1)*4+MID(O68,3,1)*3+MID(O68,4,1)*2+MID(O68,5,1)*9+MID(O68,6,1)*8+MID(O68,7,1)*7+MID(O68,8,1)*6+MID(O68,9,1)*5+MID(O68,10,1)*4+MID(O68,11,1)*3+MID(O68,12,1)*2,11)) -> 4 | Q68: =IF(MOD(MID(O68,1,1)*6+MID(O68,2,1)*5+MID(O68,3,1)*4+MID(O68,4,1)*3+MID(O68,5,1)*2+MID(O68,6,1)*9+MID(O68,7,1)*8+MID(O68,8,1)*7+MID(O68,9,1)*6+MID(O68,10,1)*5+MID(O68,11,1)*4+MID(O68,12,1)*3+P68*2,11)<2,0,11-MOD(MID(O68,1,1)*6+MID(O68,2,1)*5+MID(O68,3,1)*4+MID(O68,4,1)*3+MID(O68,5,1)*2+MID(O68,6,1)*9+MID(O68,7,1)*8+MID(O68,8,1)*7+MID(O68,9,1)*6+MID(O68,10,1)*5+MID(O68,11,1)*4+MID(O68,12,1)*3+P68*2,11)) -> 7 | R68: =MID(O68,1,2)&"."&MID(O68,3,3)&"."&MID(O68,6,3)&"/"&MID(O68,9,4)&"-"&TEXT(P68,"0")&TEXT(Q68,"0") -> 01.436.308/0001-47 | T68: =IF(S68="","",IF(S68="Cadastrou","",XLOOKUP(S68,$BA$2:$BA$6,$BB$2:$BB$6,""))) | U68: =IF(S68="","",IF(S68="Cadastrou","",XLOOKUP(S68,$BA$2:$BA$6,$BC$2:$BC$6,""))) | V68: =IF(S68="","",XLOOKUP(S68,$BA$2:$BA$6,$BD$2:$BD$6,"")) | AA68: =IF(Y68="","",IF(INT(TODAY()-Y68)<0,"⚠️ Data futura",INT(TODAY()-Y68))) | AB68: =IF(AA68="","",IF(Z68="",IF(AA68>14,"🔴 Atrasado",IF(AA68>7,"🟡 Atenção","🟢 Em dia")),IF(TODAY()>Z68,"🔴 Atrasado",IF(Z68-TODAY()<=3,"🟡 Atenção","🟢 Em dia")))) | AD68: =IF(OR(AC68="",H68=""),"",H68*AC68) | AF68: =IF(AC68>0,AC68,'⚙️ Config'!$B$10) -> 0.0075 | AG68: =H68*AF68 -> 76069.355 | AH68: =AG68*'⚙️ Config'!$B$11 -> 380346.77 | AI68: =AH68*'⚙️ Config'!$B$12 -> 114104.03
A69: 66 | B69: INDARU INDUSTRIA E COMERCIO LTD | C69: SP | D69: 62474564 | E69: 52.09 | F69: 🔴 ALTA | G69: R$ 5-10M | H69: 9974958.8 | I69: 1 | J69: 1.7 | K69: 2024 | L69: IPI - Receita da dívida ativa | M69: 2024 | N69: COBRANCA | O69: =TEXT(D69,"00000000")&"0001" -> 624745640001 | P69: =IF(MOD(MID(O69,1,1)*5+MID(O69,2,1)*4+MID(O69,3,1)*3+MID(O69,4,1)*2+MID(O69,5,1)*9+MID(O69,6,1)*8+MID(O69,7,1)*7+MID(O69,8,1)*6+MID(O69,9,1)*5+MID(O69,10,1)*4+MID(O69,11,1)*3+MID(O69,12,1)*2,11)<2,0,11-MOD(MID(O69,1,1)*5+MID(O69,2,1)*4+MID(O69,3,1)*3+MID(O69,4,1)*2+MID(O69,5,1)*9+MID(O69,6,1)*8+MID(O69,7,1)*7+MID(O69,8,1)*6+MID(O69,9,1)*5+MID(O69,10,1)*4+MID(O69,11,1)*3+MID(O69,12,1)*2,11)) -> 1 | Q69: =IF(MOD(MID(O69,1,1)*6+MID(O69,2,1)*5+MID(O69,3,1)*4+MID(O69,4,1)*3+MID(O69,5,1)*2+MID(O69,6,1)*9+MID(O69,7,1)*8+MID(O69,8,1)*7+MID(O69,9,1)*6+MID(O69,10,1)*5+MID(O69,11,1)*4+MID(O69,12,1)*3+P69*2,11)<2,0,11-MOD(MID(O69,1,1)*6+MID(O69,2,1)*5+MID(O69,3,1)*4+MID(O69,4,1)*3+MID(O69,5,1)*2+MID(O69,6,1)*9+MID(O69,7,1)*8+MID(O69,8,1)*7+MID(O69,9,1)*6+MID(O69,10,1)*5+MID(O69,11,1)*4+MID(O69,12,1)*3+P69*2,11)) -> 3 | R69: =MID(O69,1,2)&"."&MID(O69,3,3)&"."&MID(O69,6,3)&"/"&MID(O69,9,4)&"-"&TEXT(P69,"0")&TEXT(Q69,"0") -> 62.474.564/0001-13 | T69: =IF(S69="","",IF(S69="Cadastrou","",XLOOKUP(S69,$BA$2:$BA$6,$BB$2:$BB$6,""))) | U69: =IF(S69="","",IF(S69="Cadastrou","",XLOOKUP(S69,$BA$2:$BA$6,$BC$2:$BC$6,""))) | V69: =IF(S69="","",XLOOKUP(S69,$BA$2:$BA$6,$BD$2:$BD$6,"")) | AA69: =IF(Y69="","",IF(INT(TODAY()-Y69)<0,"⚠️ Data futura",INT(TODAY()-Y69))) | AB69: =IF(AA69="","",IF(Z69="",IF(AA69>14,"🔴 Atrasado",IF(AA69>7,"🟡 Atenção","🟢 Em dia")),IF(TODAY()>Z69,"🔴 Atrasado",IF(Z69-TODAY()<=3,"🟡 Atenção","🟢 Em dia")))) | AD69: =IF(OR(AC69="",H69=""),"",H69*AC69) | AF69: =IF(AC69>0,AC69,'⚙️ Config'!$B$10) -> 0.0075 | AG69: =H69*AF69 -> 74812.191 | AH69: =AG69*'⚙️ Config'!$B$11 -> 374060.96 | AI69: =AH69*'⚙️ Config'!$B$12 -> 112218.29 | AO69: PEDRO JESUS SERRANO LETOSA | AP69: Sócio-Administrador
A70: 67 | B70: SCIENCE VALE CONSULTORIA PESQUISA E DESENVOLVIMENTO NA AREA MEDICA LTDA | C70: SP | D70: 30324102 | E70: 54.01 | F70: 🔴 ALTA | G70: R$ 5-10M | H70: 9694333.9 | I70: 2 | J70: 1.1 | K70: 2025 | L70: Receita da dívida ativa - CSLL | Receita da dívida ativa - IRPJ | M70: 2025 | N70: AJUIZADA_SEM_GAR | O70: =TEXT(D70,"00000000")&"0001" -> 303241020001 | P70: =IF(MOD(MID(O70,1,1)*5+MID(O70,2,1)*4+MID(O70,3,1)*3+MID(O70,4,1)*2+MID(O70,5,1)*9+MID(O70,6,1)*8+MID(O70,7,1)*7+MID(O70,8,1)*6+MID(O70,9,1)*5+MID(O70,10,1)*4+MID(O70,11,1)*3+MID(O70,12,1)*2,11)<2,0,11-MOD(MID(O70,1,1)*5+MID(O70,2,1)*4+MID(O70,3,1)*3+MID(O70,4,1)*2+MID(O70,5,1)*9+MID(O70,6,1)*8+MID(O70,7,1)*7+MID(O70,8,1)*6+MID(O70,9,1)*5+MID(O70,10,1)*4+MID(O70,11,1)*3+MID(O70,12,1)*2,11)) -> 2 | Q70: =IF(MOD(MID(O70,1,1)*6+MID(O70,2,1)*5+MID(O70,3,1)*4+MID(O70,4,1)*3+MID(O70,5,1)*2+MID(O70,6,1)*9+MID(O70,7,1)*8+MID(O70,8,1)*7+MID(O70,9,1)*6+MID(O70,10,1)*5+MID(O70,11,1)*4+MID(O70,12,1)*3+P70*2,11)<2,0,11-MOD(MID(O70,1,1)*6+MID(O70,2,1)*5+MID(O70,3,1)*4+MID(O70,4,1)*3+MID(O70,5,1)*2+MID(O70,6,1)*9+MID(O70,7,1)*8+MID(O70,8,1)*7+MID(O70,9,1)*6+MID(O70,10,1)*5+MID(O70,11,1)*4+MID(O70,12,1)*3+P70*2,11)) -> 3 | R70: =MID(O70,1,2)&"."&MID(O70,3,3)&"."&MID(O70,6,3)&"/"&MID(O70,9,4)&"-"&TEXT(P70,"0")&TEXT(Q70,"0") -> 30.324.102/0001-23 | T70: =IF(S70="","",IF(S70="Cadastrou","",XLOOKUP(S70,$BA$2:$BA$6,$BB$2:$BB$6,""))) | U70: =IF(S70="","",IF(S70="Cadastrou","",XLOOKUP(S70,$BA$2:$BA$6,$BC$2:$BC$6,""))) | V70: =IF(S70="","",XLOOKUP(S70,$BA$2:$BA$6,$BD$2:$BD$6,"")) | AA70: =IF(Y70="","",IF(INT(TODAY()-Y70)<0,"⚠️ Data futura",INT(TODAY()-Y70))) | AB70: =IF(AA70="","",IF(Z70="",IF(AA70>14,"🔴 Atrasado",IF(AA70>7,"🟡 Atenção","🟢 Em dia")),IF(TODAY()>Z70,"🔴 Atrasado",IF(Z70-TODAY()<=3,"🟡 Atenção","🟢 Em dia")))) | AD70: =IF(OR(AC70="",H70=""),"",H70*AC70) | AF70: =IF(AC70>0,AC70,'⚙️ Config'!$B$10) -> 0.0075 | AG70: =H70*AF70 -> 72707.505 | AH70: =AG70*'⚙️ Config'!$B$11 -> 363537.52 | AI70: =AH70*'⚙️ Config'!$B$12 -> 109061.26 | AJ70: 10000 | AM70: (11) 4040-8670 | AO70: EDUARDO RAMACCIOTTI | AP70: Sócio-Administrador
A71: 68 | B71: VOLKSWAGEN PARTICIPACOES LTDA | C71: SP | D71: 03495672 | E71: 68.59 | F71: 🔴 ALTA | G71: R$ 5-10M | H71: 9540132.4 | I71: 2 | J71: 0.7 | K71: 2025 | L71: Receita da dívida ativa - PIS | Receita da dívida ativa - IRRF | M71: 2025 | N71: COBRANCA | O71: =TEXT(D71,"00000000")&"0001" -> 034956720001 | P71: =IF(MOD(MID(O71,1,1)*5+MID(O71,2,1)*4+MID(O71,3,1)*3+MID(O71,4,1)*2+MID(O71,5,1)*9+MID(O71,6,1)*8+MID(O71,7,1)*7+MID(O71,8,1)*6+MID(O71,9,1)*5+MID(O71,10,1)*4+MID(O71,11,1)*3+MID(O71,12,1)*2,11)<2,0,11-MOD(MID(O71,1,1)*5+MID(O71,2,1)*4+MID(O71,3,1)*3+MID(O71,4,1)*2+MID(O71,5,1)*9+MID(O71,6,1)*8+MID(O71,7,1)*7+MID(O71,8,1)*6+MID(O71,9,1)*5+MID(O71,10,1)*4+MID(O71,11,1)*3+MID(O71,12,1)*2,11)) -> 0 | Q71: =IF(MOD(MID(O71,1,1)*6+MID(O71,2,1)*5+MID(O71,3,1)*4+MID(O71,4,1)*3+MID(O71,5,1)*2+MID(O71,6,1)*9+MID(O71,7,1)*8+MID(O71,8,1)*7+MID(O71,9,1)*6+MID(O71,10,1)*5+MID(O71,11,1)*4+MID(O71,12,1)*3+P71*2,11)<2,0,11-MOD(MID(O71,1,1)*6+MID(O71,2,1)*5+MID(O71,3,1)*4+MID(O71,4,1)*3+MID(O71,5,1)*2+MID(O71,6,1)*9+MID(O71,7,1)*8+MID(O71,8,1)*7+MID(O71,9,1)*6+MID(O71,10,1)*5+MID(O71,11,1)*4+MID(O71,12,1)*3+P71*2,11)) -> 3 | R71: =MID(O71,1,2)&"."&MID(O71,3,3)&"."&MID(O71,6,3)&"/"&MID(O71,9,4)&"-"&TEXT(P71,"0")&TEXT(Q71,"0") -> 03.495.672/0001-03 | T71: =IF(S71="","",IF(S71="Cadastrou","",XLOOKUP(S71,$BA$2:$BA$6,$BB$2:$BB$6,""))) | U71: =IF(S71="","",IF(S71="Cadastrou","",XLOOKUP(S71,$BA$2:$BA$6,$BC$2:$BC$6,""))) | V71: =IF(S71="","",XLOOKUP(S71,$BA$2:$BA$6,$BD$2:$BD$6,"")) | AA71: =IF(Y71="","",IF(INT(TODAY()-Y71)<0,"⚠️ Data futura",INT(TODAY()-Y71))) | AB71: =IF(AA71="","",IF(Z71="",IF(AA71>14,"🔴 Atrasado",IF(AA71>7,"🟡 Atenção","🟢 Em dia")),IF(TODAY()>Z71,"🔴 Atrasado",IF(Z71-TODAY()<=3,"🟡 Atenção","🟢 Em dia")))) | AD71: =IF(OR(AC71="",H71=""),"",H71*AC71) | AF71: =IF(AC71>0,AC71,'⚙️ Config'!$B$10) -> 0.0075 | AG71: =H71*AF71 -> 71550.993 | AH71: =AG71*'⚙️ Config'!$B$11 -> 357754.97 | AI71: =AH71*'⚙️ Config'!$B$12 -> 107326.49 | AP71: 3459360
A72: 69 | B72: PROLUB SERVICOS ADMINISTRATIVOS LTDA | C72: SP | D72: 52554300 | E72: 38.25 | F72: 🔴 ALTA | G72: R$ 5-10M | H72: 9470663.6 | I72: 2 | J72: 2 | K72: 2024 | L72: Receita da dívida ativa - CSLL | Receita da dívida ativa - IRPJ | M72: 2024 | N72: AJUIZADA_SEM_GAR|COBRANCA | O72: =TEXT(D72,"00000000")&"0001" -> 525543000001 | P72: =IF(MOD(MID(O72,1,1)*5+MID(O72,2,1)*4+MID(O72,3,1)*3+MID(O72,4,1)*2+MID(O72,5,1)*9+MID(O72,6,1)*8+MID(O72,7,1)*7+MID(O72,8,1)*6+MID(O72,9,1)*5+MID(O72,10,1)*4+MID(O72,11,1)*3+MID(O72,12,1)*2,11)<2,0,11-MOD(MID(O72,1,1)*5+MID(O72,2,1)*4+MID(O72,3,1)*3+MID(O72,4,1)*2+MID(O72,5,1)*9+MID(O72,6,1)*8+MID(O72,7,1)*7+MID(O72,8,1)*6+MID(O72,9,1)*5+MID(O72,10,1)*4+MID(O72,11,1)*3+MID(O72,12,1)*2,11)) -> 1 | Q72: =IF(MOD(MID(O72,1,1)*6+MID(O72,2,1)*5+MID(O72,3,1)*4+MID(O72,4,1)*3+MID(O72,5,1)*2+MID(O72,6,1)*9+MID(O72,7,1)*8+MID(O72,8,1)*7+MID(O72,9,1)*6+MID(O72,10,1)*5+MID(O72,11,1)*4+MID(O72,12,1)*3+P72*2,11)<2,0,11-MOD(MID(O72,1,1)*6+MID(O72,2,1)*5+MID(O72,3,1)*4+MID(O72,4,1)*3+MID(O72,5,1)*2+MID(O72,6,1)*9+MID(O72,7,1)*8+MID(O72,8,1)*7+MID(O72,9,1)*6+MID(O72,10,1)*5+MID(O72,11,1)*4+MID(O72,12,1)*3+P72*2,11)) -> 6 | R72: =MID(O72,1,2)&"."&MID(O72,3,3)&"."&MID(O72,6,3)&"/"&MID(O72,9,4)&"-"&TEXT(P72,"0")&TEXT(Q72,"0") -> 52.554.300/0001-16 | T72: =IF(S72="","",IF(S72="Cadastrou","",XLOOKUP(S72,$BA$2:$BA$6,$BB$2:$BB$6,""))) | U72: =IF(S72="","",IF(S72="Cadastrou","",XLOOKUP(S72,$BA$2:$BA$6,$BC$2:$BC$6,""))) | V72: =IF(S72="","",XLOOKUP(S72,$BA$2:$BA$6,$BD$2:$BD$6,"")) | AA72: =IF(Y72="","",IF(INT(TODAY()-Y72)<0,"⚠️ Data futura",INT(TODAY()-Y72))) | AB72: =IF(AA72="","",IF(Z72="",IF(AA72>14,"🔴 Atrasado",IF(AA72>7,"🟡 Atenção","🟢 Em dia")),IF(TODAY()>Z72,"🔴 Atrasado",IF(Z72-TODAY()<=3,"🟡 Atenção","🟢 Em dia")))) | AD72: =IF(OR(AC72="",H72=""),"",H72*AC72) | AF72: =IF(AC72>0,AC72,'⚙️ Config'!$B$10) -> 0.0075 | AG72: =H72*AF72 -> 71029.977 | AH72: =AG72*'⚙️ Config'!$B$11 -> 355149.89 | AI72: =AH72*'⚙️ Config'!$B$12 -> 106544.97 | AJ72: 3459360 | AM72: (18) 3311-1665 | AO72: DEMETRIO AUGUSTO ZACHARIAS | AP72: Sócio-Administrador
A73: 70 | B73: ATENAS ELETRO ELETRONICOS LTDA | C73: SP | D73: 16868040 | E73: 60.25 | F73: 🔴 ALTA | G73: R$ 5-10M | H73: 9350328.9 | I73: 2 | J73: 0.9 | K73: 2025 | L73: Receita da dívida ativa - CSLL | Receita da dívida ativa - IRPJ | M73: 2025 | N73: COBRANCA | O73: =TEXT(D73,"00000000")&"0001" -> 168680400001 | P73: =IF(MOD(MID(O73,1,1)*5+MID(O73,2,1)*4+MID(O73,3,1)*3+MID(O73,4,1)*2+MID(O73,5,1)*9+MID(O73,6,1)*8+MID(O73,7,1)*7+MID(O73,8,1)*6+MID(O73,9,1)*5+MID(O73,10,1)*4+MID(O73,11,1)*3+MID(O73,12,1)*2,11)<2,0,11-MOD(MID(O73,1,1)*5+MID(O73,2,1)*4+MID(O73,3,1)*3+MID(O73,4,1)*2+MID(O73,5,1)*9+MID(O73,6,1)*8+MID(O73,7,1)*7+MID(O73,8,1)*6+MID(O73,9,1)*5+MID(O73,10,1)*4+MID(O73,11,1)*3+MID(O73,12,1)*2,11)) -> 9 | Q73: =IF(MOD(MID(O73,1,1)*6+MID(O73,2,1)*5+MID(O73,3,1)*4+MID(O73,4,1)*3+MID(O73,5,1)*2+MID(O73,6,1)*9+MID(O73,7,1)*8+MID(O73,8,1)*7+MID(O73,9,1)*6+MID(O73,10,1)*5+MID(O73,11,1)*4+MID(O73,12,1)*3+P73*2,11)<2,0,11-MOD(MID(O73,1,1)*6+MID(O73,2,1)*5+MID(O73,3,1)*4+MID(O73,4,1)*3+MID(O73,5,1)*2+MID(O73,6,1)*9+MID(O73,7,1)*8+MID(O73,8,1)*7+MID(O73,9,1)*6+MID(O73,10,1)*5+MID(O73,11,1)*4+MID(O73,12,1)*3+P73*2,11)) -> 0 | R73: =MID(O73,1,2)&"."&MID(O73,3,3)&"."&MID(O73,6,3)&"/"&MID(O73,9,4)&"-"&TEXT(P73,"0")&TEXT(Q73,"0") -> 16.868.040/0001-90 | T73: =IF(S73="","",IF(S73="Cadastrou","",XLOOKUP(S73,$BA$2:$BA$6,$BB$2:$BB$6,""))) | U73: =IF(S73="","",IF(S73="Cadastrou","",XLOOKUP(S73,$BA$2:$BA$6,$BC$2:$BC$6,""))) | V73: =IF(S73="","",XLOOKUP(S73,$BA$2:$BA$6,$BD$2:$BD$6,"")) | AA73: =IF(Y73="","",IF(INT(TODAY()-Y73)<0,"⚠️ Data futura",INT(TODAY()-Y73))) | AB73: =IF(AA73="","",IF(Z73="",IF(AA73>14,"🔴 Atrasado",IF(AA73>7,"🟡 Atenção","🟢 Em dia")),IF(TODAY()>Z73,"🔴 Atrasado",IF(Z73-TODAY()<=3,"🟡 Atenção","🟢 Em dia")))) | AD73: =IF(OR(AC73="",H73=""),"",H73*AC73) | AF73: =IF(AC73>0,AC73,'⚙️ Config'!$B$10) -> 0.0075 | AG73: =H73*AF73 -> 70127.467 | AH73: =AG73*'⚙️ Config'!$B$11 -> 350637.33 | AI73: =AH73*'⚙️ Config'!$B$12 -> 105191.2
A74: 71 | B74: AMG COMERCIO DE MATERIAIS LTDA | C74: SP | D74: 18939938 | E74: 43.58 | F74: 🔴 ALTA | G74: R$ 5-10M | H74: 9225140 | I74: 2 | J74: 1.9 | K74: 2024 | L74: Receita da dívida ativa - IRPJ | M74: 2024 | N74: AJUIZADA_SEM_GAR | O74: =TEXT(D74,"00000000")&"0001" -> 189399380001 | P74: =IF(MOD(MID(O74,1,1)*5+MID(O74,2,1)*4+MID(O74,3,1)*3+MID(O74,4,1)*2+MID(O74,5,1)*9+MID(O74,6,1)*8+MID(O74,7,1)*7+MID(O74,8,1)*6+MID(O74,9,1)*5+MID(O74,10,1)*4+MID(O74,11,1)*3+MID(O74,12,1)*2,11)<2,0,11-MOD(MID(O74,1,1)*5+MID(O74,2,1)*4+MID(O74,3,1)*3+MID(O74,4,1)*2+MID(O74,5,1)*9+MID(O74,6,1)*8+MID(O74,7,1)*7+MID(O74,8,1)*6+MID(O74,9,1)*5+MID(O74,10,1)*4+MID(O74,11,1)*3+MID(O74,12,1)*2,11)) -> 3 | Q74: =IF(MOD(MID(O74,1,1)*6+MID(O74,2,1)*5+MID(O74,3,1)*4+MID(O74,4,1)*3+MID(O74,5,1)*2+MID(O74,6,1)*9+MID(O74,7,1)*8+MID(O74,8,1)*7+MID(O74,9,1)*6+MID(O74,10,1)*5+MID(O74,11,1)*4+MID(O74,12,1)*3+P74*2,11)<2,0,11-MOD(MID(O74,1,1)*6+MID(O74,2,1)*5+MID(O74,3,1)*4+MID(O74,4,1)*3+MID(O74,5,1)*2+MID(O74,6,1)*9+MID(O74,7,1)*8+MID(O74,8,1)*7+MID(O74,9,1)*6+MID(O74,10,1)*5+MID(O74,11,1)*4+MID(O74,12,1)*3+P74*2,11)) -> 7 | R74: =MID(O74,1,2)&"."&MID(O74,3,3)&"."&MID(O74,6,3)&"/"&MID(O74,9,4)&"-"&TEXT(P74,"0")&TEXT(Q74,"0") -> 18.939.938/0001-37 | T74: =IF(S74="","",IF(S74="Cadastrou","",XLOOKUP(S74,$BA$2:$BA$6,$BB$2:$BB$6,""))) | U74: =IF(S74="","",IF(S74="Cadastrou","",XLOOKUP(S74,$BA$2:$BA$6,$BC$2:$BC$6,""))) | V74: =IF(S74="","",XLOOKUP(S74,$BA$2:$BA$6,$BD$2:$BD$6,"")) | AA74: =IF(Y74="","",IF(INT(TODAY()-Y74)<0,"⚠️ Data futura",INT(TODAY()-Y74))) | AB74: =IF(AA74="","",IF(Z74="",IF(AA74>14,"🔴 Atrasado",IF(AA74>7,"🟡 Atenção","🟢 Em dia")),IF(TODAY()>Z74,"🔴 Atrasado",IF(Z74-TODAY()<=3,"🟡 Atenção","🟢 Em dia")))) | AD74: =IF(OR(AC74="",H74=""),"",H74*AC74) | AF74: =IF(AC74>0,AC74,'⚙️ Config'!$B$10) -> 0.0075 | AG74: =H74*AF74 -> 69188.55 | AH74: =AG74*'⚙️ Config'!$B$11 -> 345942.75 | AI74: =AH74*'⚙️ Config'!$B$12 -> 103782.82
A75: 72 | B75: ECB COMERCIAL BAZAR LTDA | C75: SP | D75: 07604491 | E75: 48.25 | F75: 🔴 ALTA | G75: R$ 5-10M | H75: 9216257.6 | I75: 1 | J75: 2 | K75: 2024 | L75: R D Ativa - Multa Isolada | M75: 2024 | N75: AJUIZADA_SEM_GAR | O75: =TEXT(D75,"00000000")&"0001" -> 076044910001 | P75: =IF(MOD(MID(O75,1,1)*5+MID(O75,2,1)*4+MID(O75,3,1)*3+MID(O75,4,1)*2+MID(O75,5,1)*9+MID(O75,6,1)*8+MID(O75,7,1)*7+MID(O75,8,1)*6+MID(O75,9,1)*5+MID(O75,10,1)*4+MID(O75,11,1)*3+MID(O75,12,1)*2,11)<2,0,11-MOD(MID(O75,1,1)*5+MID(O75,2,1)*4+MID(O75,3,1)*3+MID(O75,4,1)*2+MID(O75,5,1)*9+MID(O75,6,1)*8+MID(O75,7,1)*7+MID(O75,8,1)*6+MID(O75,9,1)*5+MID(O75,10,1)*4+MID(O75,11,1)*3+MID(O75,12,1)*2,11)) -> 2 | Q75: =IF(MOD(MID(O75,1,1)*6+MID(O75,2,1)*5+MID(O75,3,1)*4+MID(O75,4,1)*3+MID(O75,5,1)*2+MID(O75,6,1)*9+MID(O75,7,1)*8+MID(O75,8,1)*7+MID(O75,9,1)*6+MID(O75,10,1)*5+MID(O75,11,1)*4+MID(O75,12,1)*3+P75*2,11)<2,0,11-MOD(MID(O75,1,1)*6+MID(O75,2,1)*5+MID(O75,3,1)*4+MID(O75,4,1)*3+MID(O75,5,1)*2+MID(O75,6,1)*9+MID(O75,7,1)*8+MID(O75,8,1)*7+MID(O75,9,1)*6+MID(O75,10,1)*5+MID(O75,11,1)*4+MID(O75,12,1)*3+P75*2,11)) -> 9 | R75: =MID(O75,1,2)&"."&MID(O75,3,3)&"."&MID(O75,6,3)&"/"&MID(O75,9,4)&"-"&TEXT(P75,"0")&TEXT(Q75,"0") -> 07.604.491/0001-29 | T75: =IF(S75="","",IF(S75="Cadastrou","",XLOOKUP(S75,$BA$2:$BA$6,$BB$2:$BB$6,""))) | U75: =IF(S75="","",IF(S75="Cadastrou","",XLOOKUP(S75,$BA$2:$BA$6,$BC$2:$BC$6,""))) | V75: =IF(S75="","",XLOOKUP(S75,$BA$2:$BA$6,$BD$2:$BD$6,"")) | AA75: =IF(Y75="","",IF(INT(TODAY()-Y75)<0,"⚠️ Data futura",INT(TODAY()-Y75))) | AB75: =IF(AA75="","",IF(Z75="",IF(AA75>14,"🔴 Atrasado",IF(AA75>7,"🟡 Atenção","🟢 Em dia")),IF(TODAY()>Z75,"🔴 Atrasado",IF(Z75-TODAY()<=3,"🟡 Atenção","🟢 Em dia")))) | AD75: =IF(OR(AC75="",H75=""),"",H75*AC75) | AF75: =IF(AC75>0,AC75,'⚙️ Config'!$B$10) -> 0.0075 | AG75: =H75*AF75 -> 69121.932 | AH75: =AG75*'⚙️ Config'!$B$11 -> 345609.66 | AI75: =AH75*'⚙️ Config'!$B$12 -> 103682.9
A76: 73 | B76: PONTO A PONTO SP CONSERVACAO COMERCIAL E DOMICILIAR LTDA | C76: SP | D76: 19447268 | E76: 54 | F76: 🔴 ALTA | G76: R$ 5-10M | H76: 9141304.5 | I76: 2 | J76: 1.1 | K76: 2025 | L76: Receita da dívida ativa - CSLL | Receita da dívida ativa - IRPJ | M76: 2025 | N76: COBRANCA | O76: =TEXT(D76,"00000000")&"0001" -> 194472680001 | P76: =IF(MOD(MID(O76,1,1)*5+MID(O76,2,1)*4+MID(O76,3,1)*3+MID(O76,4,1)*2+MID(O76,5,1)*9+MID(O76,6,1)*8+MID(O76,7,1)*7+MID(O76,8,1)*6+MID(O76,9,1)*5+MID(O76,10,1)*4+MID(O76,11,1)*3+MID(O76,12,1)*2,11)<2,0,11-MOD(MID(O76,1,1)*5+MID(O76,2,1)*4+MID(O76,3,1)*3+MID(O76,4,1)*2+MID(O76,5,1)*9+MID(O76,6,1)*8+MID(O76,7,1)*7+MID(O76,8,1)*6+MID(O76,9,1)*5+MID(O76,10,1)*4+MID(O76,11,1)*3+MID(O76,12,1)*2,11)) -> 0 | Q76: =IF(MOD(MID(O76,1,1)*6+MID(O76,2,1)*5+MID(O76,3,1)*4+MID(O76,4,1)*3+MID(O76,5,1)*2+MID(O76,6,1)*9+MID(O76,7,1)*8+MID(O76,8,1)*7+MID(O76,9,1)*6+MID(O76,10,1)*5+MID(O76,11,1)*4+MID(O76,12,1)*3+P76*2,11)<2,0,11-MOD(MID(O76,1,1)*6+MID(O76,2,1)*5+MID(O76,3,1)*4+MID(O76,4,1)*3+MID(O76,5,1)*2+MID(O76,6,1)*9+MID(O76,7,1)*8+MID(O76,8,1)*7+MID(O76,9,1)*6+MID(O76,10,1)*5+MID(O76,11,1)*4+MID(O76,12,1)*3+P76*2,11)) -> 2 | R76: =MID(O76,1,2)&"."&MID(O76,3,3)&"."&MID(O76,6,3)&"/"&MID(O76,9,4)&"-"&TEXT(P76,"0")&TEXT(Q76,"0") -> 19.447.268/0001-02 | T76: =IF(S76="","",IF(S76="Cadastrou","",XLOOKUP(S76,$BA$2:$BA$6,$BB$2:$BB$6,""))) | U76: =IF(S76="","",IF(S76="Cadastrou","",XLOOKUP(S76,$BA$2:$BA$6,$BC$2:$BC$6,""))) | V76: =IF(S76="","",XLOOKUP(S76,$BA$2:$BA$6,$BD$2:$BD$6,"")) | AA76: =IF(Y76="","",IF(INT(TODAY()-Y76)<0,"⚠️ Data futura",INT(TODAY()-Y76))) | AB76: =IF(AA76="","",IF(Z76="",IF(AA76>14,"🔴 Atrasado",IF(AA76>7,"🟡 Atenção","🟢 Em dia")),IF(TODAY()>Z76,"🔴 Atrasado",IF(Z76-TODAY()<=3,"🟡 Atenção","🟢 Em dia")))) | AD76: =IF(OR(AC76="",H76=""),"",H76*AC76) | AF76: =IF(AC76>0,AC76,'⚙️ Config'!$B$10) -> 0.0075 | AG76: =H76*AF76 -> 68559.784 | AH76: =AG76*'⚙️ Config'!$B$11 -> 342798.92 | AI76: =AH76*'⚙️ Config'!$B$12 -> 102839.68
A77: 74 | B77: AQUITAINE SERVICOS DE MECANICA E FUNILARIA LTDA | C77: SP | D77: 02590237 | E77: 47.09 | F77: 🔴 ALTA | G77: R$ 5-10M | H77: 9087203.1 | I77: 2 | J77: 1.4 | K77: 2024 | L77: Receita da dívida ativa - IRPJ | Receita da dívida ativa - IRRF | M77: 2024 | N77: COBRANCA | O77: =TEXT(D77,"00000000")&"0001" -> 025902370001 | P77: =IF(MOD(MID(O77,1,1)*5+MID(O77,2,1)*4+MID(O77,3,1)*3+MID(O77,4,1)*2+MID(O77,5,1)*9+MID(O77,6,1)*8+MID(O77,7,1)*7+MID(O77,8,1)*6+MID(O77,9,1)*5+MID(O77,10,1)*4+MID(O77,11,1)*3+MID(O77,12,1)*2,11)<2,0,11-MOD(MID(O77,1,1)*5+MID(O77,2,1)*4+MID(O77,3,1)*3+MID(O77,4,1)*2+MID(O77,5,1)*9+MID(O77,6,1)*8+MID(O77,7,1)*7+MID(O77,8,1)*6+MID(O77,9,1)*5+MID(O77,10,1)*4+MID(O77,11,1)*3+MID(O77,12,1)*2,11)) -> 0 | Q77: =IF(MOD(MID(O77,1,1)*6+MID(O77,2,1)*5+MID(O77,3,1)*4+MID(O77,4,1)*3+MID(O77,5,1)*2+MID(O77,6,1)*9+MID(O77,7,1)*8+MID(O77,8,1)*7+MID(O77,9,1)*6+MID(O77,10,1)*5+MID(O77,11,1)*4+MID(O77,12,1)*3+P77*2,11)<2,0,11-MOD(MID(O77,1,1)*6+MID(O77,2,1)*5+MID(O77,3,1)*4+MID(O77,4,1)*3+MID(O77,5,1)*2+MID(O77,6,1)*9+MID(O77,7,1)*8+MID(O77,8,1)*7+MID(O77,9,1)*6+MID(O77,10,1)*5+MID(O77,11,1)*4+MID(O77,12,1)*3+P77*2,11)) -> 3 | R77: =MID(O77,1,2)&"."&MID(O77,3,3)&"."&MID(O77,6,3)&"/"&MID(O77,9,4)&"-"&TEXT(P77,"0")&TEXT(Q77,"0") -> 02.590.237/0001-03 | T77: =IF(S77="","",IF(S77="Cadastrou","",XLOOKUP(S77,$BA$2:$BA$6,$BB$2:$BB$6,""))) | U77: =IF(S77="","",IF(S77="Cadastrou","",XLOOKUP(S77,$BA$2:$BA$6,$BC$2:$BC$6,""))) | V77: =IF(S77="","",XLOOKUP(S77,$BA$2:$BA$6,$BD$2:$BD$6,"")) | AA77: =IF(Y77="","",IF(INT(TODAY()-Y77)<0,"⚠️ Data futura",INT(TODAY()-Y77))) | AB77: =IF(AA77="","",IF(Z77="",IF(AA77>14,"🔴 Atrasado",IF(AA77>7,"🟡 Atenção","🟢 Em dia")),IF(TODAY()>Z77,"🔴 Atrasado",IF(Z77-TODAY()<=3,"🟡 Atenção","🟢 Em dia")))) | AD77: =IF(OR(AC77="",H77=""),"",H77*AC77) | AF77: =IF(AC77>0,AC77,'⚙️ Config'!$B$10) -> 0.0075 | AG77: =H77*AF77 -> 68154.023 | AH77: =AG77*'⚙️ Config'!$B$11 -> 340770.12 | AI77: =AH77*'⚙️ Config'!$B$12 -> 102231.04
A78: 75 | B78: CONDOMINIO SHOPPING CENTER IGUATEMI | C78: SP | D78: 53991378 | E78: 83.88 | F78: 🔴 ALTA | G78: R$ 5-10M | H78: 9037714.5 | I78: 1 | J78: 0.6 | K78: 2025 | L78: Receita da dívida ativa - COFINS | M78: 2025 | N78: COBRANCA | O78: =TEXT(D78,"00000000")&"0001" -> 539913780001 | P78: =IF(MOD(MID(O78,1,1)*5+MID(O78,2,1)*4+MID(O78,3,1)*3+MID(O78,4,1)*2+MID(O78,5,1)*9+MID(O78,6,1)*8+MID(O78,7,1)*7+MID(O78,8,1)*6+MID(O78,9,1)*5+MID(O78,10,1)*4+MID(O78,11,1)*3+MID(O78,12,1)*2,11)<2,0,11-MOD(MID(O78,1,1)*5+MID(O78,2,1)*4+MID(O78,3,1)*3+MID(O78,4,1)*2+MID(O78,5,1)*9+MID(O78,6,1)*8+MID(O78,7,1)*7+MID(O78,8,1)*6+MID(O78,9,1)*5+MID(O78,10,1)*4+MID(O78,11,1)*3+MID(O78,12,1)*2,11)) -> 6 | Q78: =IF(MOD(MID(O78,1,1)*6+MID(O78,2,1)*5+MID(O78,3,1)*4+MID(O78,4,1)*3+MID(O78,5,1)*2+MID(O78,6,1)*9+MID(O78,7,1)*8+MID(O78,8,1)*7+MID(O78,9,1)*6+MID(O78,10,1)*5+MID(O78,11,1)*4+MID(O78,12,1)*3+P78*2,11)<2,0,11-MOD(MID(O78,1,1)*6+MID(O78,2,1)*5+MID(O78,3,1)*4+MID(O78,4,1)*3+MID(O78,5,1)*2+MID(O78,6,1)*9+MID(O78,7,1)*8+MID(O78,8,1)*7+MID(O78,9,1)*6+MID(O78,10,1)*5+MID(O78,11,1)*4+MID(O78,12,1)*3+P78*2,11)) -> 0 | R78: =MID(O78,1,2)&"."&MID(O78,3,3)&"."&MID(O78,6,3)&"/"&MID(O78,9,4)&"-"&TEXT(P78,"0")&TEXT(Q78,"0") -> 53.991.378/0001-60 | T78: =IF(S78="","",IF(S78="Cadastrou","",XLOOKUP(S78,$BA$2:$BA$6,$BB$2:$BB$6,""))) | U78: =IF(S78="","",IF(S78="Cadastrou","",XLOOKUP(S78,$BA$2:$BA$6,$BC$2:$BC$6,""))) | V78: =IF(S78="","",XLOOKUP(S78,$BA$2:$BA$6,$BD$2:$BD$6,"")) | AA78: =IF(Y78="","",IF(INT(TODAY()-Y78)<0,"⚠️ Data futura",INT(TODAY()-Y78))) | AB78: =IF(AA78="","",IF(Z78="",IF(AA78>14,"🔴 Atrasado",IF(AA78>7,"🟡 Atenção","🟢 Em dia")),IF(TODAY()>Z78,"🔴 Atrasado",IF(Z78-TODAY()<=3,"🟡 Atenção","🟢 Em dia")))) | AD78: =IF(OR(AC78="",H78=""),"",H78*AC78) | AF78: =IF(AC78>0,AC78,'⚙️ Config'!$B$10) -> 0.0075 | AG78: =H78*AF78 -> 67782.859 | AH78: =AG78*'⚙️ Config'!$B$11 -> 338914.3 | AI78: =AH78*'⚙️ Config'!$B$12 -> 101674.29
A79: 76 | B79: HARA EMPREENDIMENTOS LTDA | C79: SP | D79: 44717171 | E79: 40.68 | F79: 🔴 ALTA | G79: R$ 5-10M | H79: 9027047.8 | I79: 2 | J79: 1.8 | K79: 2024 | L79: Receita da dívida ativa - PIS | Receita da dívida ativa - COFINS | M79: 2024 | N79: COBRANCA | O79: =TEXT(D79,"00000000")&"0001" -> 447171710001 | P79: =IF(MOD(MID(O79,1,1)*5+MID(O79,2,1)*4+MID(O79,3,1)*3+MID(O79,4,1)*2+MID(O79,5,1)*9+MID(O79,6,1)*8+MID(O79,7,1)*7+MID(O79,8,1)*6+MID(O79,9,1)*5+MID(O79,10,1)*4+MID(O79,11,1)*3+MID(O79,12,1)*2,11)<2,0,11-MOD(MID(O79,1,1)*5+MID(O79,2,1)*4+MID(O79,3,1)*3+MID(O79,4,1)*2+MID(O79,5,1)*9+MID(O79,6,1)*8+MID(O79,7,1)*7+MID(O79,8,1)*6+MID(O79,9,1)*5+MID(O79,10,1)*4+MID(O79,11,1)*3+MID(O79,12,1)*2,11)) -> 0 | Q79: =IF(MOD(MID(O79,1,1)*6+MID(O79,2,1)*5+MID(O79,3,1)*4+MID(O79,4,1)*3+MID(O79,5,1)*2+MID(O79,6,1)*9+MID(O79,7,1)*8+MID(O79,8,1)*7+MID(O79,9,1)*6+MID(O79,10,1)*5+MID(O79,11,1)*4+MID(O79,12,1)*3+P79*2,11)<2,0,11-MOD(MID(O79,1,1)*6+MID(O79,2,1)*5+MID(O79,3,1)*4+MID(O79,4,1)*3+MID(O79,5,1)*2+MID(O79,6,1)*9+MID(O79,7,1)*8+MID(O79,8,1)*7+MID(O79,9,1)*6+MID(O79,10,1)*5+MID(O79,11,1)*4+MID(O79,12,1)*3+P79*2,11)) -> 1 | R79: =MID(O79,1,2)&"."&MID(O79,3,3)&"."&MID(O79,6,3)&"/"&MID(O79,9,4)&"-"&TEXT(P79,"0")&TEXT(Q79,"0") -> 44.717.171/0001-01 | T79: =IF(S79="","",IF(S79="Cadastrou","",XLOOKUP(S79,$BA$2:$BA$6,$BB$2:$BB$6,""))) | U79: =IF(S79="","",IF(S79="Cadastrou","",XLOOKUP(S79,$BA$2:$BA$6,$BC$2:$BC$6,""))) | V79: =IF(S79="","",XLOOKUP(S79,$BA$2:$BA$6,$BD$2:$BD$6,"")) | AA79: =IF(Y79="","",IF(INT(TODAY()-Y79)<0,"⚠️ Data futura",INT(TODAY()-Y79))) | AB79: =IF(AA79="","",IF(Z79="",IF(AA79>14,"🔴 Atrasado",IF(AA79>7,"🟡 Atenção","🟢 Em dia")),IF(TODAY()>Z79,"🔴 Atrasado",IF(Z79-TODAY()<=3,"🟡 Atenção","🟢 Em dia")))) | AD79: =IF(OR(AC79="",H79=""),"",H79*AC79) | AF79: =IF(AC79>0,AC79,'⚙️ Config'!$B$10) -> 0.0075 | AG79: =H79*AF79 -> 67702.858 | AH79: =AG79*'⚙️ Config'!$B$11 -> 338514.29 | AI79: =AH79*'⚙️ Config'!$B$12 -> 101554.29
A80: 77 | B80: CEBI BRASIL LTDA | C80: SP | D80: 03171093 | E80: 64.08 | F80: 🔴 ALTA | G80: R$ 5-10M | H80: 8843689.7 | I80: 2 | J80: 0.8 | K80: 2025 | L80: R D Ativa - Contribuição Empresa/Empregador | R D Ativa - Contribuição Risco Ambiental/Aposent Especial | M80: 2025 | N80: AJUIZADA_SEM_GAR | O80: =TEXT(D80,"00000000")&"0001" -> 031710930001 | P80: =IF(MOD(MID(O80,1,1)*5+MID(O80,2,1)*4+MID(O80,3,1)*3+MID(O80,4,1)*2+MID(O80,5,1)*9+MID(O80,6,1)*8+MID(O80,7,1)*7+MID(O80,8,1)*6+MID(O80,9,1)*5+MID(O80,10,1)*4+MID(O80,11,1)*3+MID(O80,12,1)*2,11)<2,0,11-MOD(MID(O80,1,1)*5+MID(O80,2,1)*4+MID(O80,3,1)*3+MID(O80,4,1)*2+MID(O80,5,1)*9+MID(O80,6,1)*8+MID(O80,7,1)*7+MID(O80,8,1)*6+MID(O80,9,1)*5+MID(O80,10,1)*4+MID(O80,11,1)*3+MID(O80,12,1)*2,11)) -> 0 | Q80: =IF(MOD(MID(O80,1,1)*6+MID(O80,2,1)*5+MID(O80,3,1)*4+MID(O80,4,1)*3+MID(O80,5,1)*2+MID(O80,6,1)*9+MID(O80,7,1)*8+MID(O80,8,1)*7+MID(O80,9,1)*6+MID(O80,10,1)*5+MID(O80,11,1)*4+MID(O80,12,1)*3+P80*2,11)<2,0,11-MOD(MID(O80,1,1)*6+MID(O80,2,1)*5+MID(O80,3,1)*4+MID(O80,4,1)*3+MID(O80,5,1)*2+MID(O80,6,1)*9+MID(O80,7,1)*8+MID(O80,8,1)*7+MID(O80,9,1)*6+MID(O80,10,1)*5+MID(O80,11,1)*4+MID(O80,12,1)*3+P80*2,11)) -> 5 | R80: =MID(O80,1,2)&"."&MID(O80,3,3)&"."&MID(O80,6,3)&"/"&MID(O80,9,4)&"-"&TEXT(P80,"0")&TEXT(Q80,"0") -> 03.171.093/0001-05 | T80: =IF(S80="","",IF(S80="Cadastrou","",XLOOKUP(S80,$BA$2:$BA$6,$BB$2:$BB$6,""))) | U80: =IF(S80="","",IF(S80="Cadastrou","",XLOOKUP(S80,$BA$2:$BA$6,$BC$2:$BC$6,""))) | V80: =IF(S80="","",XLOOKUP(S80,$BA$2:$BA$6,$BD$2:$BD$6,"")) | AA80: =IF(Y80="","",IF(INT(TODAY()-Y80)<0,"⚠️ Data futura",INT(TODAY()-Y80))) | AB80: =IF(AA80="","",IF(Z80="",IF(AA80>14,"🔴 Atrasado",IF(AA80>7,"🟡 Atenção","🟢 Em dia")),IF(TODAY()>Z80,"🔴 Atrasado",IF(Z80-TODAY()<=3,"🟡 Atenção","🟢 Em dia")))) | AD80: =IF(OR(AC80="",H80=""),"",H80*AC80) | AF80: =IF(AC80>0,AC80,'⚙️ Config'!$B$10) -> 0.0075 | AG80: =H80*AF80 -> 66327.673 | AH80: =AG80*'⚙️ Config'!$B$11 -> 331638.36 | AI80: =AH80*'⚙️ Config'!$B$12 -> 99491.509 | AJ80: 16500000 | AM80: (19) 3834-3543 | AO80: LUCIANO DA MOTA PRESTES | AP80: Administrador
A81: 78 | B81: W M LOGISTICA E COMERCIO DE CEREAIS LTDA | C81: SP | D81: 12185343 | E81: 49.4 | F81: 🔴 ALTA | G81: R$ 5-10M | H81: 8730270.7 | I81: 1 | J81: 1.9 | K81: 2024 | L81: R D Ativa - Contribuição Previdenciária Sobre Receita Bruta | M81: 2024 | N81: AJUIZADA_SEM_GAR | O81: =TEXT(D81,"00000000")&"0001" -> 121853430001 | P81: =IF(MOD(MID(O81,1,1)*5+MID(O81,2,1)*4+MID(O81,3,1)*3+MID(O81,4,1)*2+MID(O81,5,1)*9+MID(O81,6,1)*8+MID(O81,7,1)*7+MID(O81,8,1)*6+MID(O81,9,1)*5+MID(O81,10,1)*4+MID(O81,11,1)*3+MID(O81,12,1)*2,11)<2,0,11-MOD(MID(O81,1,1)*5+MID(O81,2,1)*4+MID(O81,3,1)*3+MID(O81,4,1)*2+MID(O81,5,1)*9+MID(O81,6,1)*8+MID(O81,7,1)*7+MID(O81,8,1)*6+MID(O81,9,1)*5+MID(O81,10,1)*4+MID(O81,11,1)*3+MID(O81,12,1)*2,11)) -> 5 | Q81: =IF(MOD(MID(O81,1,1)*6+MID(O81,2,1)*5+MID(O81,3,1)*4+MID(O81,4,1)*3+MID(O81,5,1)*2+MID(O81,6,1)*9+MID(O81,7,1)*8+MID(O81,8,1)*7+MID(O81,9,1)*6+MID(O81,10,1)*5+MID(O81,11,1)*4+MID(O81,12,1)*3+P81*2,11)<2,0,11-MOD(MID(O81,1,1)*6+MID(O81,2,1)*5+MID(O81,3,1)*4+MID(O81,4,1)*3+MID(O81,5,1)*2+MID(O81,6,1)*9+MID(O81,7,1)*8+MID(O81,8,1)*7+MID(O81,9,1)*6+MID(O81,10,1)*5+MID(O81,11,1)*4+MID(O81,12,1)*3+P81*2,11)) -> 7 | R81: =MID(O81,1,2)&"."&MID(O81,3,3)&"."&MID(O81,6,3)&"/"&MID(O81,9,4)&"-"&TEXT(P81,"0")&TEXT(Q81,"0") -> 12.185.343/0001-57 | T81: =IF(S81="","",IF(S81="Cadastrou","",XLOOKUP(S81,$BA$2:$BA$6,$BB$2:$BB$6,""))) | U81: =IF(S81="","",IF(S81="Cadastrou","",XLOOKUP(S81,$BA$2:$BA$6,$BC$2:$BC$6,""))) | V81: =IF(S81="","",XLOOKUP(S81,$BA$2:$BA$6,$BD$2:$BD$6,"")) | AA81: =IF(Y81="","",IF(INT(TODAY()-Y81)<0,"⚠️ Data futura",INT(TODAY()-Y81))) | AB81: =IF(AA81="","",IF(Z81="",IF(AA81>14,"🔴 Atrasado",IF(AA81>7,"🟡 Atenção","🟢 Em dia")),IF(TODAY()>Z81,"🔴 Atrasado",IF(Z81-TODAY()<=3,"🟡 Atenção","🟢 Em dia")))) | AD81: =IF(OR(AC81="",H81=""),"",H81*AC81) | AF81: =IF(AC81>0,AC81,'⚙️ Config'!$B$10) -> 0.0075 | AG81: =H81*AF81 -> 65477.03 | AH81: =AG81*'⚙️ Config'!$B$11 -> 327385.15 | AI81: =AH81*'⚙️ Config'!$B$12 -> 98215.546
A82: 79 | B82: AVIBRAS DIVISAO AEREA E NAVAL SA | C82: SP | D82: 00435091 | E82: 80.23 | F82: 🔴 ALTA | G82: R$ 5-10M | H82: 8677186.1 | I82: 2 | J82: 0.5 | K82: 2025 | L82: Receita da dívida ativa - Outras multas | M82: 2025 | N82: COBRANCA | O82: =TEXT(D82,"00000000")&"0001" -> 004350910001 | P82: =IF(MOD(MID(O82,1,1)*5+MID(O82,2,1)*4+MID(O82,3,1)*3+MID(O82,4,1)*2+MID(O82,5,1)*9+MID(O82,6,1)*8+MID(O82,7,1)*7+MID(O82,8,1)*6+MID(O82,9,1)*5+MID(O82,10,1)*4+MID(O82,11,1)*3+MID(O82,12,1)*2,11)<2,0,11-MOD(MID(O82,1,1)*5+MID(O82,2,1)*4+MID(O82,3,1)*3+MID(O82,4,1)*2+MID(O82,5,1)*9+MID(O82,6,1)*8+MID(O82,7,1)*7+MID(O82,8,1)*6+MID(O82,9,1)*5+MID(O82,10,1)*4+MID(O82,11,1)*3+MID(O82,12,1)*2,11)) -> 9 | Q82: =IF(MOD(MID(O82,1,1)*6+MID(O82,2,1)*5+MID(O82,3,1)*4+MID(O82,4,1)*3+MID(O82,5,1)*2+MID(O82,6,1)*9+MID(O82,7,1)*8+MID(O82,8,1)*7+MID(O82,9,1)*6+MID(O82,10,1)*5+MID(O82,11,1)*4+MID(O82,12,1)*3+P82*2,11)<2,0,11-MOD(MID(O82,1,1)*6+MID(O82,2,1)*5+MID(O82,3,1)*4+MID(O82,4,1)*3+MID(O82,5,1)*2+MID(O82,6,1)*9+MID(O82,7,1)*8+MID(O82,8,1)*7+MID(O82,9,1)*6+MID(O82,10,1)*5+MID(O82,11,1)*4+MID(O82,12,1)*3+P82*2,11)) -> 8 | R82: =MID(O82,1,2)&"."&MID(O82,3,3)&"."&MID(O82,6,3)&"/"&MID(O82,9,4)&"-"&TEXT(P82,"0")&TEXT(Q82,"0") -> 00.435.091/0001-98 | T82: =IF(S82="","",IF(S82="Cadastrou","",XLOOKUP(S82,$BA$2:$BA$6,$BB$2:$BB$6,""))) | U82: =IF(S82="","",IF(S82="Cadastrou","",XLOOKUP(S82,$BA$2:$BA$6,$BC$2:$BC$6,""))) | V82: =IF(S82="","",XLOOKUP(S82,$BA$2:$BA$6,$BD$2:$BD$6,"")) | AA82: =IF(Y82="","",IF(INT(TODAY()-Y82)<0,"⚠️ Data futura",INT(TODAY()-Y82))) | AB82: =IF(AA82="","",IF(Z82="",IF(AA82>14,"🔴 Atrasado",IF(AA82>7,"🟡 Atenção","🟢 Em dia")),IF(TODAY()>Z82,"🔴 Atrasado",IF(Z82-TODAY()<=3,"🟡 Atenção","🟢 Em dia")))) | AD82: =IF(OR(AC82="",H82=""),"",H82*AC82) | AF82: =IF(AC82>0,AC82,'⚙️ Config'!$B$10) -> 0.0075 | AG82: =H82*AF82 -> 65078.896 | AH82: =AG82*'⚙️ Config'!$B$11 -> 325394.48 | AI82: =AH82*'⚙️ Config'!$B$12 -> 97618.343 | AJ82: 13000000 | AM82: (12) 3955-6426 | AO82: FABIO GUIMARAES LEITE | AP82: Presidente
A83: 80 | B83: SUPERPACK INDUSTRIA DE PRODUTOS PLASTICOS LTDA | C83: SP | D83: 05994759 | E83: 50.66 | F83: 🔴 ALTA | G83: R$ 5-10M | H83: 8523764.2 | I83: 1 | J83: 1.8 | K83: 2024 | L83: IPI - Receita da dívida ativa | M83: 2024 | N83: COBRANCA | O83: =TEXT(D83,"00000000")&"0001" -> 059947590001 | P83: =IF(MOD(MID(O83,1,1)*5+MID(O83,2,1)*4+MID(O83,3,1)*3+MID(O83,4,1)*2+MID(O83,5,1)*9+MID(O83,6,1)*8+MID(O83,7,1)*7+MID(O83,8,1)*6+MID(O83,9,1)*5+MID(O83,10,1)*4+MID(O83,11,1)*3+MID(O83,12,1)*2,11)<2,0,11-MOD(MID(O83,1,1)*5+MID(O83,2,1)*4+MID(O83,3,1)*3+MID(O83,4,1)*2+MID(O83,5,1)*9+MID(O83,6,1)*8+MID(O83,7,1)*7+MID(O83,8,1)*6+MID(O83,9,1)*5+MID(O83,10,1)*4+MID(O83,11,1)*3+MID(O83,12,1)*2,11)) -> 5 | Q83: =IF(MOD(MID(O83,1,1)*6+MID(O83,2,1)*5+MID(O83,3,1)*4+MID(O83,4,1)*3+MID(O83,5,1)*2+MID(O83,6,1)*9+MID(O83,7,1)*8+MID(O83,8,1)*7+MID(O83,9,1)*6+MID(O83,10,1)*5+MID(O83,11,1)*4+MID(O83,12,1)*3+P83*2,11)<2,0,11-MOD(MID(O83,1,1)*6+MID(O83,2,1)*5+MID(O83,3,1)*4+MID(O83,4,1)*3+MID(O83,5,1)*2+MID(O83,6,1)*9+MID(O83,7,1)*8+MID(O83,8,1)*7+MID(O83,9,1)*6+MID(O83,10,1)*5+MID(O83,11,1)*4+MID(O83,12,1)*3+P83*2,11)) -> 0 | R83: =MID(O83,1,2)&"."&MID(O83,3,3)&"."&MID(O83,6,3)&"/"&MID(O83,9,4)&"-"&TEXT(P83,"0")&TEXT(Q83,"0") -> 05.994.759/0001-50 | T83: =IF(S83="","",IF(S83="Cadastrou","",XLOOKUP(S83,$BA$2:$BA$6,$BB$2:$BB$6,""))) | U83: =IF(S83="","",IF(S83="Cadastrou","",XLOOKUP(S83,$BA$2:$BA$6,$BC$2:$BC$6,""))) | V83: =IF(S83="","",XLOOKUP(S83,$BA$2:$BA$6,$BD$2:$BD$6,"")) | AA83: =IF(Y83="","",IF(INT(TODAY()-Y83)<0,"⚠️ Data futura",INT(TODAY()-Y83))) | AB83: =IF(AA83="","",IF(Z83="",IF(AA83>14,"🔴 Atrasado",IF(AA83>7,"🟡 Atenção","🟢 Em dia")),IF(TODAY()>Z83,"🔴 Atrasado",IF(Z83-TODAY()<=3,"🟡 Atenção","🟢 Em dia")))) | AD83: =IF(OR(AC83="",H83=""),"",H83*AC83) | AF83: =IF(AC83>0,AC83,'⚙️ Config'!$B$10) -> 0.0075 | AG83: =H83*AF83 -> 63928.232 | AH83: =AG83*'⚙️ Config'!$B$11 -> 319641.16 | AI83: =AH83*'⚙️ Config'!$B$12 -> 95892.347
A84: 81 | B84: GUARU COMERCIO DE EMBALAGENS EM GERAL LTDA | C84: SP | D84: 03852789 | E84: 49.39 | F84: 🔴 ALTA | G84: R$ 5-10M | H84: 8384883.4 | I84: 1 | J84: 1.9 | K84: 2024 | L84: IPI - Receita da dívida ativa | M84: 2024 | N84: AJUIZADA_SEM_GAR | O84: =TEXT(D84,"00000000")&"0001" -> 038527890001 | P84: =IF(MOD(MID(O84,1,1)*5+MID(O84,2,1)*4+MID(O84,3,1)*3+MID(O84,4,1)*2+MID(O84,5,1)*9+MID(O84,6,1)*8+MID(O84,7,1)*7+MID(O84,8,1)*6+MID(O84,9,1)*5+MID(O84,10,1)*4+MID(O84,11,1)*3+MID(O84,12,1)*2,11)<2,0,11-MOD(MID(O84,1,1)*5+MID(O84,2,1)*4+MID(O84,3,1)*3+MID(O84,4,1)*2+MID(O84,5,1)*9+MID(O84,6,1)*8+MID(O84,7,1)*7+MID(O84,8,1)*6+MID(O84,9,1)*5+MID(O84,10,1)*4+MID(O84,11,1)*3+MID(O84,12,1)*2,11)) -> 0 | Q84: =IF(MOD(MID(O84,1,1)*6+MID(O84,2,1)*5+MID(O84,3,1)*4+MID(O84,4,1)*3+MID(O84,5,1)*2+MID(O84,6,1)*9+MID(O84,7,1)*8+MID(O84,8,1)*7+MID(O84,9,1)*6+MID(O84,10,1)*5+MID(O84,11,1)*4+MID(O84,12,1)*3+P84*2,11)<2,0,11-MOD(MID(O84,1,1)*6+MID(O84,2,1)*5+MID(O84,3,1)*4+MID(O84,4,1)*3+MID(O84,5,1)*2+MID(O84,6,1)*9+MID(O84,7,1)*8+MID(O84,8,1)*7+MID(O84,9,1)*6+MID(O84,10,1)*5+MID(O84,11,1)*4+MID(O84,12,1)*3+P84*2,11)) -> 5 | R84: =MID(O84,1,2)&"."&MID(O84,3,3)&"."&MID(O84,6,3)&"/"&MID(O84,9,4)&"-"&TEXT(P84,"0")&TEXT(Q84,"0") -> 03.852.789/0001-05 | T84: =IF(S84="","",IF(S84="Cadastrou","",XLOOKUP(S84,$BA$2:$BA$6,$BB$2:$BB$6,""))) | U84: =IF(S84="","",IF(S84="Cadastrou","",XLOOKUP(S84,$BA$2:$BA$6,$BC$2:$BC$6,""))) | V84: =IF(S84="","",XLOOKUP(S84,$BA$2:$BA$6,$BD$2:$BD$6,"")) | AA84: =IF(Y84="","",IF(INT(TODAY()-Y84)<0,"⚠️ Data futura",INT(TODAY()-Y84))) | AB84: =IF(AA84="","",IF(Z84="",IF(AA84>14,"🔴 Atrasado",IF(AA84>7,"🟡 Atenção","🟢 Em dia")),IF(TODAY()>Z84,"🔴 Atrasado",IF(Z84-TODAY()<=3,"🟡 Atenção","🟢 Em dia")))) | AD84: =IF(OR(AC84="",H84=""),"",H84*AC84) | AF84: =IF(AC84>0,AC84,'⚙️ Config'!$B$10) -> 0.0075 | AG84: =H84*AF84 -> 62886.626 | AH84: =AG84*'⚙️ Config'!$B$11 -> 314433.13 | AI84: =AH84*'⚙️ Config'!$B$12 -> 94329.938
A85: 82 | B85: VITAE SERVICOS EMPRESARIAIS LTDA | C85: SP | D85: 02105644 | E85: 40.66 | F85: 🔴 ALTA | G85: R$ 5-10M | H85: 8377377 | I85: 2 | J85: 1.8 | K85: 2024 | L85: Receita da dívida ativa - CSLL | Receita da dívida ativa - IRPJ | M85: 2024 | N85: COBRANCA | O85: =TEXT(D85,"00000000")&"0001" -> 021056440001 | P85: =IF(MOD(MID(O85,1,1)*5+MID(O85,2,1)*4+MID(O85,3,1)*3+MID(O85,4,1)*2+MID(O85,5,1)*9+MID(O85,6,1)*8+MID(O85,7,1)*7+MID(O85,8,1)*6+MID(O85,9,1)*5+MID(O85,10,1)*4+MID(O85,11,1)*3+MID(O85,12,1)*2,11)<2,0,11-MOD(MID(O85,1,1)*5+MID(O85,2,1)*4+MID(O85,3,1)*3+MID(O85,4,1)*2+MID(O85,5,1)*9+MID(O85,6,1)*8+MID(O85,7,1)*7+MID(O85,8,1)*6+MID(O85,9,1)*5+MID(O85,10,1)*4+MID(O85,11,1)*3+MID(O85,12,1)*2,11)) -> 7 | Q85: =IF(MOD(MID(O85,1,1)*6+MID(O85,2,1)*5+MID(O85,3,1)*4+MID(O85,4,1)*3+MID(O85,5,1)*2+MID(O85,6,1)*9+MID(O85,7,1)*8+MID(O85,8,1)*7+MID(O85,9,1)*6+MID(O85,10,1)*5+MID(O85,11,1)*4+MID(O85,12,1)*3+P85*2,11)<2,0,11-MOD(MID(O85,1,1)*6+MID(O85,2,1)*5+MID(O85,3,1)*4+MID(O85,4,1)*3+MID(O85,5,1)*2+MID(O85,6,1)*9+MID(O85,7,1)*8+MID(O85,8,1)*7+MID(O85,9,1)*6+MID(O85,10,1)*5+MID(O85,11,1)*4+MID(O85,12,1)*3+P85*2,11)) -> 0 | R85: =MID(O85,1,2)&"."&MID(O85,3,3)&"."&MID(O85,6,3)&"/"&MID(O85,9,4)&"-"&TEXT(P85,"0")&TEXT(Q85,"0") -> 02.105.644/0001-70 | T85: =IF(S85="","",IF(S85="Cadastrou","",XLOOKUP(S85,$BA$2:$BA$6,$BB$2:$BB$6,""))) | U85: =IF(S85="","",IF(S85="Cadastrou","",XLOOKUP(S85,$BA$2:$BA$6,$BC$2:$BC$6,""))) | V85: =IF(S85="","",XLOOKUP(S85,$BA$2:$BA$6,$BD$2:$BD$6,"")) | AA85: =IF(Y85="","",IF(INT(TODAY()-Y85)<0,"⚠️ Data futura",INT(TODAY()-Y85))) | AB85: =IF(AA85="","",IF(Z85="",IF(AA85>14,"🔴 Atrasado",IF(AA85>7,"🟡 Atenção","🟢 Em dia")),IF(TODAY()>Z85,"🔴 Atrasado",IF(Z85-TODAY()<=3,"🟡 Atenção","🟢 Em dia")))) | AD85: =IF(OR(AC85="",H85=""),"",H85*AC85) | AF85: =IF(AC85>0,AC85,'⚙️ Config'!$B$10) -> 0.0075 | AG85: =H85*AF85 -> 62830.328 | AH85: =AG85*'⚙️ Config'!$B$11 -> 314151.64 | AI85: =AH85*'⚙️ Config'!$B$12 -> 94245.492
A86: 83 | B86: ANAN SERVICOS MEDICOS E EM SAUDE LTDA | C86: SP | D86: 57746208 | E86: 49.11 | F86: 🔴 ALTA | G86: R$ 5-10M | H86: 8215044.5 | I86: 2 | J86: 1.3 | K86: 2024 | L86: Receita da dívida ativa - CSLL | Receita da dívida ativa - IRPJ | M86: 2024 | N86: AJUIZADA_SEM_GAR | O86: =TEXT(D86,"00000000")&"0001" -> 577462080001 | P86: =IF(MOD(MID(O86,1,1)*5+MID(O86,2,1)*4+MID(O86,3,1)*3+MID(O86,4,1)*2+MID(O86,5,1)*9+MID(O86,6,1)*8+MID(O86,7,1)*7+MID(O86,8,1)*6+MID(O86,9,1)*5+MID(O86,10,1)*4+MID(O86,11,1)*3+MID(O86,12,1)*2,11)<2,0,11-MOD(MID(O86,1,1)*5+MID(O86,2,1)*4+MID(O86,3,1)*3+MID(O86,4,1)*2+MID(O86,5,1)*9+MID(O86,6,1)*8+MID(O86,7,1)*7+MID(O86,8,1)*6+MID(O86,9,1)*5+MID(O86,10,1)*4+MID(O86,11,1)*3+MID(O86,12,1)*2,11)) -> 7 | Q86: =IF(MOD(MID(O86,1,1)*6+MID(O86,2,1)*5+MID(O86,3,1)*4+MID(O86,4,1)*3+MID(O86,5,1)*2+MID(O86,6,1)*9+MID(O86,7,1)*8+MID(O86,8,1)*7+MID(O86,9,1)*6+MID(O86,10,1)*5+MID(O86,11,1)*4+MID(O86,12,1)*3+P86*2,11)<2,0,11-MOD(MID(O86,1,1)*6+MID(O86,2,1)*5+MID(O86,3,1)*4+MID(O86,4,1)*3+MID(O86,5,1)*2+MID(O86,6,1)*9+MID(O86,7,1)*8+MID(O86,8,1)*7+MID(O86,9,1)*6+MID(O86,10,1)*5+MID(O86,11,1)*4+MID(O86,12,1)*3+P86*2,11)) -> 1 | R86: =MID(O86,1,2)&"."&MID(O86,3,3)&"."&MID(O86,6,3)&"/"&MID(O86,9,4)&"-"&TEXT(P86,"0")&TEXT(Q86,"0") -> 57.746.208/0001-71 | T86: =IF(S86="","",IF(S86="Cadastrou","",XLOOKUP(S86,$BA$2:$BA$6,$BB$2:$BB$6,""))) | U86: =IF(S86="","",IF(S86="Cadastrou","",XLOOKUP(S86,$BA$2:$BA$6,$BC$2:$BC$6,""))) | V86: =IF(S86="","",XLOOKUP(S86,$BA$2:$BA$6,$BD$2:$BD$6,"")) | AA86: =IF(Y86="","",IF(INT(TODAY()-Y86)<0,"⚠️ Data futura",INT(TODAY()-Y86))) | AB86: =IF(AA86="","",IF(Z86="",IF(AA86>14,"🔴 Atrasado",IF(AA86>7,"🟡 Atenção","🟢 Em dia")),IF(TODAY()>Z86,"🔴 Atrasado",IF(Z86-TODAY()<=3,"🟡 Atenção","🟢 Em dia")))) | AD86: =IF(OR(AC86="",H86=""),"",H86*AC86) | AF86: =IF(AC86>0,AC86,'⚙️ Config'!$B$10) -> 0.0075 | AG86: =H86*AF86 -> 61612.834 | AH86: =AG86*'⚙️ Config'!$B$11 -> 308064.17 | AI86: =AH86*'⚙️ Config'!$B$12 -> 92419.251
A87: 84 | B87: NOVACKI INDUSTRIAL S.A. | C87: SP | D87: 13284642 | E87: 71.27 | F87: 🔴 ALTA | G87: R$ 5-10M | H87: 8071040.2 | I87: 1 | J87: 1.4 | K87: 2025 | L87: Receita da dívida ativa - PIS | IPI - Receita da dívida ativa | Receita da dívida ativa - COFINS | M87: 2024 | N87: AJUIZADA_SEM_GAR|OUTROS | O87: =TEXT(D87,"00000000")&"0001" -> 132846420001 | P87: =IF(MOD(MID(O87,1,1)*5+MID(O87,2,1)*4+MID(O87,3,1)*3+MID(O87,4,1)*2+MID(O87,5,1)*9+MID(O87,6,1)*8+MID(O87,7,1)*7+MID(O87,8,1)*6+MID(O87,9,1)*5+MID(O87,10,1)*4+MID(O87,11,1)*3+MID(O87,12,1)*2,11)<2,0,11-MOD(MID(O87,1,1)*5+MID(O87,2,1)*4+MID(O87,3,1)*3+MID(O87,4,1)*2+MID(O87,5,1)*9+MID(O87,6,1)*8+MID(O87,7,1)*7+MID(O87,8,1)*6+MID(O87,9,1)*5+MID(O87,10,1)*4+MID(O87,11,1)*3+MID(O87,12,1)*2,11)) -> 0 | Q87: =IF(MOD(MID(O87,1,1)*6+MID(O87,2,1)*5+MID(O87,3,1)*4+MID(O87,4,1)*3+MID(O87,5,1)*2+MID(O87,6,1)*9+MID(O87,7,1)*8+MID(O87,8,1)*7+MID(O87,9,1)*6+MID(O87,10,1)*5+MID(O87,11,1)*4+MID(O87,12,1)*3+P87*2,11)<2,0,11-MOD(MID(O87,1,1)*6+MID(O87,2,1)*5+MID(O87,3,1)*4+MID(O87,4,1)*3+MID(O87,5,1)*2+MID(O87,6,1)*9+MID(O87,7,1)*8+MID(O87,8,1)*7+MID(O87,9,1)*6+MID(O87,10,1)*5+MID(O87,11,1)*4+MID(O87,12,1)*3+P87*2,11)) -> 1 | R87: =MID(O87,1,2)&"."&MID(O87,3,3)&"."&MID(O87,6,3)&"/"&MID(O87,9,4)&"-"&TEXT(P87,"0")&TEXT(Q87,"0") -> 13.284.642/0001-01 | T87: =IF(S87="","",IF(S87="Cadastrou","",XLOOKUP(S87,$BA$2:$BA$6,$BB$2:$BB$6,""))) | U87: =IF(S87="","",IF(S87="Cadastrou","",XLOOKUP(S87,$BA$2:$BA$6,$BC$2:$BC$6,""))) | V87: =IF(S87="","",XLOOKUP(S87,$BA$2:$BA$6,$BD$2:$BD$6,"")) | AA87: =IF(Y87="","",IF(INT(TODAY()-Y87)<0,"⚠️ Data futura",INT(TODAY()-Y87))) | AB87: =IF(AA87="","",IF(Z87="",IF(AA87>14,"🔴 Atrasado",IF(AA87>7,"🟡 Atenção","🟢 Em dia")),IF(TODAY()>Z87,"🔴 Atrasado",IF(Z87-TODAY()<=3,"🟡 Atenção","🟢 Em dia")))) | AD87: =IF(OR(AC87="",H87=""),"",H87*AC87) | AF87: =IF(AC87>0,AC87,'⚙️ Config'!$B$10) -> 0.0075 | AG87: =H87*AF87 -> 60532.802 | AH87: =AG87*'⚙️ Config'!$B$11 -> 302664.01 | AI87: =AH87*'⚙️ Config'!$B$12 -> 90799.203 | AJ87: 16650567 | AM87: (42) 3903-3454 | AO87: MARCIA HELENA KOCHAKI | AP87: Administrador
A88: 85 | B88: ABC INCORPORACAO E EMPREENDIMENTOS IMOBILIARIOS LTDA | C88: SP | D88: 26080230 | E88: 64.06 | F88: 🔴 ALTA | G88: R$ 5-10M | H88: 8045697.6 | I88: 2 | J88: 0.8 | K88: 2025 | L88: Receita da dívida ativa - CSLL | Receita da dívida ativa - IRPJ | M88: 2025 | N88: COBRANCA | O88: =TEXT(D88,"00000000")&"0001" -> 260802300001 | P88: =IF(MOD(MID(O88,1,1)*5+MID(O88,2,1)*4+MID(O88,3,1)*3+MID(O88,4,1)*2+MID(O88,5,1)*9+MID(O88,6,1)*8+MID(O88,7,1)*7+MID(O88,8,1)*6+MID(O88,9,1)*5+MID(O88,10,1)*4+MID(O88,11,1)*3+MID(O88,12,1)*2,11)<2,0,11-MOD(MID(O88,1,1)*5+MID(O88,2,1)*4+MID(O88,3,1)*3+MID(O88,4,1)*2+MID(O88,5,1)*9+MID(O88,6,1)*8+MID(O88,7,1)*7+MID(O88,8,1)*6+MID(O88,9,1)*5+MID(O88,10,1)*4+MID(O88,11,1)*3+MID(O88,12,1)*2,11)) -> 0 | Q88: =IF(MOD(MID(O88,1,1)*6+MID(O88,2,1)*5+MID(O88,3,1)*4+MID(O88,4,1)*3+MID(O88,5,1)*2+MID(O88,6,1)*9+MID(O88,7,1)*8+MID(O88,8,1)*7+MID(O88,9,1)*6+MID(O88,10,1)*5+MID(O88,11,1)*4+MID(O88,12,1)*3+P88*2,11)<2,0,11-MOD(MID(O88,1,1)*6+MID(O88,2,1)*5+MID(O88,3,1)*4+MID(O88,4,1)*3+MID(O88,5,1)*2+MID(O88,6,1)*9+MID(O88,7,1)*8+MID(O88,8,1)*7+MID(O88,9,1)*6+MID(O88,10,1)*5+MID(O88,11,1)*4+MID(O88,12,1)*3+P88*2,11)) -> 0 | R88: =MID(O88,1,2)&"."&MID(O88,3,3)&"."&MID(O88,6,3)&"/"&MID(O88,9,4)&"-"&TEXT(P88,"0")&TEXT(Q88,"0") -> 26.080.230/0001-00 | T88: =IF(S88="","",IF(S88="Cadastrou","",XLOOKUP(S88,$BA$2:$BA$6,$BB$2:$BB$6,""))) | U88: =IF(S88="","",IF(S88="Cadastrou","",XLOOKUP(S88,$BA$2:$BA$6,$BC$2:$BC$6,""))) | V88: =IF(S88="","",XLOOKUP(S88,$BA$2:$BA$6,$BD$2:$BD$6,"")) | AA88: =IF(Y88="","",IF(INT(TODAY()-Y88)<0,"⚠️ Data futura",INT(TODAY()-Y88))) | AB88: =IF(AA88="","",IF(Z88="",IF(AA88>14,"🔴 Atrasado",IF(AA88>7,"🟡 Atenção","🟢 Em dia")),IF(TODAY()>Z88,"🔴 Atrasado",IF(Z88-TODAY()<=3,"🟡 Atenção","🟢 Em dia")))) | AD88: =IF(OR(AC88="",H88=""),"",H88*AC88) | AF88: =IF(AC88>0,AC88,'⚙️ Config'!$B$10) -> 0.0075 | AG88: =H88*AF88 -> 60342.732 | AH88: =AG88*'⚙️ Config'!$B$11 -> 301713.66 | AI88: =AH88*'⚙️ Config'!$B$12 -> 90514.098
A89: 86 | B89: TURISCENTER TURISMO LTDA | C89: SP | D89: 68827435 | E89: 49.38 | F89: 🔴 ALTA | G89: R$ 5-10M | H89: 7995375.8 | I89: 1 | J89: 1.9 | K89: 2024 | L89: Receita da dívida ativa - IRRF | M89: 2024 | N89: COBRANCA | O89: =TEXT(D89,"00000000")&"0001" -> 688274350001 | P89: =IF(MOD(MID(O89,1,1)*5+MID(O89,2,1)*4+MID(O89,3,1)*3+MID(O89,4,1)*2+MID(O89,5,1)*9+MID(O89,6,1)*8+MID(O89,7,1)*7+MID(O89,8,1)*6+MID(O89,9,1)*5+MID(O89,10,1)*4+MID(O89,11,1)*3+MID(O89,12,1)*2,11)<2,0,11-MOD(MID(O89,1,1)*5+MID(O89,2,1)*4+MID(O89,3,1)*3+MID(O89,4,1)*2+MID(O89,5,1)*9+MID(O89,6,1)*8+MID(O89,7,1)*7+MID(O89,8,1)*6+MID(O89,9,1)*5+MID(O89,10,1)*4+MID(O89,11,1)*3+MID(O89,12,1)*2,11)) -> 4 | Q89: =IF(MOD(MID(O89,1,1)*6+MID(O89,2,1)*5+MID(O89,3,1)*4+MID(O89,4,1)*3+MID(O89,5,1)*2+MID(O89,6,1)*9+MID(O89,7,1)*8+MID(O89,8,1)*7+MID(O89,9,1)*6+MID(O89,10,1)*5+MID(O89,11,1)*4+MID(O89,12,1)*3+P89*2,11)<2,0,11-MOD(MID(O89,1,1)*6+MID(O89,2,1)*5+MID(O89,3,1)*4+MID(O89,4,1)*3+MID(O89,5,1)*2+MID(O89,6,1)*9+MID(O89,7,1)*8+MID(O89,8,1)*7+MID(O89,9,1)*6+MID(O89,10,1)*5+MID(O89,11,1)*4+MID(O89,12,1)*3+P89*2,11)) -> 8 | R89: =MID(O89,1,2)&"."&MID(O89,3,3)&"."&MID(O89,6,3)&"/"&MID(O89,9,4)&"-"&TEXT(P89,"0")&TEXT(Q89,"0") -> 68.827.435/0001-48 | T89: =IF(S89="","",IF(S89="Cadastrou","",XLOOKUP(S89,$BA$2:$BA$6,$BB$2:$BB$6,""))) | U89: =IF(S89="","",IF(S89="Cadastrou","",XLOOKUP(S89,$BA$2:$BA$6,$BC$2:$BC$6,""))) | V89: =IF(S89="","",XLOOKUP(S89,$BA$2:$BA$6,$BD$2:$BD$6,"")) | AA89: =IF(Y89="","",IF(INT(TODAY()-Y89)<0,"⚠️ Data futura",INT(TODAY()-Y89))) | AB89: =IF(AA89="","",IF(Z89="",IF(AA89>14,"🔴 Atrasado",IF(AA89>7,"🟡 Atenção","🟢 Em dia")),IF(TODAY()>Z89,"🔴 Atrasado",IF(Z89-TODAY()<=3,"🟡 Atenção","🟢 Em dia")))) | AD89: =IF(OR(AC89="",H89=""),"",H89*AC89) | AF89: =IF(AC89>0,AC89,'⚙️ Config'!$B$10) -> 0.0075 | AG89: =H89*AF89 -> 59965.319 | AH89: =AG89*'⚙️ Config'!$B$11 -> 299826.59 | AI89: =AH89*'⚙️ Config'!$B$12 -> 89947.978
A90: 87 | B90: LOGPORT LOGISTICA PORTUARIA LTDA | C90: SP | D90: 29443142 | E90: 56.88 | F90: 🔴 ALTA | G90: R$ 5-10M | H90: 7765007 | I90: 2 | J90: 1 | K90: 2025 | L90: Receita da dívida ativa - CSLL | Receita da dívida ativa - IRPJ | M90: 2025 | N90: COBRANCA | O90: =TEXT(D90,"00000000")&"0001" -> 294431420001 | P90: =IF(MOD(MID(O90,1,1)*5+MID(O90,2,1)*4+MID(O90,3,1)*3+MID(O90,4,1)*2+MID(O90,5,1)*9+MID(O90,6,1)*8+MID(O90,7,1)*7+MID(O90,8,1)*6+MID(O90,9,1)*5+MID(O90,10,1)*4+MID(O90,11,1)*3+MID(O90,12,1)*2,11)<2,0,11-MOD(MID(O90,1,1)*5+MID(O90,2,1)*4+MID(O90,3,1)*3+MID(O90,4,1)*2+MID(O90,5,1)*9+MID(O90,6,1)*8+MID(O90,7,1)*7+MID(O90,8,1)*6+MID(O90,9,1)*5+MID(O90,10,1)*4+MID(O90,11,1)*3+MID(O90,12,1)*2,11)) -> 0 | Q90: =IF(MOD(MID(O90,1,1)*6+MID(O90,2,1)*5+MID(O90,3,1)*4+MID(O90,4,1)*3+MID(O90,5,1)*2+MID(O90,6,1)*9+MID(O90,7,1)*8+MID(O90,8,1)*7+MID(O90,9,1)*6+MID(O90,10,1)*5+MID(O90,11,1)*4+MID(O90,12,1)*3+P90*2,11)<2,0,11-MOD(MID(O90,1,1)*6+MID(O90,2,1)*5+MID(O90,3,1)*4+MID(O90,4,1)*3+MID(O90,5,1)*2+MID(O90,6,1)*9+MID(O90,7,1)*8+MID(O90,8,1)*7+MID(O90,9,1)*6+MID(O90,10,1)*5+MID(O90,11,1)*4+MID(O90,12,1)*3+P90*2,11)) -> 5 | R90: =MID(O90,1,2)&"."&MID(O90,3,3)&"."&MID(O90,6,3)&"/"&MID(O90,9,4)&"-"&TEXT(P90,"0")&TEXT(Q90,"0") -> 29.443.142/0001-05 | T90: =IF(S90="","",IF(S90="Cadastrou","",XLOOKUP(S90,$BA$2:$BA$6,$BB$2:$BB$6,""))) | U90: =IF(S90="","",IF(S90="Cadastrou","",XLOOKUP(S90,$BA$2:$BA$6,$BC$2:$BC$6,""))) | V90: =IF(S90="","",XLOOKUP(S90,$BA$2:$BA$6,$BD$2:$BD$6,"")) | AA90: =IF(Y90="","",IF(INT(TODAY()-Y90)<0,"⚠️ Data futura",INT(TODAY()-Y90))) | AB90: =IF(AA90="","",IF(Z90="",IF(AA90>14,"🔴 Atrasado",IF(AA90>7,"🟡 Atenção","🟢 Em dia")),IF(TODAY()>Z90,"🔴 Atrasado",IF(Z90-TODAY()<=3,"🟡 Atenção","🟢 Em dia")))) | AD90: =IF(OR(AC90="",H90=""),"",H90*AC90) | AF90: =IF(AC90>0,AC90,'⚙️ Config'!$B$10) -> 0.0075 | AG90: =H90*AF90 -> 58237.552 | AH90: =AG90*'⚙️ Config'!$B$11 -> 291187.76 | AI90: =AH90*'⚙️ Config'!$B$12 -> 87356.328
A91: 88 | B91: FEREZIN GUINDASTES MONTAGENS E TRANSPORTES LTDA | C91: SP | D91: 02348094 | E91: 73.84 | F91: 🔴 ALTA | G91: R$ 5-10M | H91: 7758187.1 | I91: 2 | J91: 0.6 | K91: 2025 | L91: R D Ativa - Contribuição Empresa/Empregador | R D Ativa - Contribuição Risco Ambiental/Aposent Especial | M91: 2025 | N91: COBRANCA | O91: =TEXT(D91,"00000000")&"0001" -> 023480940001 | P91: =IF(MOD(MID(O91,1,1)*5+MID(O91,2,1)*4+MID(O91,3,1)*3+MID(O91,4,1)*2+MID(O91,5,1)*9+MID(O91,6,1)*8+MID(O91,7,1)*7+MID(O91,8,1)*6+MID(O91,9,1)*5+MID(O91,10,1)*4+MID(O91,11,1)*3+MID(O91,12,1)*2,11)<2,0,11-MOD(MID(O91,1,1)*5+MID(O91,2,1)*4+MID(O91,3,1)*3+MID(O91,4,1)*2+MID(O91,5,1)*9+MID(O91,6,1)*8+MID(O91,7,1)*7+MID(O91,8,1)*6+MID(O91,9,1)*5+MID(O91,10,1)*4+MID(O91,11,1)*3+MID(O91,12,1)*2,11)) -> 1 | Q91: =IF(MOD(MID(O91,1,1)*6+MID(O91,2,1)*5+MID(O91,3,1)*4+MID(O91,4,1)*3+MID(O91,5,1)*2+MID(O91,6,1)*9+MID(O91,7,1)*8+MID(O91,8,1)*7+MID(O91,9,1)*6+MID(O91,10,1)*5+MID(O91,11,1)*4+MID(O91,12,1)*3+P91*2,11)<2,0,11-MOD(MID(O91,1,1)*6+MID(O91,2,1)*5+MID(O91,3,1)*4+MID(O91,4,1)*3+MID(O91,5,1)*2+MID(O91,6,1)*9+MID(O91,7,1)*8+MID(O91,8,1)*7+MID(O91,9,1)*6+MID(O91,10,1)*5+MID(O91,11,1)*4+MID(O91,12,1)*3+P91*2,11)) -> 0 | R91: =MID(O91,1,2)&"."&MID(O91,3,3)&"."&MID(O91,6,3)&"/"&MID(O91,9,4)&"-"&TEXT(P91,"0")&TEXT(Q91,"0") -> 02.348.094/0001-10 | T91: =IF(S91="","",IF(S91="Cadastrou","",XLOOKUP(S91,$BA$2:$BA$6,$BB$2:$BB$6,""))) | U91: =IF(S91="","",IF(S91="Cadastrou","",XLOOKUP(S91,$BA$2:$BA$6,$BC$2:$BC$6,""))) | V91: =IF(S91="","",XLOOKUP(S91,$BA$2:$BA$6,$BD$2:$BD$6,"")) | AA91: =IF(Y91="","",IF(INT(TODAY()-Y91)<0,"⚠️ Data futura",INT(TODAY()-Y91))) | AB91: =IF(AA91="","",IF(Z91="",IF(AA91>14,"🔴 Atrasado",IF(AA91>7,"🟡 Atenção","🟢 Em dia")),IF(TODAY()>Z91,"🔴 Atrasado",IF(Z91-TODAY()<=3,"🟡 Atenção","🟢 Em dia")))) | AD91: =IF(OR(AC91="",H91=""),"",H91*AC91) | AF91: =IF(AC91>0,AC91,'⚙️ Config'!$B$10) -> 0.0075 | AG91: =H91*AF91 -> 58186.403 | AH91: =AG91*'⚙️ Config'!$B$11 -> 290932.02 | AI91: =AH91*'⚙️ Config'!$B$12 -> 87279.605
A92: 89 | B92: CASAGRANDE ARTIGOS RECREATIVOS E ESPORTIVOS LTDA | C92: SP | D92: 14914812 | E92: 53.54 | F92: 🔴 ALTA | G92: R$ 5-10M | H92: 7753251.2 | I92: 1 | J92: 1.6 | K92: 2024 | L92: IPI - Receita da dívida ativa | M92: 2024 | N92: AJUIZADA_SEM_GAR | O92: =TEXT(D92,"00000000")&"0001" -> 149148120001 | P92: =IF(MOD(MID(O92,1,1)*5+MID(O92,2,1)*4+MID(O92,3,1)*3+MID(O92,4,1)*2+MID(O92,5,1)*9+MID(O92,6,1)*8+MID(O92,7,1)*7+MID(O92,8,1)*6+MID(O92,9,1)*5+MID(O92,10,1)*4+MID(O92,11,1)*3+MID(O92,12,1)*2,11)<2,0,11-MOD(MID(O92,1,1)*5+MID(O92,2,1)*4+MID(O92,3,1)*3+MID(O92,4,1)*2+MID(O92,5,1)*9+MID(O92,6,1)*8+MID(O92,7,1)*7+MID(O92,8,1)*6+MID(O92,9,1)*5+MID(O92,10,1)*4+MID(O92,11,1)*3+MID(O92,12,1)*2,11)) -> 5 | Q92: =IF(MOD(MID(O92,1,1)*6+MID(O92,2,1)*5+MID(O92,3,1)*4+MID(O92,4,1)*3+MID(O92,5,1)*2+MID(O92,6,1)*9+MID(O92,7,1)*8+MID(O92,8,1)*7+MID(O92,9,1)*6+MID(O92,10,1)*5+MID(O92,11,1)*4+MID(O92,12,1)*3+P92*2,11)<2,0,11-MOD(MID(O92,1,1)*6+MID(O92,2,1)*5+MID(O92,3,1)*4+MID(O92,4,1)*3+MID(O92,5,1)*2+MID(O92,6,1)*9+MID(O92,7,1)*8+MID(O92,8,1)*7+MID(O92,9,1)*6+MID(O92,10,1)*5+MID(O92,11,1)*4+MID(O92,12,1)*3+P92*2,11)) -> 7 | R92: =MID(O92,1,2)&"."&MID(O92,3,3)&"."&MID(O92,6,3)&"/"&MID(O92,9,4)&"-"&TEXT(P92,"0")&TEXT(Q92,"0") -> 14.914.812/0001-57 | T92: =IF(S92="","",IF(S92="Cadastrou","",XLOOKUP(S92,$BA$2:$BA$6,$BB$2:$BB$6,""))) | U92: =IF(S92="","",IF(S92="Cadastrou","",XLOOKUP(S92,$BA$2:$BA$6,$BC$2:$BC$6,""))) | V92: =IF(S92="","",XLOOKUP(S92,$BA$2:$BA$6,$BD$2:$BD$6,"")) | AA92: =IF(Y92="","",IF(INT(TODAY()-Y92)<0,"⚠️ Data futura",INT(TODAY()-Y92))) | AB92: =IF(AA92="","",IF(Z92="",IF(AA92>14,"🔴 Atrasado",IF(AA92>7,"🟡 Atenção","🟢 Em dia")),IF(TODAY()>Z92,"🔴 Atrasado",IF(Z92-TODAY()<=3,"🟡 Atenção","🟢 Em dia")))) | AD92: =IF(OR(AC92="",H92=""),"",H92*AC92) | AF92: =IF(AC92>0,AC92,'⚙️ Config'!$B$10) -> 0.0075 | AG92: =H92*AF92 -> 58149.384 | AH92: =AG92*'⚙️ Config'!$B$11 -> 290746.92 | AI92: =AH92*'⚙️ Config'!$B$12 -> 87224.075
A93: 90 | B93: RN EXPRESS E COURIER DO BRASIL LTDA | C93: SP | D93: 03243739 | E93: 42.03 | F93: 🔴 ALTA | G93: R$ 5-10M | H93: 7730371.8 | I93: 2 | J93: 1.7 | K93: 2024 | L93: Receita da dívida ativa - PIS | Receita da dívida ativa - COFINS | M93: 2024 | N93: AJUIZADA_SEM_GAR | O93: =TEXT(D93,"00000000")&"0001" -> 032437390001 | P93: =IF(MOD(MID(O93,1,1)*5+MID(O93,2,1)*4+MID(O93,3,1)*3+MID(O93,4,1)*2+MID(O93,5,1)*9+MID(O93,6,1)*8+MID(O93,7,1)*7+MID(O93,8,1)*6+MID(O93,9,1)*5+MID(O93,10,1)*4+MID(O93,11,1)*3+MID(O93,12,1)*2,11)<2,0,11-MOD(MID(O93,1,1)*5+MID(O93,2,1)*4+MID(O93,3,1)*3+MID(O93,4,1)*2+MID(O93,5,1)*9+MID(O93,6,1)*8+MID(O93,7,1)*7+MID(O93,8,1)*6+MID(O93,9,1)*5+MID(O93,10,1)*4+MID(O93,11,1)*3+MID(O93,12,1)*2,11)) -> 1 | Q93: =IF(MOD(MID(O93,1,1)*6+MID(O93,2,1)*5+MID(O93,3,1)*4+MID(O93,4,1)*3+MID(O93,5,1)*2+MID(O93,6,1)*9+MID(O93,7,1)*8+MID(O93,8,1)*7+MID(O93,9,1)*6+MID(O93,10,1)*5+MID(O93,11,1)*4+MID(O93,12,1)*3+P93*2,11)<2,0,11-MOD(MID(O93,1,1)*6+MID(O93,2,1)*5+MID(O93,3,1)*4+MID(O93,4,1)*3+MID(O93,5,1)*2+MID(O93,6,1)*9+MID(O93,7,1)*8+MID(O93,8,1)*7+MID(O93,9,1)*6+MID(O93,10,1)*5+MID(O93,11,1)*4+MID(O93,12,1)*3+P93*2,11)) -> 2 | R93: =MID(O93,1,2)&"."&MID(O93,3,3)&"."&MID(O93,6,3)&"/"&MID(O93,9,4)&"-"&TEXT(P93,"0")&TEXT(Q93,"0") -> 03.243.739/0001-12 | T93: =IF(S93="","",IF(S93="Cadastrou","",XLOOKUP(S93,$BA$2:$BA$6,$BB$2:$BB$6,""))) | U93: =IF(S93="","",IF(S93="Cadastrou","",XLOOKUP(S93,$BA$2:$BA$6,$BC$2:$BC$6,""))) | V93: =IF(S93="","",XLOOKUP(S93,$BA$2:$BA$6,$BD$2:$BD$6,"")) | AA93: =IF(Y93="","",IF(INT(TODAY()-Y93)<0,"⚠️ Data futura",INT(TODAY()-Y93))) | AB93: =IF(AA93="","",IF(Z93="",IF(AA93>14,"🔴 Atrasado",IF(AA93>7,"🟡 Atenção","🟢 Em dia")),IF(TODAY()>Z93,"🔴 Atrasado",IF(Z93-TODAY()<=3,"🟡 Atenção","🟢 Em dia")))) | AD93: =IF(OR(AC93="",H93=""),"",H93*AC93) | AF93: =IF(AC93>0,AC93,'⚙️ Config'!$B$10) -> 0.0075 | AG93: =H93*AF93 -> 57977.789 | AH93: =AG93*'⚙️ Config'!$B$11 -> 289888.94 | AI93: =AH93*'⚙️ Config'!$B$12 -> 86966.683
A94: 91 | B94: TIOSERTEC COMERCIO E TRANSPORTE DE PRODUTOS LTDA. | C94: SP | D94: 03120135 | E94: 49.37 | F94: 🔴 ALTA | G94: R$ 5-10M | H94: 7565378.7 | I94: 1 | J94: 1.9 | K94: 2024 | L94: Receita da dívida ativa - IRRF | M94: 2024 | N94: COBRANCA | O94: =TEXT(D94,"00000000")&"0001" -> 031201350001 | P94: =IF(MOD(MID(O94,1,1)*5+MID(O94,2,1)*4+MID(O94,3,1)*3+MID(O94,4,1)*2+MID(O94,5,1)*9+MID(O94,6,1)*8+MID(O94,7,1)*7+MID(O94,8,1)*6+MID(O94,9,1)*5+MID(O94,10,1)*4+MID(O94,11,1)*3+MID(O94,12,1)*2,11)<2,0,11-MOD(MID(O94,1,1)*5+MID(O94,2,1)*4+MID(O94,3,1)*3+MID(O94,4,1)*2+MID(O94,5,1)*9+MID(O94,6,1)*8+MID(O94,7,1)*7+MID(O94,8,1)*6+MID(O94,9,1)*5+MID(O94,10,1)*4+MID(O94,11,1)*3+MID(O94,12,1)*2,11)) -> 8 | Q94: =IF(MOD(MID(O94,1,1)*6+MID(O94,2,1)*5+MID(O94,3,1)*4+MID(O94,4,1)*3+MID(O94,5,1)*2+MID(O94,6,1)*9+MID(O94,7,1)*8+MID(O94,8,1)*7+MID(O94,9,1)*6+MID(O94,10,1)*5+MID(O94,11,1)*4+MID(O94,12,1)*3+P94*2,11)<2,0,11-MOD(MID(O94,1,1)*6+MID(O94,2,1)*5+MID(O94,3,1)*4+MID(O94,4,1)*3+MID(O94,5,1)*2+MID(O94,6,1)*9+MID(O94,7,1)*8+MID(O94,8,1)*7+MID(O94,9,1)*6+MID(O94,10,1)*5+MID(O94,11,1)*4+MID(O94,12,1)*3+P94*2,11)) -> 9 | R94: =MID(O94,1,2)&"."&MID(O94,3,3)&"."&MID(O94,6,3)&"/"&MID(O94,9,4)&"-"&TEXT(P94,"0")&TEXT(Q94,"0") -> 03.120.135/0001-89 | T94: =IF(S94="","",IF(S94="Cadastrou","",XLOOKUP(S94,$BA$2:$BA$6,$BB$2:$BB$6,""))) | U94: =IF(S94="","",IF(S94="Cadastrou","",XLOOKUP(S94,$BA$2:$BA$6,$BC$2:$BC$6,""))) | V94: =IF(S94="","",XLOOKUP(S94,$BA$2:$BA$6,$BD$2:$BD$6,"")) | AA94: =IF(Y94="","",IF(INT(TODAY()-Y94)<0,"⚠️ Data futura",INT(TODAY()-Y94))) | AB94: =IF(AA94="","",IF(Z94="",IF(AA94>14,"🔴 Atrasado",IF(AA94>7,"🟡 Atenção","🟢 Em dia")),IF(TODAY()>Z94,"🔴 Atrasado",IF(Z94-TODAY()<=3,"🟡 Atenção","🟢 Em dia")))) | AD94: =IF(OR(AC94="",H94=""),"",H94*AC94) | AF94: =IF(AC94>0,AC94,'⚙️ Config'!$B$10) -> 0.0075 | AG94: =H94*AF94 -> 56740.34 | AH94: =AG94*'⚙️ Config'!$B$11 -> 283701.7 | AI94: =AH94*'⚙️ Config'!$B$12 -> 85110.51
A95: 92 | B95: ANSHUN COMERCIO DE ELETRONICOS LTDA | C95: SP | D95: 15830406 | E95: 48.2 | F95: 🔴 ALTA | G95: R$ 5-10M | H95: 7555024.9 | I95: 1 | J95: 2 | K95: 2024 | L95: Receita da dívida ativa - IRRF | M95: 2024 | N95: AJUIZADA_SEM_GAR | O95: =TEXT(D95,"00000000")&"0001" -> 158304060001 | P95: =IF(MOD(MID(O95,1,1)*5+MID(O95,2,1)*4+MID(O95,3,1)*3+MID(O95,4,1)*2+MID(O95,5,1)*9+MID(O95,6,1)*8+MID(O95,7,1)*7+MID(O95,8,1)*6+MID(O95,9,1)*5+MID(O95,10,1)*4+MID(O95,11,1)*3+MID(O95,12,1)*2,11)<2,0,11-MOD(MID(O95,1,1)*5+MID(O95,2,1)*4+MID(O95,3,1)*3+MID(O95,4,1)*2+MID(O95,5,1)*9+MID(O95,6,1)*8+MID(O95,7,1)*7+MID(O95,8,1)*6+MID(O95,9,1)*5+MID(O95,10,1)*4+MID(O95,11,1)*3+MID(O95,12,1)*2,11)) -> 7 | Q95: =IF(MOD(MID(O95,1,1)*6+MID(O95,2,1)*5+MID(O95,3,1)*4+MID(O95,4,1)*3+MID(O95,5,1)*2+MID(O95,6,1)*9+MID(O95,7,1)*8+MID(O95,8,1)*7+MID(O95,9,1)*6+MID(O95,10,1)*5+MID(O95,11,1)*4+MID(O95,12,1)*3+P95*2,11)<2,0,11-MOD(MID(O95,1,1)*6+MID(O95,2,1)*5+MID(O95,3,1)*4+MID(O95,4,1)*3+MID(O95,5,1)*2+MID(O95,6,1)*9+MID(O95,7,1)*8+MID(O95,8,1)*7+MID(O95,9,1)*6+MID(O95,10,1)*5+MID(O95,11,1)*4+MID(O95,12,1)*3+P95*2,11)) -> 9 | R95: =MID(O95,1,2)&"."&MID(O95,3,3)&"."&MID(O95,6,3)&"/"&MID(O95,9,4)&"-"&TEXT(P95,"0")&TEXT(Q95,"0") -> 15.830.406/0001-79 | T95: =IF(S95="","",IF(S95="Cadastrou","",XLOOKUP(S95,$BA$2:$BA$6,$BB$2:$BB$6,""))) | U95: =IF(S95="","",IF(S95="Cadastrou","",XLOOKUP(S95,$BA$2:$BA$6,$BC$2:$BC$6,""))) | V95: =IF(S95="","",XLOOKUP(S95,$BA$2:$BA$6,$BD$2:$BD$6,"")) | AA95: =IF(Y95="","",IF(INT(TODAY()-Y95)<0,"⚠️ Data futura",INT(TODAY()-Y95))) | AB95: =IF(AA95="","",IF(Z95="",IF(AA95>14,"🔴 Atrasado",IF(AA95>7,"🟡 Atenção","🟢 Em dia")),IF(TODAY()>Z95,"🔴 Atrasado",IF(Z95-TODAY()<=3,"🟡 Atenção","🟢 Em dia")))) | AD95: =IF(OR(AC95="",H95=""),"",H95*AC95) | AF95: =IF(AC95>0,AC95,'⚙️ Config'!$B$10) -> 0.0075 | AG95: =H95*AF95 -> 56662.686 | AH95: =AG95*'⚙️ Config'!$B$11 -> 283313.43 | AI95: =AH95*'⚙️ Config'!$B$12 -> 84994.03
A96: 93 | B96: LUPE CONSULTORIA E ASSESSORIA LTDA | C96: SP | D96: 59710582 | E96: 83.84 | F96: 🔴 ALTA | G96: R$ 5-10M | H96: 7418702.7 | I96: 1 | J96: 0.6 | K96: 2025 | L96: Receita Dívida Ativa - Multa Não Tributária - RFB | M96: 2025 | N96: COBRANCA | O96: =TEXT(D96,"00000000")&"0001" -> 597105820001 | P96: =IF(MOD(MID(O96,1,1)*5+MID(O96,2,1)*4+MID(O96,3,1)*3+MID(O96,4,1)*2+MID(O96,5,1)*9+MID(O96,6,1)*8+MID(O96,7,1)*7+MID(O96,8,1)*6+MID(O96,9,1)*5+MID(O96,10,1)*4+MID(O96,11,1)*3+MID(O96,12,1)*2,11)<2,0,11-MOD(MID(O96,1,1)*5+MID(O96,2,1)*4+MID(O96,3,1)*3+MID(O96,4,1)*2+MID(O96,5,1)*9+MID(O96,6,1)*8+MID(O96,7,1)*7+MID(O96,8,1)*6+MID(O96,9,1)*5+MID(O96,10,1)*4+MID(O96,11,1)*3+MID(O96,12,1)*2,11)) -> 4 | Q96: =IF(MOD(MID(O96,1,1)*6+MID(O96,2,1)*5+MID(O96,3,1)*4+MID(O96,4,1)*3+MID(O96,5,1)*2+MID(O96,6,1)*9+MID(O96,7,1)*8+MID(O96,8,1)*7+MID(O96,9,1)*6+MID(O96,10,1)*5+MID(O96,11,1)*4+MID(O96,12,1)*3+P96*2,11)<2,0,11-MOD(MID(O96,1,1)*6+MID(O96,2,1)*5+MID(O96,3,1)*4+MID(O96,4,1)*3+MID(O96,5,1)*2+MID(O96,6,1)*9+MID(O96,7,1)*8+MID(O96,8,1)*7+MID(O96,9,1)*6+MID(O96,10,1)*5+MID(O96,11,1)*4+MID(O96,12,1)*3+P96*2,11)) -> 2 | R96: =MID(O96,1,2)&"."&MID(O96,3,3)&"."&MID(O96,6,3)&"/"&MID(O96,9,4)&"-"&TEXT(P96,"0")&TEXT(Q96,"0") -> 59.710.582/0001-42 | T96: =IF(S96="","",IF(S96="Cadastrou","",XLOOKUP(S96,$BA$2:$BA$6,$BB$2:$BB$6,""))) | U96: =IF(S96="","",IF(S96="Cadastrou","",XLOOKUP(S96,$BA$2:$BA$6,$BC$2:$BC$6,""))) | V96: =IF(S96="","",XLOOKUP(S96,$BA$2:$BA$6,$BD$2:$BD$6,"")) | AA96: =IF(Y96="","",IF(INT(TODAY()-Y96)<0,"⚠️ Data futura",INT(TODAY()-Y96))) | AB96: =IF(AA96="","",IF(Z96="",IF(AA96>14,"🔴 Atrasado",IF(AA96>7,"🟡 Atenção","🟢 Em dia")),IF(TODAY()>Z96,"🔴 Atrasado",IF(Z96-TODAY()<=3,"🟡 Atenção","🟢 Em dia")))) | AD96: =IF(OR(AC96="",H96=""),"",H96*AC96) | AF96: =IF(AC96>0,AC96,'⚙️ Config'!$B$10) -> 0.0075 | AG96: =H96*AF96 -> 55640.27 | AH96: =AG96*'⚙️ Config'!$B$11 -> 278201.35 | AI96: =AH96*'⚙️ Config'!$B$12 -> 83460.406
A97: 94 | B97: DROGAVIDA COMERCIAL DE DROGAS LTDA. | C97: SP | D97: 55992358 | E97: 39.35 | F97: 🔴 ALTA | G97: R$ 5-10M | H97: 6954934.2 | I97: 2 | J97: 1.9 | K97: 2024 | L97: Receita da dívida ativa - PIS | Receita da dívida ativa - COFINS | M97: 2024 | N97: AJUIZADA_SEM_GAR | O97: =TEXT(D97,"00000000")&"0001" -> 559923580001 | P97: =IF(MOD(MID(O97,1,1)*5+MID(O97,2,1)*4+MID(O97,3,1)*3+MID(O97,4,1)*2+MID(O97,5,1)*9+MID(O97,6,1)*8+MID(O97,7,1)*7+MID(O97,8,1)*6+MID(O97,9,1)*5+MID(O97,10,1)*4+MID(O97,11,1)*3+MID(O97,12,1)*2,11)<2,0,11-MOD(MID(O97,1,1)*5+MID(O97,2,1)*4+MID(O97,3,1)*3+MID(O97,4,1)*2+MID(O97,5,1)*9+MID(O97,6,1)*8+MID(O97,7,1)*7+MID(O97,8,1)*6+MID(O97,9,1)*5+MID(O97,10,1)*4+MID(O97,11,1)*3+MID(O97,12,1)*2,11)) -> 3 | Q97: =IF(MOD(MID(O97,1,1)*6+MID(O97,2,1)*5+MID(O97,3,1)*4+MID(O97,4,1)*3+MID(O97,5,1)*2+MID(O97,6,1)*9+MID(O97,7,1)*8+MID(O97,8,1)*7+MID(O97,9,1)*6+MID(O97,10,1)*5+MID(O97,11,1)*4+MID(O97,12,1)*3+P97*2,11)<2,0,11-MOD(MID(O97,1,1)*6+MID(O97,2,1)*5+MID(O97,3,1)*4+MID(O97,4,1)*3+MID(O97,5,1)*2+MID(O97,6,1)*9+MID(O97,7,1)*8+MID(O97,8,1)*7+MID(O97,9,1)*6+MID(O97,10,1)*5+MID(O97,11,1)*4+MID(O97,12,1)*3+P97*2,11)) -> 0 | R97: =MID(O97,1,2)&"."&MID(O97,3,3)&"."&MID(O97,6,3)&"/"&MID(O97,9,4)&"-"&TEXT(P97,"0")&TEXT(Q97,"0") -> 55.992.358/0001-30 | T97: =IF(S97="","",IF(S97="Cadastrou","",XLOOKUP(S97,$BA$2:$BA$6,$BB$2:$BB$6,""))) | U97: =IF(S97="","",IF(S97="Cadastrou","",XLOOKUP(S97,$BA$2:$BA$6,$BC$2:$BC$6,""))) | V97: =IF(S97="","",XLOOKUP(S97,$BA$2:$BA$6,$BD$2:$BD$6,"")) | AA97: =IF(Y97="","",IF(INT(TODAY()-Y97)<0,"⚠️ Data futura",INT(TODAY()-Y97))) | AB97: =IF(AA97="","",IF(Z97="",IF(AA97>14,"🔴 Atrasado",IF(AA97>7,"🟡 Atenção","🟢 Em dia")),IF(TODAY()>Z97,"🔴 Atrasado",IF(Z97-TODAY()<=3,"🟡 Atenção","🟢 Em dia")))) | AD97: =IF(OR(AC97="",H97=""),"",H97*AC97) | AF97: =IF(AC97>0,AC97,'⚙️ Config'!$B$10) -> 0.0075 | AG97: =H97*AF97 -> 52162.006 | AH97: =AG97*'⚙️ Config'!$B$11 -> 260810.03 | AI97: =AH97*'⚙️ Config'!$B$12 -> 78243.01
